Workbook

Sheet PIC_API_SUITE
A1: TestCaseName | B1: EndPoint | C1: Method | D1: Payload | E1: ExpectedStatusCode | F1: Expected Response | G1: Extracted Key
A2: =CONCATENATE("TC_",'API Test Inputs'!A2,"_",'API Test Inputs'!B2,"_Description:",'API Test Inputs'!E2,"_Tester:",'API Test Inputs'!C2) -> TC_1_AI_Chat_Description:verifyCreateConversation_Tester:Alok Kumar | B2: ='API Test Inputs'!D2 -> /genai/graphql | C2: ='API Test Inputs'!F2 -> POST | D2: ='API Test Inputs'!G2 -> {"query":"mutation MyMutation {\n create_conversation(\n inputs: {scope_id: \"04b7fc60-63bd-44d7-bcbf-09d1476fa0aa\", conversation_name: \"Created Conv by Automation\", conversation_id: \"{conversation_id}\", created_timestamp: \"{current_timeStamp}\", owned_by_user_id: 50395262, shared_by_user_id : 50395262}\n ) {\n data {\n conversation_id\n conv_own_emp_id\n conversation_name\n created_timestamp\n last_msg_timestamp\n scope_id\n shared_by_user_id\n }\n message\n status\n }\n}"} | E2: ='API Test Inputs'!H2 -> 200 | F2: ='API Test Inputs'!I2 -> {"data":{"create_conversation":{"data":[{"conversation_id":"{conversation_id}","conv_own_emp_id":50395262,"conversation_name":"Created Conv by Automation","scope_id":"04b7fc60-63bd-44d7-bcbf-09d1476fa0aa","shared_by_user_id":50395262}],"message":"Conversation created successfully","status":"Created"}}} | G2: conversation_id
A3: =CONCATENATE("TC_",'API Test Inputs'!A3,"_",'API Test Inputs'!B3,"_Description:",'API Test Inputs'!E3,"_Tester:",'API Test Inputs'!C3) -> TC_2_AI_Chat_Description:verifyCreateMessage_Tester:Alok Kumar | B3: ='API Test Inputs'!D3 -> /genai/graphql | C3: ='API Test Inputs'!F3 -> POST | D3: ='API Test Inputs'!G3 -> {"query":"mutation MyMutation { create_message( input: {prompt: \"{\\\"task\\\": \\\"\\\", \\\"scope\\\": \\\"\\\", \\\"context\\\": \\\"\\\", \\\"user_text\\\": \\\"What is PIC?\\\", \\\"custom_instruction\\\": \\\"\\\"}\", response: \"{\\\"long_response\\\": {\\\"graph\\\": [], \\\"table\\\": []}, \\\"short_response\\\": \\\"## Predictive Insights Center (PIC)\\\\n\\\\nThe **Predictive Insights Center (PIC)** is a strategic initiative driving Takeda's digital transformation through:\\\\n\\\\n- **Centralized Data Platform**: Unifies data from GMS/GQ systems into one source\\\\n- **AI Integration**: Provides automated, AI-driven prescriptive analytics\\\\n- **Cross-Functional Collaboration**: Bridges data silos between teams and departments\\\\n- **Decision Support**: Enables proactive, predictive decision-making\\\\n\\\\n### Key Features:\\\\n- Replaces fragmented tools with integrated digital solutions\\\\n- Facilitates end-to-end process orchestration\\\\n- Embeds AI for advanced predictive analytics\\\\n- Aims for faster, smarter operational decisions\\\\n\\\\n*Vision 2030 Goal*: Establish a single-source-of-truth environment for enterprise-wide insights.\\\", \\\"reasoning_response\\\": \\\"\\\"}\", prompt_datetime: \"{current_timeStamp}\", response_datetime: \"{current_timeStamp}\", prompt_emp_id: 50395262, conversation_id: \"{conversation_id}\", task_id: \"cc5f121d-f478-4f83-a88e-f092ae29e921\"} ) { message status data { message_id prompt response task_id user_rating conversation_id } }}"} | E3: ='API Test Inputs'!H3 -> 200 | F3: ='API Test Inputs'!I3 -> {"data":{"create_message":{"message":"Message created successfully","status":"Created","data":[{"message_id":"{message_id}","prompt":{"task":"","scope":"","context":"","user_text":"What is PIC?","custom_instruction":""},"response":{"long_response":{"graph":[],"table":[]},"reasoning_response":""},"task_id":"cc5f121d-f478-4f83-a88e-f092ae29e921","conversation_id":"{conversation_id}"}]}}} | G3: message_id
A4: =CONCATENATE("TC_",'API Test Inputs'!A4,"_",'API Test Inputs'!B4,"_Description:",'API Test Inputs'!E4,"_Tester:",'API Test Inputs'!C4) -> TC_3_AI_Chat_Description:verifyFetchConversation_Tester:Alok Kumar | B4: ='API Test Inputs'!D4 -> /genai/graphql | C4: ='API Test Inputs'!F4 -> POST | D4: ='API Test Inputs'!G4 -> {"operationName":"GetConversationName","variables":{},"query":"query GetConversationName {\n fetch_conversations(\n conversation_ids: \"{conversation_id}\"\n for_current_user: true\n scope_id: \"04b7fc60-63bd-44d7-bcbf-09d1476fa0aa\"\n ) {\n conversations {\n conversation_id\n conversation_name\n __typename\n }\n __typename\n }\n}"} | E4: ='API Test Inputs'!H4 -> 200 | F4: ='API Test Inputs'!I4 -> {"data":{"fetch_conversations":{"conversations":[{"conversation_id":"{conversation_id}","__typename":"Conversation"}],"__typename":"PaginatedConversations"}}}
A5: =CONCATENATE("TC_",'API Test Inputs'!A5,"_",'API Test Inputs'!B5,"_Description:",'API Test Inputs'!E5,"_Tester:",'API Test Inputs'!C5) -> TC_4_AI_Chat_Description:verifyFetchMessage_Tester:Alok Kumar | B5: ='API Test Inputs'!D5 -> /genai/graphql | C5: ='API Test Inputs'!F5 -> POST | D5: ='API Test Inputs'!G5 -> {"operationName":"UserGroupMemberId","variables":{},"query":"query UserGroupMemberId {\n fetch_messages(\n conversation_ids: [\"{conversation_id}\"]\n for_current_user: true\n task_id: \"cc5f121d-f478-4f83-a88e-f092ae29e921\"\n ) {\n messages {\n message_id\n conversation_id\n prompt\n prompt_created_ts\n response\n response_created_ts\n src_type\n user_rating\n prompted_by_emp_id\n gen_ai_audit\n task_id\n __typename\n }\n page_info {\n has_next_page\n has_previous_page\n start_cursor\n end_cursor\n __typename\n }\n __typename\n }\n}"} | E5: ='API Test Inputs'!H5 -> 200 | F5: ='API Test Inputs'!I5 -> {"data":{"fetch_messages":{"messages":[{"message_id":"{message_id}","conversation_id":"{conversation_id}","prompt":{"task":"","scope":"","context":"","user_text":"What is PIC?","custom_instruction":""},"response":{"long_response":{"graph":[],"table":[]},"reasoning_response":""},"src_type":"GEN_AI","prompted_by_emp_id":"50395262","task_id":"cc5f121d-f478-4f83-a88e-f092ae29e921"}],"page_info":{"has_next_page":false,"has_previous_page":false}}}}
A6: =CONCATENATE("TC_",'API Test Inputs'!A6,"_",'API Test Inputs'!B6,"_Description:",'API Test Inputs'!E6,"_Tester:",'API Test Inputs'!C6) -> TC_5_AI_Chat_Description:verifyUpdateConversation_Tester:Alok Kumar | B6: ='API Test Inputs'!D6 -> /genai/graphql | C6: ='API Test Inputs'!F6 -> POST | D6: ='API Test Inputs'!G6 -> {"operationName":"UpdateConversation","variables":{},"query":"mutation UpdateConversation {\n update_conversation(\n inputs: {scope_id: \"04b7fc60-63bd-44d7-bcbf-09d1476fa0aa\", conversation_name: \"Updated Conv by Automation\", conversation_id: \"{conversation_id}\"}\n ) {\n message\n status\n __typename\n }\n}"} | E6: ='API Test Inputs'!H6 -> 200 | F6: ='API Test Inputs'!I6 -> {"data":{"update_conversation":{"message":"Conversation updated successfully","status":"Updated","__typename":"ConversationResponse"}}}
A7: =CONCATENATE("TC_",'API Test Inputs'!A7,"_",'API Test Inputs'!B7,"_Description:",'API Test Inputs'!E7,"_Tester:",'API Test Inputs'!C7) -> TC_6_AI_Chat_Description:verifyUpdateMessage_Tester:Alok Kumar | B7: ='API Test Inputs'!D7 -> /genai/graphql | C7: ='API Test Inputs'!F7 -> POST | D7: ='API Test Inputs'!G7 -> {"operationName":"MyMutation","variables":{},"query":"mutation MyMutation {\n update_message(\n input: {message_id: \"{message_id}\", user_rating: 3}\n ) {\n data {\n conversation_id\n user_rating\n message_id\n task_id\n __typename\n }\n message\n status\n __typename\n }\n}"} | E7: ='API Test Inputs'!H7 -> 200 | F7: ='API Test Inputs'!I7 -> {"data":{"update_message":{"data":[{"conversation_id":"{conversation_id}","user_rating":3,"message_id":"{message_id}","task_id":"cc5f121d-f478-4f83-a88e-f092ae29e921","__typename":"MessageResponse"}],"message":"Message updated successfully","status":"Updated","__typename":"StandardResponse"}}}

Sheet NMT
A1: TestCaseName | B1: EndPoint | C1: Method | D1: Payload | E1: ExpectedStatusCode | F1: Expected Response | G1: Extracted Key
A2: TC_CreateScenario | B2: /nmt/api/v1/nmt/scenarios/ | C2: POST | D2: { "no_advance_calculation": false, "scenario_name": "Test-API-Automation", "scenario_description": "test", "users": [], "access_level": "private", "forecast_version": "2026-JAN", "start_date": "2026-JAN", "end_date": "2026-DEC", "flows": [ { "nodes": [ { "site_id": "3623", "description": "3623 - MFCT Lessines, Lessines (MFCT)" }, { "site_id": "7807", "description": "7807 - LOC Canada, Halton Hills (LOC)" } ], "index": "PLASMA:5500736 - CUVITRU,10G,CA:Canada:Cold:NO:B2B:3623|7807", "routed_nodes": [ "3623", "7807" ], "market_iso2": "CA", "trade_name": "CUVITRU", "operating_unit": "PLASMA", "temperature_range": "Cold", "controlled_drugs": "NO", "plm_status": "B2B", "sku_description": "5500736-CUVITRU,10G,CA", "country_description": "Canada", "gross_weight": 147, "quantity_per_pal": 1600, "material_text": "CUVITRU,10G,CA", "customer_code_in_ibp": "D_CA HM_DI_3032", "finance_country_code": "CA", "unit_of_measure": "PC", "material_type": "S - Finished Goods", "weight_unit": "G", "material_clean": "5500736", "temperature_detailed": "+2°C to +8°C", "distrib_sites": "3623|7807", "quantity_demand": [ { "lane_id": "3623_7807", "volume": 69049 } ], "quantity_supply": [ { "lane_id": "3623_7807", "volume": 77470.70031738281 } ], "flow_type": "Scope", "flow_key": 5225, "tariff_details": [ { "lane_id": "3623_7807", "country_code": "BE", "tariff_code": "3002150000", "unit_price": null, "currency": null, "total_price": 0, "tariff_rate_pct": 0, "tariff_rate_annex_1": null, "tariff_rate_annex_2": null, "tariff_duty": 0, "volume": 77470.70031738281 } ] }, { "nodes": [ { "site_id": "1501", "description": "1501 - MFCT Bray, Bray (MFCT)" }, { "site_id": "3801", "description": "3801 - RDC Germany Arvato, Harsewinkel (RDC)" }, { "site_id": "SA", "description": "Saudi arabia Wholes./Cust." } ], "index": "SM&O:6522110 - Fruzaqla 1mg 21ct Bottle KSA:Saudi Arabia:Ambient:NO:B2B:1501|3801|SA", "routed_nodes": [ "1501", "3801", "SA" ], "market_iso2": "SA", "trade_name": "FRUZAQLA", "operating_unit": "SM&O", "temperature_range": "Ambient", "controlled_drugs": "NO", "plm_status": "B2B", "sku_description": "6522110-Fruzaqla 1mg 21ct Bottle KSA", "country_description": "Saudi Arabia", "gross_weight": 41, "quantity_per_pal": 1200, "material_text": "Fruzaqla 1mg 21ct Bottle KSA", "customer_code_in_ibp": "D_SA OP_EP_1380", "finance_country_code": "SA", "unit_of_measure": "PC", "material_type": "S - Finished Goods", "weight_unit": "G", "material_clean": "6522110", "temperature_detailed": "+15°C to +25°C", "distrib_sites": "1501|3801|SA", "quantity_demand": [ { "lane_id": "1501_3801", "volume": 30 }, { "lane_id": "3801_SA", "volume": 30 } ], "quantity_supply": [ { "lane_id": "1501_3801", "volume": 48 }, { "lane_id": "3801_SA", "volume": 30 } ], "flow_type": "Scope", "flow_key": 11, "tariff_details": [ { "lane_id": "1501_3801", "country_code": null, "tariff_code": "30049000", "unit_price": 0, "currency": "EUR", "total_price": 0, "tariff_rate_pct": null, "tariff_rate_annex_1": null, "tariff_rate_annex_2": null, "tariff_duty": 0, "volume": 48 } ] }, { "nodes": [ { "site_id": "3623", "description": "3623 - MFCT Lessines, Lessines (MFCT)" }, { "site_id": "350", "description": "350 - LOC Switzerland, Niederbipp (LOC)" } ], "index": "PLASMA:1800223 - IG Infusion 10%, 20G - Clinical Studies:Switzerland:Cold:NO:CLINICAL:3623|350", "routed_nodes": [ "3623", "350" ], "market_iso2": "CH", "trade_name": "GAMMAGARD KIOVIG LIQUID", "operating_unit": "PLASMA", "temperature_range": "Cold", "controlled_drugs": "NO", "plm_status": "CLINICAL", "sku_description": "1800223-IG Infusion 10%, 20G - Clinical Studies", "country_description": "Switzerland", "gross_weight": 368, "quantity_per_pal": 600, "material_text": "IG Infusion 10%, 20G - Clinical Studies", "customer_code_in_ibp": "D_CH OP_EP_8036", "finance_country_code": "CH", "unit_of_measure": "PC", "material_type": "S - Finished Goods", "weight_unit": "G", "material_clean": "1800223", "temperature_detailed": "+2°C to +8°C", "distrib_sites": "3623|350", "quantity_demand": [ { "lane_id": "3623_350", "volume": 3900 } ], "quantity_supply": [ { "lane_id": "3623_350", "volume": 1968.5742797851562 } ], "flow_type": "Scope", "flow_key": 12, "tariff_details": [ { "lane_id": "3623_350", "country_code": null, "tariff_code": null, "unit_price": null, "currency": null, "total_price": 0, "tariff_rate_pct": null, "tariff_rate_annex_1": null, "tariff_rate_annex_2": null, "tariff_duty": 0, "volume": 1968.5742797851562 } ] }, { "nodes": [ { "site_id": "3623", "description": "3623 - MFCT Lessines, Lessines (MFCT)" }, { "site_id": "3801", "description": "3801 - RDC Germany Arvato, Harsewinkel (RDC)" } ], "index": "PLASMA:1800226 - BULK PACK CUVITRU 20G:Germany:Cold:NO:CLINICAL:3623|3801", "routed_nodes": [ "3623", "3801" ], "market_iso2": "DE", "trade_name": "CUVITRU", "operating_unit": "PLASMA", "temperature_range": "Cold", "controlled_drugs": "NO", "plm_status": "CLINICAL", "sku_description": "1800226-BULK PACK CUVITRU 20G", "country_description": "Germany", "gross_weight": 206, "quantity_per_pal": 1440, "material_text": "BULK PACK CUVITRU 20G", "customer_code_in_ibp": "D_DE HM_DI_8012", "finance_country_code": "DE", "unit_of_measure": "PC", "material_type": "S - Finished Goods", "weight_unit": "G", "material_clean": "1800226", "temperature_detailed": "+2°C to +8°C", "distrib_sites": "3623|3801", "quantity_demand": [ { "lane_id": "3623_3801", "volume": 2300 } ], "quantity_supply": [ { "lane_id": "3623_3801", "volume": 1257.1471862792969 } ], "flow_type": "Scope", "flow_key": 13, "tariff_details": [ { "lane_id": "3623_3801", "country_code": null, "tariff_code": null, "unit_price": null, "currency": null, "total_price": 0, "tariff_rate_pct": null, "tariff_rate_annex_1": null, "tariff_rate_annex_2": null, "tariff_duty": 0, "volume": 1257.1471862792969 } ] }, { "nodes": [ { "site_id": "3623", "description": "3623 - MFCT Lessines, Lessines (MFCT)" }, { "site_id": "3811", "description": "3811 - RDC Germany TOF, Alzenau (RDC)" } ], "index": "BIOLOGICS:8800240 - ADVATE,HIGH,CLINICAL,BAX111:Germany:Cold:NO:CLINICAL:3623|3811", "routed_nodes": [ "3623", "3811" ], "market_iso2": "DE", "trade_name": "ADVATE", "operating_unit": "BIOLOGICS", "temperature_range": "Cold", "controlled_drugs": "NO", "plm_status": "CLINICAL", "sku_description": "8800240-ADVATE,HIGH,CLINICAL,BAX111", "country_description": "Germany", "gross_weight": 11, "quantity_per_pal": 12960, "material_text": "ADVATE,HIGH,CLINICAL,BAX111", "customer_code_in_ibp": "D_DE HM_DI_8036", "finance_country_code": "DE", "unit_of_measure": "PC", "material_type": "S - Finished Goods", "weight_unit": "G", "material_clean": "8800240", "temperature_detailed": "+2°C to +8°C", "distrib_sites": "3623|3811", "quantity_demand": [ { "lane_id": "3623_3811", "volume": 500 } ], "quantity_supply": [ { "lane_id": "3623_3811", "volume": 357.1428527832031 } ], "flow_type": "Scope", "flow_key": 14, "tariff_details": [ { "lane_id": "3623_3811", "country_code": null, "tariff_code": null, "unit_price": null, "currency": null, "total_price": 0, "tariff_rate_pct": null, "tariff_rate_annex_1": null, "tariff_rate_annex_2": null, "tariff_duty": 0, "volume": 357.1428527832031 } ] }, { "nodes": [ { "site_id": "3622", "description": "3622 - MFCT Vienna, Vienna (MFCT)" }, { "site_id": "3811", "description": "3811 - RDC Germany TOF, Alzenau (RDC)" } ], "index": "OTHER:6510365 - RADAMTS13,1500IU,BJIIHF,5ML,YL CLINICAL:Germany:Cold:NO:CLINICAL:3622|3811", "routed_nodes": [ "3622", "3811" ], "market_iso2": "DE", "trade_name": "OTHER BIOTHERAPEUTICS", "operating_unit": "OTHER", "temperature_range": "Cold", "controlled_drugs": "NO", "plm_status": "CLINICAL", "sku_description": "6510365-RADAMTS13,1500IU,BJIIHF,5ML,YL CLINICAL", "country_description": "Germany", "gross_weight": 13, "quantity_per_pal": 2014, "material_text": "RADAMTS13,1500IU,BJIIHF,5ML,YL CLINICAL", "customer_code_in_ibp": "D_DE HM_DI_8036", "finance_country_code": "DE", "unit_of_measure": "PC", "material_type": "S - Finished Goods", "weight_unit": "G", "material_clean": "6510365", "temperature_detailed": "+2°C to +8°C", "distrib_sites": "3622|3811", "quantity_demand": [ { "lane_id": "3622_3811", "volume": 14000 } ], "quantity_supply": [ { "lane_id": "3622_3811", "volume": 18000 } ], "flow_type": "Scope", "flow_key": 15, "tariff_details": [ { "lane_id": "3622_3811", "country_code": null, "tariff_code": null, "unit_price": null, "currency": null, "total_price": 0, "tariff_rate_pct": null, "tariff_rate_annex_1": null, "tariff_rate_annex_2": null, "tariff_duty": 0, "volume": 18000 } ] }, { "nodes": [ { "site_id": "3623", "description": "3623 - MFCT Lessines, Lessines (MFCT)" }, { "site_id": "3001", "description": "3001 - LOC Argentina, Olivos (LOC)" } ], "index": "PLASMA:1501302 - KIOVIG,10G,AR:Argentina:Cold:NO:CONSTRAINED:3623|3001", "routed_nodes": [ "3623", "3001" ], "market_iso2": "AR", "trade_name": "GAMMAGARD KIOVIG LIQUID", "operating_unit": "PLASMA", "temperature_range": "Cold", "controlled_drugs": "NO", "plm_status": "CONSTRAINED", "sku_description": "1501302-KIOVIG,10G,AR", "country_description": "Argentina", "gross_weight": 238, "quantity_per_pal": 1008, "material_text": "KIOVIG,10G,AR", "customer_code_in_ibp": "D_AR HM_DI_9730", "finance_country_code": "AR", "unit_of_measure": "PC", "material_type": "S - Finished Goods", "weight_unit": "G", "material_clean": "1501302", "temperature_detailed": "+2°C to +8°C", "distrib_sites": "3623|3001", "quantity_demand": [ { "lane_id": "3623_3001", "volume": 5900 } ], "quantity_supply": [ { "lane_id": "3623_3001", "volume": 11828.03384399414 } ], "flow_type": "Scope", "flow_key": 17, "tariff_details": [ { "lane_id": "3623_3001", "country_code": null, "tariff_code": null, "unit_price": null, "currency": null, "total_price": 0, "tariff_rate_pct": null, "tariff_rate_annex_1": null, "tariff_rate_annex_2": null, "tariff_duty": 0, "volume": 11828.03384399414 } ] } ], "edited_flows": [], "reroute_flows": [], "lanes": [], "tariff_changes": [], "updated_lanes": [], "custom_node": [], "volume_type": "Supply" } | E2: 200 | F2: { "status": "Success", "data": { "scenario_id": "{scenario_id}" }, "error": null } | G2: scenario_id
A3: TC_SharedScenario | B3: /nmt/api/v1/nmt/scenarios/shared-scenario | C3: POST | D3: { "scenario_id": "{scenario_id}", "users": [ { "email_id": "soni.k-s@takeda.com", "user_name": "Soni K S [C]" } ] } | E3: 200 | F3: { "status": "Success", "data": { "message": "Email sent successfully" }, "error": null }
A4: TC_DeleteScenario | B4: /nmt/api/v1/nmt/scenarios?scenario_ids={scenario_id} | C4: DELETE | E4: 200 | F4: { "status": "Success", "data": { "message": "Record deleted successfully" }, "error": null }
A5: TC_GetScenarios | B5: /nmt/api/v1/nmt/scenarios/?is_historical=true | C5: GET | D5: {} | E5: 200 | F5: { "status": "Success", "data": { "scenarios": [ { "scenario_id": "scen-62a908e6066b4ab98021c3a3febcd9f5", "scenario_name": "Network overview - Nov 24 to Oct 25", "description": "Based on 12 months existing historical data", "markets": [ "Norway", "Argentina", "Kazakhstan", "Libya", "Panama", "Hong Kong", "Bulgaria", "Germany", "Ecuador", "Philippines", "Vietnam", "Croatia", "Kuwait", "Turkey", "Egypt", "France", "Czech Republic", "Belarus", "Finland", "Taiwan", "Estonia", "Denmark", "Singapore", "Russia", "Poland", "Colombia", "Serbia", "Costa Rica", "Brazil", "Mexico", "El Salvador", "Indonesia", "Paraguay", "South Africa", "New Zealand", "Slovakia", "Algeria", "Trinidad and Tobago", "Peru", "Switzerland", "Jordan", "Guatemala", "Slovenia", "Hungary", "Spain", "United States", "Ukraine", "Ireland", "Iraq", "Portugal", "Sweden", "Lithuania", "Honduras", "Lebanon", "Belgium", "Chile", "Romania", "Iran", "Canada", "Japan", "UK", "Tunisia", "Uruguay", "Netherlands", "Saudi Arabia", "Latvia", "Oman", "Bahrain", "Austria", "Italy", "Sri Lanka", "Thailand", "United Arab Emirates", "Israel", "Greece", "Azerbaijan", "India", "China", "Malaysia", "Australia" ], "brands": [ "TAKHZYRO", "ADVATE", "AFIPRAN", "ACTOVEGIN", "LEUPRORELIN", "CALCIUM", "MELATONINA", "GLYCOSTIGMIN", "QDENGA", "BRENTUXIMAB", "GUTRON", "PRUCALOPRIDE", "LANSOPRAZOLE", "PREDNISOLON", "OBIZUR", "VPRIV", "ASAFLOW", "VONOPRAZAN", "FLEXBUMIN", "FACTOR VII", "ADYNOVATE", "ASACOL", "LANTHANUM", "PONATINIB", "CUVITRU", "FUROSEMID", "NORIPURUM", "ICATIBANT", "ATROPIN", "VORTIOXETINE", "GYNIPRAL", "ALBYL-E", "IMMUNATE", "AT-III", "ELAPRASE", "LISDEXAMFETAMINE", "ARALAST", "DOPAMIN", "RIOPAN", "VITAMIN B12", "AZILSARTAN MEDOXOMIL", "PANTOPRAZOLE", "PIOGLITAZONE", "CINRYZE", "GATTEX/REVESTIVE", "XEFO", "NYCOPLUS", "LIQUID HYQVIA", "ALOGLIPTIN", "OTHER BIOTHERAPEUTICS", "BRIGATINIB", "IXAZOMIB", "RECOMBINATE", "ANAGRELIDE", "CIRCADINE", "DEXLANSOPRAZOLE", "FLOWEASE", "GLASSIA", "MISCELLANEOUS PRODUCTS", "RAMELTEON", "REPLAGAL", "MESALAZINE", "VONVENDI", "HYDROCOBAMIN", "RIXUBIS", "FAKTU", "-", "LYSTHENON", "CONDYLINE", "FEIBA", "LEVOTHYROXIN", "KLORAMFENIKOL", "EUPHYLLIN", "GAMMAGARD", "WARFARIN", "ADZYNMA", "ADRENALIN", "HYDROCORTISONE", "ADDERALL XR", "PROTHROMBIN", "VEDOLIZUMAB", "POLICRESULEN", "MAGNYL", "LIQUID IGIV", "MEPACT", "CEDOCARD", "MARIBAVIR", "IMMUNINE", "PROTEIN C", "FERRUM", "GEWACALM", "ALBUMIN NG", "OTHER", "FRUQUINTINIB", "GUANFACINE", "EBRANTIL" ], "market_count": 80, "brand_count": 96, "forecast_version": "", "start_date": "2024-NOV", "end_date": "2025-OCT", "scoring_available": "processing", "users": [], "created_by": { "user_name": "PIC_NMT_SERVICE", "image_url": "" }, "created_at": "2026-01-27T16:44:23.625816", "access_level": "global", "shared_with_user_emails": [], "volume_type": "Supply", "scen_stat_desc": "SUCCESS", "material_type": [ "RAW", "PACK", "TRAD", "HALB", "FINI" ] }, { "scenario_id": "scen-b938fc96a1e348188c6a77ea5ce5139e", "scenario_name": "Network overview - Dec 24 to Nov 25", "description": "Based on 12 months existing historical data", "markets": [ "Norway", "Argentina", "Kazakhstan", "Libya", "Panama", "Hong Kong", "Bulgaria", "Germany", "Ecuador", "Philippines", "Vietnam", "Croatia", "Kuwait", "Turkey", "Egypt", "France", "Czech Republic", "Belarus", "Finland", "Taiwan", "Estonia", "Denmark", "Singapore", "Russia", "Poland", "Colombia", "Serbia", "Costa Rica", "Brazil", "Mexico", "El Salvador", "Indonesia", "Paraguay", "South Africa", "New Zealand", "Slovakia", "Algeria", "Trinidad and Tobago", "Peru", "Switzerland", "Jordan", "Guatemala", "Slovenia", "Hungary", "Spain", "United States", "Ukraine", "Ireland", "Iraq", "Portugal", "Sweden", "Lithuania", "Honduras", "Lebanon", "Belgium", "Chile", "Romania", "Iran", "Canada", "Japan", "UK", "Tunisia", "Uruguay", "Netherlands", "Saudi Arabia", "Latvia", "Oman", "Bahrain", "Austria", "Italy", "Sri Lanka", "Thailand", "United Arab Emirates", "Israel", "Greece", "Azerbaijan", "India", "China", "Malaysia", "Australia" ], "brands": [ "TAKHZYRO", "ADVATE", "AFIPRAN", "ACTOVEGIN", "LEUPRORELIN", "CALCIUM", "MELATONINA", "GLYCOSTIGMIN", "QDENGA", "BRENTUXIMAB", "GUTRON", "PRUCALOPRIDE", "LANSOPRAZOLE", "PREDNISOLON", "OBIZUR", "VPRIV", "ASAFLOW", "VONOPRAZAN", "FLEXBUMIN", "FACTOR VII", "ADYNOVATE", "ASACOL", "LANTHANUM", "PONATINIB", "CUVITRU", "FUROSEMID", "NORIPURUM", "ICATIBANT", "ATROPIN", "VORTIOXETINE", "GYNIPRAL", "ALBYL-E", "IMMUNATE", "AT-III", "ELAPRASE", "LISDEXAMFETAMINE", "ARALAST", "DOPAMIN", "RIOPAN", "VITAMIN B12", "AZILSARTAN MEDOXOMIL", "PANTOPRAZOLE", "PIOGLITAZONE", "CINRYZE", "GATTEX/REVESTIVE", "XEFO", "NYCOPLUS", "LIQUID HYQVIA", "ALOGLIPTIN", "OTHER BIOTHERAPEUTICS", "BRIGATINIB", "IXAZOMIB", "RECOMBINATE", "ANAGRELIDE", "CIRCADINE", "DEXLANSOPRAZOLE", "FLOWEASE", "GLASSIA", "MISCELLANEOUS PRODUCTS", "RAMELTEON", "REPLAGAL", "MESALAZINE", "VONVENDI", "HYDROCOBAMIN", "RIXUBIS", "FAKTU", "-", "LYSTHENON", "CONDYLINE", "FEIBA", "LEVOTHYROXIN", "KLORAMFENIKOL", "EUPHYLLIN", "GAMMAGARD", "WARFARIN", "ADZYNMA", "ADRENALIN", "HYDROCORTISONE", "ADDERALL XR", "PROTHROMBIN", "VEDOLIZUMAB", "POLICRESULEN", "MAGNYL", "LIQUID IGIV", "MEPACT", "CEDOCARD", "MARIBAVIR", "IMMUNINE", "PROTEIN C", "FERRUM", "GEWACALM", "ALBUMIN NG", "OTHER", "FRUQUINTINIB", "GUANFACINE", "EBRANTIL" ], "market_count": 80, "brand_count": 96, "forecast_version": "", "start_date": "2024-DEC", "end_date": "2025-NOV", "scoring_available": "processing", "users": [], "created_by": { "user_name": "PIC_NMT_SERVICE", "image_url": "" }, "created_at": "2026-01-27T16:49:20.845209", "access_level": "global", "shared_with_user_emails": [], "volume_type": "Supply", "scen_stat_desc": "SUCCESS", "material_type": [ "RAW", "PACK", "TRAD", "HALB", "FINI" ] }, { "scenario_id": "scen-0d30009c947f45c38dd40849c606a362", "scenario_name": "Network overview - Jan 25 to Dec 25", "description": "Based on 12 months existing historical data", "markets": [ "Norway", "Argentina", "Kazakhstan", "Libya", "Panama", "Hong Kong", "Bulgaria", "Germany", "Ecuador", "Philippines", "Vietnam", "Croatia", "Kuwait", "Turkey", "Egypt", "France", "Czech Republic", "Belarus", "Finland", "Taiwan", "Estonia", "Denmark", "Singapore", "Russia", "Poland", "Colombia", "Serbia", "Costa Rica", "Brazil", "Mexico", "El Salvador", "Indonesia", "Paraguay", "South Africa", "New Zealand", "Slovakia", "Algeria", "Trinidad and Tobago", "Peru", "Switzerland", "Jordan", "Guatemala", "Slovenia", "Hungary", "Spain", "United States", "Ukraine", "Ireland", "Iraq", "Portugal", "Sweden", "Lithuania", "Honduras", "Lebanon", "Belgium", "Chile", "Romania", "Iran", "Canada", "Japan", "UK", "Tunisia", "Uruguay", "Netherlands", "Saudi Arabia", "Latvia", "Oman", "Bahrain", "Austria", "Italy", "Sri Lanka", "Thailand", "United Arab Emirates", "Israel", "Greece", "Azerbaijan", "India", "China", "Malaysia", "Australia" ], "brands": [ "TAKHZYRO", "ADVATE", "AFIPRAN", "ACTOVEGIN", "LEUPRORELIN", "CALCIUM", "MELATONINA", "GLYCOSTIGMIN", "QDENGA", "BRENTUXIMAB", "GUTRON", "PRUCALOPRIDE", "LANSOPRAZOLE", "PREDNISOLON", "OBIZUR", "VPRIV", "ASAFLOW", "VONOPRAZAN", "FLEXBUMIN", "FACTOR VII", "ADYNOVATE", "ASACOL", "LANTHANUM", "PONATINIB", "CUVITRU", "FUROSEMID", "NORIPURUM", "ICATIBANT", "ATROPIN", "VORTIOXETINE", "GYNIPRAL", "ALBYL-E", "IMMUNATE", "AT-III", "ELAPRASE", "LISDEXAMFETAMINE", "ARALAST", "DOPAMIN", "RIOPAN", "VITAMIN B12", "AZILSARTAN MEDOXOMIL", "PANTOPRAZOLE", "ALBETOL", "CINRYZE", "PIOGLITAZONE", "GATTEX/REVESTIVE", "XEFO", "NYCOPLUS", "LIQUID HYQVIA", "ALOGLIPTIN", "OTHER BIOTHERAPEUTICS", "BRIGATINIB", "IXAZOMIB", "RECOMBINATE", "ANAGRELIDE", "CIRCADINE", "DEXLANSOPRAZOLE", "FLOWEASE", "GLASSIA", "MISCELLANEOUS PRODUCTS", "RAMELTEON", "REPLAGAL", "MESALAZINE", "VONVENDI", "HYDROCOBAMIN", "RIXUBIS", "FAKTU", "-", "LYSTHENON", "CONDYLINE", "FEIBA", "LEVOTHYROXIN", "KLORAMFENIKOL", "EUPHYLLIN", "GAMMAGARD", "WARFARIN", "ADZYNMA", "ADRENALIN", "HYDROCORTISONE", "ADDERALL XR", "PROTHROMBIN", "VEDOLIZUMAB", "POLICRESULEN", "MAGNYL", "LIQUID IGIV", "MEPACT", "CEDOCARD", "MARIBAVIR", "IMMUNINE", "PROTEIN C", "FERRUM", "GEWACALM", "ALBUMIN NG", "OTHER", "FRUQUINTINIB", "GUANFACINE", "EBRANTIL" ], "market_count": 80, "brand_count": 97, "forecast_version": "", "start_date": "2025-JAN", "end_date": "2025-DEC", "scoring_available": "processing", "users": [], "created_by": { "user_name": "PIC_NMT_SERVICE", "image_url": "" }, "created_at": "2026-01-27T16:54:21.965650", "access_level": "global", "shared_with_user_emails": [], "volume_type": "Supply", "scen_stat_desc": "SUCCESS", "material_type": [ "RAW", "PACK", "TRAD", "HALB", "FINI" ] } ] }, "error": null }
A6: TC_GetScenario_By_Id | B6: /nmt/api/v1/nmt/scenarios/scenario_ids={scenario_id} | C6: GET | D6: {} | E6: 200 | F6: { "status": "Success", "data": { "is_baseline": true, "scenario_details": { "id": "{scenario_id}" "name": "Api_Automation", "description": "test", "forecast_version": "2026-JAN", "start_date": "2026-JAN", "end_date": "2026-DEC", "access_level_type_description": "restricted", "user_id": [ "soni.k-s@takeda.com", "naheeda.parveen@takeda.com" ] }, "score_details": { "cost_score": null, "co2_score": null, "leadtime_score": null, "final_score": null, "bc_score": null, "risk_score": null }, "artifact_data": { "lane_attributes": [ { "source": "517499", "sink": "3811", "lats": [ 51.98196029663086, 50.050270080566406 ], "lons": [ 19.91139030456543, 9.041939735412598 ], "color": "Site-RDC", "country_color": "Poland-Germany", "volume": 2836, "skus": 1, "sku_set": [ "1142668" ], "total_weight": 163.964, "transport_cost": 1209.9671021947238, "transport_cost_lo": 0, "transport_cost_up": 0, "transport_cost_road": 1209.9671021947238, "transport_cost_air": 0, "transport_cost_sea": 0, "transport_cost_warning_flag": false, "co2": 0.006623476157725194, "co2_road": 0.006623476157725194, "co2_air": 0, "co2_sea": 0, "num_shipments": 1, "controlled_shipments": 0, "cold_shipments": 0, "normal_shipments": 1, "num_shipments_air_amb": 0, "num_shipments_road_amb": 1, "num_shipments_sea_amb": 0, "num_shipments_air_cold": 0, "num_shipments_road_cold": 0, "num_shipments_sea_cold": 0, "volume_pallets": 1, "volume_air_amb": 0, "volume_road_amb": 1, "volume_sea_amb": 0, "volume_air_cold": 0, "volume_road_cold": 0, "volume_sea_cold": 0, "aws_road_flag": true, "sea_flag": true, "road_distance": 990.0960083007812, "sea_distance": 1166.69, "sea_road_part": 433.132, "air_distance": 993.3475704964529, "air_road_part": 134.593, "transp_lead_time_average": 1.9801920166015625, "lt_sea": 7.913088561403509, "lt_road": 1.9801920166015625, "lt_air": 2.3354091713664302, "certainty_score": 0.6930960086299892, "aggr_level_air_amb": null, "aggr_level_road_amb": "city->city", "aggr_level_sea_amb": null, "aggr_level_air_cold": null, "aggr_level_road_cold": null, "aggr_level_sea_cold": null, "consolidation_score": 0.8236914600550964, "has_road": true, "has_air": false, "has_sea": false, "u_description": "517499 - Orifarm Manufacturing Poland Sp. z, Lyszkowice", "v_description": "3811 - RDC Germany TOF, Alzenau, Trans-O-Flex", "u_city": "LYSZKOWICE, Poland", "v_city": "ALZENAU, Germany", "is_sanctioned_lane": false, "source_subregion": "Central-South Eastern Europe", "source_region": "EU & Canada", "destination_subregion": "Germany", "destination_region": "EU & Canada", "consolidated_air": 0, "consolidated_sea": 0, "consolidated_road": 0, "enforced_air": 0, "enforced_sea": 0, "enforced_road": 0, "source_closest_airports": null, "target_closest_airports": null, "source_closest_seaports": null, "target_closest_seaports": null, "ship_sol_weight": 0, "shipping_solutions": [], "suggested_shipping_solutions": [ { "ship_sol_std_nm": "csafe_rkn", "tot_shipped_pallets": 0, "ratio": 0, "ship_sol_cat": "Small Active Container", "full_ship_sol_nm": "cSafe RKN", "ship_sol_prop": 1, "temperature": "Ambient" }, { "ship_sol_std_nm": "blanket_ecosafe_plus", "tot_shipped_pallets": 0, "ratio": 0, "ship_sol_cat": "Thermal Blanket", "full_ship_sol_nm": "Thermal Blankets EcoSafe +", "ship_sol_prop": 0, "temperature": "Ambient" }, { "ship_sol_std_nm": "envirotainer_rkn_t2", "tot_shipped_pallets": 0, "ratio": 0, "ship_sol_cat": "Small Passive Container", "full_ship_sol_nm": "Envirotainer RKN T2", "ship_sol_prop": 0.5, "temperature": "Cold" }, { "ship_sol_std_nm": "envirotainer_rkn_e1", "tot_shipped_pallets": 0, "ratio": 0, "ship_sol_cat": "Small Active Container", "full_ship_sol_nm": "Envirotainer RKN E1", "ship_sol_prop": 0.5, "temperature": "Cold" }, { "ship_sol_std_nm": "envirotainer_rap_e2", "tot_shipped_pallets": 0, "ratio": 0, "ship_sol_cat": "Large Active Container", "full_ship_sol_nm": "Envirotainer RAP E2", "ship_sol_prop": 0, "temperature": "Cold" } ], "material_type": [ "T - Traded Goods" ], "origin_country": "Poland", "destination_country": "Germany", "volume_breakdown": [ { "volume": 2836, "unit": "PC" } ] }, { "source": "3811", "sink": "43", "lats": [ 50.050270080566406, 52.29304122924805 ], "lons": [ 9.041939735412598, 4.697000026702881 ], "color": "RDC-LOC", "country_color": "Germany-Netherlands", "volume": 4238.142868041992, "skus": 1, "sku_set": [ "1142668" ], "total_weight": 232.66900053405763, "transport_cost": 741.8847557432671, "transport_cost_lo": 0, "transport_cost_up": 0, "transport_cost_road": 741.8847557432671, "transport_cost_air": 0, "transport_cost_sea": 0, "transport_cost_warning_flag": false, "co2": 0.004606095120276595, "co2_road": 0.004606095120276595, "co2_air": 0, "co2_sea": 0, "num_shipments": 1, "controlled_shipments": 0, "cold_shipments": 0, "normal_shipments": 1, "num_shipments_air_amb": 0, "num_shipments_road_amb": 1, "num_shipments_sea_amb": 0, "num_shipments_air_cold": 0, "num_shipments_road_cold": 0, "num_shipments_sea_cold": 0, "volume_pallets": 1, "volume_air_amb": 0, "volume_road_amb": 1, "volume_sea_amb": 0, "volume_air_cold": 0, "volume_road_cold": 0, "volume_sea_cold": 0, "aws_road_flag": true, "sea_flag": true, "road_distance": 485.2149963378906, "sea_distance": 403.134, "sea_road_part": 502.06100000000004, "air_distance": 460.7411613109879, "air_road_part": 64.27091748867335, "transp_lead_time_average": 0.9704299926757812, "lt_sea": 6.7113746315789475, "lt_road": 0.9704299926757812, "lt_air": 2.159257912398079, "certainty_score": 0.29817286947141314, "aggr_level_air_amb": null, "aggr_level_road_amb": "city->country", "aggr_level_sea_amb": null, "aggr_level_air_cold": null, "aggr_level_road_cold": null, "aggr_level_sea_cold": null, "consolidation_score": 0.5075757575757576, "has_road": true, "has_air": false, "has_sea": false, "u_description": "3811 - RDC Germany TOF, Alzenau, Trans-O-Flex", "v_description": "43 - LOC Netherlands, EDE", "u_city": "ALZENAU, Germany", "v_city": "EDE, Netherlands", "is_sanctioned_lane": false, "source_subregion": "Germany", "source_region": "EU & Canada", "destination_subregion": "Central-South Eastern Europe", "destination_region": "EU & Canada", "consolidated_air": 0, "consolidated_sea": 0, "consolidated_road": 0, "enforced_air": 0, "enforced_sea": 0, "enforced_road": 0, "source_closest_airports": null, "target_closest_airports": null, "source_closest_seaports": null, "target_closest_seaports": null, "ship_sol_weight": 0, "shipping_solutions": [], "suggested_shipping_solutions": [ { "ship_sol_std_nm": "csafe_rkn", "tot_shipped_pallets": 0, "ratio": 0, "ship_sol_cat": "Small Active Container", "full_ship_sol_nm": "cSafe RKN", "ship_sol_prop": 1, "temperature": "Ambient" }, { "ship_sol_std_nm": "blanket_ecosafe_plus", "tot_shipped_pallets": 0, "ratio": 0, "ship_sol_cat": "Thermal Blanket", "full_ship_sol_nm": "Thermal Blankets EcoSafe +", "ship_sol_prop": 0, "temperature": "Ambient" }, { "ship_sol_std_nm": "envirotainer_rkn_t2", "tot_shipped_pallets": 0, "ratio": 0, "ship_sol_cat": "Small Passive Container", "full_ship_sol_nm": "Envirotainer RKN T2", "ship_sol_prop": 0.5, "temperature": "Cold" }, { "ship_sol_std_nm": "envirotainer_rkn_e1", "tot_shipped_pallets": 0, "ratio": 0, "ship_sol_cat": "Small Active Container", "full_ship_sol_nm": "Envirotainer RKN E1", "ship_sol_prop": 0.5, "temperature": "Cold" }, { "ship_sol_std_nm": "envirotainer_rap_e2", "tot_shipped_pallets": 0, "ratio": 0, "ship_sol_cat": "Large Active Container", "full_ship_sol_nm": "Envirotainer RAP E2", "ship_sol_prop": 0, "temperature": "Cold" } ], "material_type": [ "T - Traded Goods" ], "origin_country": "Germany", "destination_country": "Netherlands", "volume_breakdown": [ { "volume": 4238.142868041992, "unit": "PC" } ] }, { "source": "20", "sink": "LU", "lats": [ 50.89282989501953, 49.815868 ], "lons": [ 4.462500095367432, 6.129675 ], "color": "LOC-Wholes./Distrib.", "country_color": "Belgium-Luxembourg", "volume": 36681, "skus": 1, "sku_set": [ "6062079" ], "total_weight": 985.2579999999999, "transport_cost": 2893.398652021412, "transport_cost_lo": 0, "transport_cost_up": 0, "transport_cost_road": 2893.398652021412, "transport_cost_air": 0, "transport_cost_sea": 0, "transport_cost_warning_flag": false, "co2": 0.02072473434099191, "co2_road": 0.02072473434099191, "co2_air": 0, "co2_sea": 0, "num_shipments": 7, "controlled_shipments": 0, "cold_shipments": 0, "normal_shipments": 7, "num_shipments_air_amb": 0, "num_shipments_road_amb": 7, "num_shipments_sea_amb": 0, "num_shipments_air_cold": 0, "num_shipments_road_cold": 0, "num_shipments_sea_cold": 0, "volume_pallets": 13, "volume_air_amb": 0, "volume_road_amb": 13, "volume_sea_amb": 0, "volume_air_cold": 0, "volume_road_cold": 0, "volume_sea_cold": 0, "aws_road_flag": true, "sea_flag": true, "road_distance": 203.09921823018118, "sea_distance": 70.418, "sea_road_part": 222.9862289968481, "air_distance": 262.89618669230276, "air_road_part": 126.43299999999999, "transp_lead_time_average": 0.4061984364603624, "lt_sea": 5.569512808870889, "lt_road": 0.40619843646036236, "lt_air": 2.2703924124461534, "certainty_score": 0.266647996016928, "aggr_level_air_amb": null, "aggr_level_road_amb": "country->subregion", "aggr_level_sea_amb": null, "aggr_level_air_cold": null, "aggr_level_road_cold": null, "aggr_level_sea_cold": null, "consolidation_score": 0.19450056116722786, "has_road": true, "has_air": false, "has_sea": false, "u_description": "20 - LOC Belgium, Beersel(Lot)", "v_description": "Luxembourg Wholes./Cust.", "u_city": "BEERSEL(LOT), Belgium", "v_city": ", Luxembourg", "is_sanctioned_lane": false, "source_subregion": "Central-South Eastern Europe", "source_region": "EU & Canada", "destination_subregion": "Central-South Eastern Europe", "destination_region": "EU & Canada", "consolidated_air": 0, "consolidated_sea": 0, "consolidated_road": 0, "enforced_air": 0, "enforced_sea": 0, "enforced_road": 0, "source_closest_airports": null, "target_closest_airports": null, "source_closest_seaports": null, "target_closest_seaports": null, "ship_sol_weight": 0, "shipping_solutions": [], "suggested_shipping_solutions": [ { "ship_sol_std_nm": "csafe_rkn", "tot_shipped_pallets": 0, "ratio": 0, "ship_sol_cat": "Small Active Container", "full_ship_sol_nm": "cSafe RKN", "ship_sol_prop": 1, "temperature": "Ambient" }, { "ship_sol_std_nm": "blanket_ecosafe_plus", "tot_shipped_pallets": 0, "ratio": 0, "ship_sol_cat": "Thermal Blanket", "full_ship_sol_nm": "Thermal Blankets EcoSafe +", "ship_sol_prop": 0, "temperature": "Ambient" }, { "ship_sol_std_nm": "envirotainer_rkn_t2", "tot_shipped_pallets": 0, "ratio": 0, "ship_sol_cat": "Small Passive Container", "full_ship_sol_nm": "Envirotainer RKN T2", "ship_sol_prop": 0.5, "temperature": "Cold" }, { "ship_sol_std_nm": "envirotainer_rkn_e1", "tot_shipped_pallets": 0, "ratio": 0, "ship_sol_cat": "Small Active Container", "full_ship_sol_nm": "Envirotainer RKN E1", "ship_sol_prop": 0.5, "temperature": "Cold" }, { "ship_sol_std_nm": "envirotainer_rap_e2", "tot_shipped_pallets": 0, "ratio": 0, "ship_sol_cat": "Large Active Container", "full_ship_sol_nm": "Envirotainer RAP E2", "ship_sol_prop": 0, "temperature": "Cold" } ], "material_type": [ "T - Traded Goods" ], "origin_country": "Belgium", "destination_country": "Luxembourg", "volume_breakdown": [ { "volume": 36681, "unit": "PC" } ] }, { "source": "3811", "sink": "100", "lats": [ 50.050270080566406, 55.628021240234375 ], "lons": [ 9.041939735412598, 12.385540008544922 ], "color": "RDC-LOC", "country_color": "Germany-Denmark", "volume": 0, "skus": 1, "sku_set": [ "6228081" ], "total_weight": 0, "transport_cost": 0, "transport_cost_lo": 0, "transport_cost_up": 0, "transport_cost_road": 0, "transport_cost_air": 0, "transport_cost_sea": 0, "transport_cost_warning_flag": false, "co2": 0, "co2_road": 0, "co2_air": 0, "co2_sea": 0, "num_shipments": 0, "controlled_shipments": 0, "cold_shipments": 0, "normal_shipments": 0, "num_shipments_air_amb": 0, "num_shipments_road_amb": 0, "num_shipments_sea_amb": 0, "num_shipments_air_cold": 0, "num_shipments_road_cold": 0, "num_shipments_sea_cold": 0, "volume_pallets": 0, "volume_air_amb": 0, "volume_road_amb": 0, "volume_sea_amb": 0, "volume_air_cold": 0, "volume_road_cold": 0, "volume_sea_cold": 0, "aws_road_flag": true, "sea_flag": true, "road_distance": 805.625, "sea_distance": 813.914, "sea_road_part": 756.268, "air_distance": 775.1073137575298, "air_road_part": 74.943, "transp_lead_time_average": 0, "lt_sea": 7.940455298245614, "lt_road": 1.61125, "lt_air": 2.2015598209171685, "certainty_score": 0, "aggr_level_air_amb": null, "aggr_level_road_amb": null, "aggr_level_sea_amb": null, "aggr_level_air_cold": null, "aggr_level_road_cold": null, "aggr_level_sea_cold": null, "consolidation_score": 0, "has_road": false, "has_air": false, "has_sea": false, "u_description": "3811 - RDC Germany TOF, Alzenau, Trans-O-Flex", "v_description": "100 - LOC Hobro & LOC Denmark, Køge", "u_city": "ALZENAU, Germany", "v_city": "KØGE, Denmark", "is_sanctioned_lane": false, "source_subregion": "Germany", "source_region": "EU & Canada", "destination_subregion": "Nordics", "destination_region": "EU & Canada", "consolidated_air": 0, "consolidated_sea": 0, "consolidated_road": 0, "enforced_air": 0, "enforced_sea": 0, "enforced_road": 0, "source_closest_airports": null, "target_closest_airports": null, "source_closest_seaports": null, "target_closest_seaports": null, "ship_sol_weight": 0, "shipping_solutions": [], "suggested_shipping_solutions": [ { "ship_sol_std_nm": "csafe_rkn", "tot_shipped_pallets": 0, "ratio": 0, "ship_sol_cat": "Small Active Container", "full_ship_sol_nm": "cSafe RKN", "ship_sol_prop": 1, "temperature": "Ambient" }, { "ship_sol_std_nm": "blanket_ecosafe_plus", "tot_shipped_pallets": 0, "ratio": 0, "ship_sol_cat": "Thermal Blanket", "full_ship_sol_nm": "Thermal Blankets EcoSafe +", "ship_sol_prop": 0, "temperature": "Ambient" }, { "ship_sol_std_nm": "envirotainer_rkn_t2", "tot_shipped_pallets": 0, "ratio": 0, "ship_sol_cat": "Small Passive Container", "full_ship_sol_nm": "Envirotainer RKN T2", "ship_sol_prop": 0.5, "temperature": "Cold" }, { "ship_sol_std_nm": "envirotainer_rkn_e1", "tot_shipped_pallets": 0, "ratio": 0, "ship_sol_cat": "Small Active Container", "full_ship_sol_nm": "Envirotainer RKN E1", "ship_sol_prop": 0.5, "temperature": "Cold" }, { "ship_sol_std_nm": "envirotainer_rap_e2", "tot_shipped_pallets": 0, "ratio": 0, "ship_sol_cat": "Large Active Container", "full_ship_sol_nm": "Envirotainer RAP E2", "ship_sol_prop": 0, "temperature": "Cold" } ], "material_type": [ "T - Traded Goods" ], "origin_country": "Germany", "destination_country": "Denmark", "volume_breakdown": [ { "volume": 0, "unit": "PC" } ] }, { "source": "20", "sink": "43", "lats": [ 50.89282989501953, 52.29304122924805 ], "lons": [ 4.462500095367432, 4.697000026702881 ], "color": "LOC-LOC", "country_color": "Belgium-Netherlands", "volume": 1575.1428451538086, "skus": 1, "sku_set": [ "1142668" ], "total_weight": 102.18199941253663, "transport_cost": 350.6365843319055, "transport_cost_lo": 0, "transport_cost_up": 0, "transport_cost_road": 350.6365843319055, "transport_cost_air": 0, "transport_cost_sea": 0, "transport_cost_warning_flag": false, "co2": 0.0008348431730577038, "co2_road": 0.0008348431730577038, "co2_air": 0, "co2_sea": 0, "num_shipments": 1, "controlled_shipments": 0, "cold_shipments": 0, "normal_shipments": 1, "num_shipments_air_amb": 0, "num_shipments_road_amb": 1, "num_shipments_sea_amb": 0, "num_shipments_air_cold": 0, "num_shipments_road_cold": 0, "num_shipments_sea_cold": 0, "volume_pallets": 1, "volume_air_amb": 0, "volume_road_amb": 1, "volume_sea_amb": 0, "volume_air_cold": 0, "volume_road_cold": 0, "volume_sea_cold": 0, "aws_road_flag": true, "sea_flag": true, "road_distance": 200.24899291992188, "sea_distance": 70.9654, "sea_road_part": 86.1042289968481, "air_distance": 252.6587978844417, "air_road_part": 16.030917488673353, "transp_lead_time_average": 0.40049798583984375, "lt_sea": 5.296709159748082, "lt_road": 0.40049798583984375, "lt_air": 2.0489057548363094, "certainty_score": 0.4011596548004314, "aggr_level_air_amb": null, "aggr_level_road_amb": "country->country", "aggr_level_sea_amb": null, "aggr_level_air_cold": null, "aggr_level_road_cold": null, "aggr_level_sea_cold": null, "consolidation_score": 0.20168350168350166, "has_road": true, "has_air": false, "has_sea": false, "u_description": "20 - LOC Belgium, Beersel(Lot)", "v_description": "43 - LOC Netherlands, EDE", "u_city": "BEERSEL(LOT), Belgium", "v_city": "EDE, Netherlands", "is_sanctioned_lane": false, "source_subregion": "Central-South Eastern Europe", "source_region": "EU & Canada", "destination_subregion": "Central-South Eastern Europe", "destination_region": "EU & Canada", "consolidated_air": 0, "consolidated_sea": 0, "consolidated_road": 0, "enforced_air": 0, "enforced_sea": 0, "enforced_road": 0, "source_closest_airports": null, "target_closest_airports": null, "source_closest_seaports": null, "target_closest_seaports": null, "ship_sol_weight": 0, "shipping_solutions": [], "suggested_shipping_solutions": [ { "ship_sol_std_nm": "csafe_rkn", "tot_shipped_pallets": 0, "ratio": 0, "ship_sol_cat": "Small Active Container", "full_ship_sol_nm": "cSafe RKN", "ship_sol_prop": 1, "temperature": "Ambient" }, { "ship_sol_std_nm": "blanket_ecosafe_plus", "tot_shipped_pallets": 0, "ratio": 0, "ship_sol_cat": "Thermal Blanket", "full_ship_sol_nm": "Thermal Blankets EcoSafe +", "ship_sol_prop": 0, "temperature": "Ambient" }, { "ship_sol_std_nm": "envirotainer_rkn_t2", "tot_shipped_pallets": 0, "ratio": 0, "ship_sol_cat": "Small Passive Container", "full_ship_sol_nm": "Envirotainer RKN T2", "ship_sol_prop": 0.5, "temperature": "Cold" }, { "ship_sol_std_nm": "envirotainer_rkn_e1", "tot_shipped_pallets": 0, "ratio": 0, "ship_sol_cat": "Small Active Container", "full_ship_sol_nm": "Envirotainer RKN E1", "ship_sol_prop": 0.5, "temperature": "Cold" }, { "ship_sol_std_nm": "envirotainer_rap_e2", "tot_shipped_pallets": 0, "ratio": 0, "ship_sol_cat": "Large Active Container", "full_ship_sol_nm": "Envirotainer RAP E2", "ship_sol_prop": 0, "temperature": "Cold" } ], "material_type": [ "T - Traded Goods" ], "origin_country": "Belgium", "destination_country": "Netherlands", "volume_breakdown": [ { "volume": 1575.1428451538086, "unit": "PC" } ] }, { "source": "143285", "sink": "3811", "lats": [ 32.110107421875, 50.050270080566406 ], "lons": [ 34.83861541748047, 9.041939735412598 ], "color": "Site-RDC", "country_color": "Israel-Germany", "volume": 1305955.30859375, "skus": 2, "sku_set": [ "6228081", "6062079" ], "total_weight": 104806.1955546875, "transport_cost": 370162.84511882346, "transport_cost_lo": 0, "transport_cost_up": 0, "transport_cost_road": 0, "transport_cost_air": 216990.7779739139, "transport_cost_sea": 153172.06714490947, "transport_cost_warning_flag": false, "co2": 166.4179686958179, "co2_road": 0, "co2_air": 163.9056468449986, "co2_sea": 2.512321850819271, "num_shipments": 56, "controlled_shipments": 0, "cold_shipments": 0, "normal_shipments": 56, "num_shipments_air_amb": 33, "num_shipments_road_amb": 0, "num_shipments_sea_amb": 23, "num_shipments_air_cold": 0, "num_shipments_road_cold": 0, "num_shipments_sea_cold": 0, "volume_pallets": 436, "volume_air_amb": 109, "volume_road_amb": 0, "volume_sea_amb": 327, "volume_air_cold": 0, "volume_road_cold": 0, "volume_sea_cold": 0, "aws_road_flag": true, "sea_flag": true, "road_distance": 4106.22021484375, "sea_distance": 6854.1, "sea_road_part": 478.504, "air_distance": 3049.2419650209126, "air_road_part": 78.319, "transp_lead_time_average": 14.076288830995964, "lt_sea": 17.981744842105265, "lt_road": 8.2124404296875, "lt_air": 2.3599207976680607, "certainty_score": 0.1579572160579442, "aggr_level_air_amb": "region->region", "aggr_level_road_amb": null, "aggr_level_sea_amb": "region->region", "aggr_level_air_cold": null, "aggr_level_road_cold": null, "aggr_level_sea_cold": null, "consolidation_score": 0.506424660120846, "has_road": false, "has_air": true, "has_sea": true, "u_description": "143285 - Neurim Pharmaceuticals (1991) Ltd., Tel Aviv", "v_description": "3811 - RDC Germany TOF, Alzenau, Trans-O-Flex", "u_city": "TEL AVIV, Israel", "v_city": "ALZENAU, Germany", "is_sanctioned_lane": false, "source_subregion": "Central-South Eastern Europe", "source_region": "EU & Canada", "destination_subregion": "Germany", "destination_region": "EU & Canada", "consolidated_air": 0, "consolidated_sea": 0, "consolidated_road": 0, "enforced_air": 0, "enforced_sea": 0, "enforced_road": 0, "source_closest_airports": null, "target_closest_airports": null, "source_closest_seaports": null, "target_closest_seaports": null, "ship_sol_weight": 70414, "shipping_solutions": [ { "ship_sol_std_nm": "csafe_rkn", "tot_shipped_pallets": 109, "ratio": 1, "ship_sol_cat": null, "full_ship_sol_nm": "cSafe RKN", "ship_sol_prop": 0, "temperature": null } ], "suggested_shipping_solutions": [ { "ship_sol_std_nm": "csafe_rkn", "tot_shipped_pallets": 0, "ratio": 0, "ship_sol_cat": "Small Active Container", "full_ship_sol_nm": "cSafe RKN", "ship_sol_prop": 1, "temperature": "Ambient" }, { "ship_sol_std_nm": "blanket_ecosafe_plus", "tot_shipped_pallets": 0, "ratio": 0, "ship_sol_cat": "Thermal Blanket", "full_ship_sol_nm": "Thermal Blankets EcoSafe +", "ship_sol_prop": 0, "temperature": "Ambient" }, { "ship_sol_std_nm": "envirotainer_rkn_t2", "tot_shipped_pallets": 0, "ratio": 0, "ship_sol_cat": "Small Passive Container", "full_ship_sol_nm": "Envirotainer RKN T2", "ship_sol_prop": 0.5, "temperature": "Cold" }, { "ship_sol_std_nm": "envirotainer_rkn_e1", "tot_shipped_pallets": 0, "ratio": 0, "ship_sol_cat": "Small Active Container", "full_ship_sol_nm": "Envirotainer RKN E1", "ship_sol_prop": 0.5, "temperature": "Cold" }, { "ship_sol_std_nm": "envirotainer_rap_e2", "tot_shipped_pallets": 0, "ratio": 0, "ship_sol_cat": "Large Active Container", "full_ship_sol_nm": "Envirotainer RAP E2", "ship_sol_prop": 0, "temperature": "Cold" } ], "material_type": [ "T - Traded Goods" ], "origin_country": "Israel", "destination_country": "Germany", "volume_breakdown": [ { "volume": 1305955.30859375, "unit": "PC" } ] }, { "source": "3811", "sink": "20", "lats": [ 50.050270080566406, 50.89282989501953 ], "lons": [ 9.041939735412598, 4.462500095367432
A7: TC_GetStatus | B7: /nmt/api/v1/status/ | C7: GET | D7: {} | E7: 200 | F7: { "message": "OK" }
A8: TC_Update_NmtScenario | B8: /nmt/api/v1/nmt/scenarios/{scenario_id} | C8: PATCH | D8: { "no_advance_calculation": true, "transport_lane_calculation": false, "scenario_name": "string", "scenario_description": "string", "users": [ "string" ], "access_level": "string", "forecast_version": "string", "start_date": "string", "end_date": "string", "volume_type": "Demand", "validation_params": { "lanes": [ { "source": "string", "sink": "string", "lats": [ 0 ], "lons": [ 0 ], "color": "string", "country_color": "string", "volume": 0, "skus": 0, "sku_set": "string", "total_weight": 0, "transport_cost": 0, "transport_cost_lo": 0, "transport_cost_up": 0, "transport_cost_road": 0, "transport_cost_air": 0, "transport_cost_sea": 0, "transport_cost_warning_flag": true, "co2": 0, "co2_road": 0, "co2_air": 0, "co2_sea": 0, "num_shipments": 0, "controlled_shipments": 0, "cold_shipments": 0, "normal_shipments": 0, "num_shipments_air_amb": 0, "num_shipments_road_amb": 0, "num_shipments_sea_amb": 0, "num_shipments_air_cold": 0, "num_shipments_road_cold": 0, "num_shipments_sea_cold": 0, "volume_pallets": 0, "volume_air_amb": 0, "volume_road_amb": 0, "volume_sea_amb": 0, "volume_air_cold": 0, "volume_road_cold": 0, "volume_sea_cold": 0, "aws_road_flag": true, "sea_flag": true, "road_distance": 0, "sea_distance": 0, "sea_road_part": 0, "air_distance": 0, "air_road_part": 0, "transp_lead_time_average": 0, "lt_sea": 0, "lt_road": 0, "lt_air": 0, "certainty_score": 0, "aggr_level_air_amb": "string", "aggr_level_road_amb": "string", "aggr_level_sea_amb": "string", "aggr_level_air_cold": "string", "aggr_level_road_cold": "string", "aggr_level_sea_cold": "string", "consolidation_score": 0, "has_road": true, "has_air": true, "has_sea": true, "u_description": "string", "v_description": "string", "u_city": "string", "v_city": "string", "is_sanctioned_lane": true, "source_subregion": "string", "source_region": "string", "destination_subregion": "string", "destination_region": "string", "consolidated_air": 0, "consolidated_sea": 0, "consolidated_road": 0, "enforced_air": 0, "enforced_sea": 0, "enforced_road": 0, "source_closest_airports": {}, "target_closest_airports": {}, "source_closest_seaports": {}, "target_closest_seaports": {}, "ship_sol_weight": 0, "shipping_solutions": [], "suggested_shipping_solutions": [], "material_type": [], "origin_country": "string", "destination_country": "string", "volume_breakdown": [] } ], "selected_rows": [ "string" ], "air_defined": 0, "sea_defined": 0, "road_defined": 0, "mode": "string", "consolidation": 0, "shipments_enforced": 0, "shipping_solutions": [] }, "flows": [ { "nodes": [ { "site_id": "string", "description": "string", "country": "string" } ], "routed_nodes": [ "string" ], "market_iso2": "string", "trade_name": "string", "operating_unit": "string", "temperature_range": "string", "controlled_drugs": "string", "plm_status": "string", "sku_description": "string", "country_description": "string", "gross_weight": 0, "quantity_per_pal": 0, "tariff_details": [], "quantity_demand": [ { "lane_id": "string", "volume": 0 } ], "quantity_supply": [ { "lane_id": "string", "volume": 0 } ], "material_text": "string", "customer_code_in_ibp": "string", "finance_country_code": "string", "unit_of_measure": "string", "material_type": "string", "weight_unit": "string", "material_clean": "string", "temperature_detailed": "string", "flow_type": "Scope", "region_description": "string", "sub_region_description": "string", "node_version_ids": [ "string" ], "distrib_sites": "string", "flow_key": 0, "index": "string", "distribuition_site_1": "", "distribuition_site_2": "", "distribuition_site_3": "", "distribuition_site_4": "", "distribuition_site_5": "" } ], "edited_flows": [ { "index": "string", "new_distrib_sites": "string" } ], "reroute_flows": [ { "template_index": [ "string" ], "mode": "string", "nodes": [ "string" ] } ], "lanes": [ { "from_lane": "string", "to_lane": "string", "temperature": "string", "air": 0, "road": 0, "sea": 0, "air_cons": 0, "road_cons": 0, "sea_cons": 0, "air_shipments": 0, "road_shipments": 0, "sea_shipments": 0, "air_ship_sol": { "additionalProp1": 0, "additionalProp2": 0, "additionalProp3": 0 } } ], "updated_lanes": [ { "updated_type": "string", "number_of_pallets": 0, "number_of_shipments": 0, "number_of_lanes": 0, "affected_rows": [ "string" ], "change": "string", "air_defined": 0, "sea_defined": 0, "road_defined": 0, "mode": "string", "consolidation": 0, "shipments_enforced": 0 } ], "custom_node": [ { "node_id": "string", "node_type": "string", "node_sub_type": "string", "node_country": "string", "node_postal_code": "string", "node_address": "string", "node_city": "string", "node_description": "string", "node_iso": "string", "node_latitude": 0, "node_longitude": 0, "distance_from_node": [ { "nodes": [ "string" ], "units_of_measure": "kilometer", "distance": 0 } ] } ], "tariff_changes": [], "warehouse_changes": { "brand": [ {} ], "node": [ {} ] } } | E8: 200 | F8: { "status": "Success", "data": { "scenario_id": "{scenario_id}" "task_id": "{task_id}", "message": "Record updated successfully", "details": null }, "error": null }
A9: TC_Get_Brands_Market | B9: /nmt/api/v1/nmt/scenarios/{scenario_id}/brands-markets?has_brands=true&has_markets=true | C9: GET | D9: {} | E9: 200 | F9: { "status": "Success", "data": { "scenario_details": { "brands": [ "OTHER BIOTHERAPEUTICS", "CUVITRU", "ADVATE", "GAMMAGARD KIOVIG LIQUID" ], "markets": [ "Argentina", "Switzerland", "Germany" ] } }, "error": null }

Sheet API Test Inputs
A1: TC No | B1: Team Name | C1: QE Resource | D1: EndPoint | E1: TestCaseName | F1: Method | G1: Payload | H1: ExpectedStatusCode | I1: Expected Response | J1: Extracted_Key
A2: 1 | B2: AI_Chat | C2: Alok Kumar | D2: /genai/graphql | E2: verifyCreateConversation | F2: POST | G2: {"query":"mutation MyMutation {\n create_conversation(\n inputs: {scope_id: \"04b7fc60-63bd-44d7-bcbf-09d1476fa0aa\", conversation_name: \"Created Conv by Automation\", conversation_id: \"{conversation_id}\", created_timestamp: \"{current_timeStamp}\", owned_by_user_id: 50395262, shared_by_user_id : 50395262}\n ) {\n data {\n conversation_id\n conv_own_emp_id\n conversation_name\n created_timestamp\n last_msg_timestamp\n scope_id\n shared_by_user_id\n }\n message\n status\n }\n}"} | H2: 200 | I2: {"data":{"create_conversation":{"data":[{"conversation_id":"{conversation_id}","conv_own_emp_id":50395262,"conversation_name":"Created Conv by Automation","scope_id":"04b7fc60-63bd-44d7-bcbf-09d1476fa0aa","shared_by_user_id":50395262}],"message":"Conversation created successfully","status":"Created"}}} | J2: conversation_id
A3: 2 | B3: AI_Chat | C3: Alok Kumar | D3: /genai/graphql | E3: verifyCreateMessage | F3: POST | G3: {"query":"mutation MyMutation { create_message( input: {prompt: \"{\\\"task\\\": \\\"\\\", \\\"scope\\\": \\\"\\\", \\\"context\\\": \\\"\\\", \\\"user_text\\\": \\\"What is PIC?\\\", \\\"custom_instruction\\\": \\\"\\\"}\", response: \"{\\\"long_response\\\": {\\\"graph\\\": [], \\\"table\\\": []}, \\\"short_response\\\": \\\"## Predictive Insights Center (PIC)\\\\n\\\\nThe **Predictive Insights Center (PIC)** is a strategic initiative driving Takeda's digital transformation through:\\\\n\\\\n- **Centralized Data Platform**: Unifies data from GMS/GQ systems into one source\\\\n- **AI Integration**: Provides automated, AI-driven prescriptive analytics\\\\n- **Cross-Functional Collaboration**: Bridges data silos between teams and departments\\\\n- **Decision Support**: Enables proactive, predictive decision-making\\\\n\\\\n### Key Features:\\\\n- Replaces fragmented tools with integrated digital solutions\\\\n- Facilitates end-to-end process orchestration\\\\n- Embeds AI for advanced predictive analytics\\\\n- Aims for faster, smarter operational decisions\\\\n\\\\n*Vision 2030 Goal*: Establish a single-source-of-truth environment for enterprise-wide insights.\\\", \\\"reasoning_response\\\": \\\"\\\"}\", prompt_datetime: \"{current_timeStamp}\", response_datetime: \"{current_timeStamp}\", prompt_emp_id: 50395262, conversation_id: \"{conversation_id}\", task_id: \"cc5f121d-f478-4f83-a88e-f092ae29e921\"} ) { message status data { message_id prompt response task_id user_rating conversation_id } }}"} | H3: 200 | I3: {"data":{"create_message":{"message":"Message created successfully","status":"Created","data":[{"message_id":"{message_id}","prompt":{"task":"","scope":"","context":"","user_text":"What is PIC?","custom_instruction":""},"response":{"long_response":{"graph":[],"table":[]},"reasoning_response":""},"task_id":"cc5f121d-f478-4f83-a88e-f092ae29e921","conversation_id":"{conversation_id}"}]}}} | J3: message_id
A4: 3 | B4: AI_Chat | C4: Alok Kumar | D4: /genai/graphql | E4: verifyFetchConversation | F4: POST | G4: {"operationName":"GetConversationName","variables":{},"query":"query GetConversationName {\n fetch_conversations(\n conversation_ids: \"{conversation_id}\"\n for_current_user: true\n scope_id: \"04b7fc60-63bd-44d7-bcbf-09d1476fa0aa\"\n ) {\n conversations {\n conversation_id\n conversation_name\n __typename\n }\n __typename\n }\n}"} | H4: 200 | I4: {"data":{"fetch_conversations":{"conversations":[{"conversation_id":"{conversation_id}","__typename":"Conversation"}],"__typename":"PaginatedConversations"}}}
A5: 4 | B5: AI_Chat | C5: Alok Kumar | D5: /genai/graphql | E5: verifyFetchMessage | F5: POST | G5: {"operationName":"UserGroupMemberId","variables":{},"query":"query UserGroupMemberId {\n fetch_messages(\n conversation_ids: [\"{conversation_id}\"]\n for_current_user: true\n task_id: \"cc5f121d-f478-4f83-a88e-f092ae29e921\"\n ) {\n messages {\n message_id\n conversation_id\n prompt\n prompt_created_ts\n response\n response_created_ts\n src_type\n user_rating\n prompted_by_emp_id\n gen_ai_audit\n task_id\n __typename\n }\n page_info {\n has_next_page\n has_previous_page\n start_cursor\n end_cursor\n __typename\n }\n __typename\n }\n}"} | H5: 200 | I5: {"data":{"fetch_messages":{"messages":[{"message_id":"{message_id}","conversation_id":"{conversation_id}","prompt":{"task":"","scope":"","context":"","user_text":"What is PIC?","custom_instruction":""},"response":{"long_response":{"graph":[],"table":[]},"reasoning_response":""},"src_type":"GEN_AI","prompted_by_emp_id":"50395262","task_id":"cc5f121d-f478-4f83-a88e-f092ae29e921"}],"page_info":{"has_next_page":false,"has_previous_page":false}}}}
A6: 5 | B6: AI_Chat | C6: Alok Kumar | D6: /genai/graphql | E6: verifyUpdateConversation | F6: POST | G6: {"operationName":"UpdateConversation","variables":{},"query":"mutation UpdateConversation {\n update_conversation(\n inputs: {scope_id: \"04b7fc60-63bd-44d7-bcbf-09d1476fa0aa\", conversation_name: \"Updated Conv by Automation\", conversation_id: \"{conversation_id}\"}\n ) {\n message\n status\n __typename\n }\n}"} | H6: 200 | I6: {"data":{"update_conversation":{"message":"Conversation updated successfully","status":"Updated","__typename":"ConversationResponse"}}}
A7: 6 | B7: AI_Chat | C7: Alok Kumar | D7: /genai/graphql | E7: verifyUpdateMessage | F7: POST | G7: {"operationName":"MyMutation","variables":{},"query":"mutation MyMutation {\n update_message(\n input: {message_id: \"{message_id}\", user_rating: 3}\n ) {\n data {\n conversation_id\n user_rating\n message_id\n task_id\n __typename\n }\n message\n status\n __typename\n }\n}"} | H7: 200 | I7: {"data":{"update_message":{"data":[{"conversation_id":"{conversation_id}","user_rating":3,"message_id":"{message_id}","task_id":"cc5f121d-f478-4f83-a88e-f092ae29e921","__typename":"MessageResponse"}],"message":"Message updated successfully","status":"Updated","__typename":"StandardResponse"}}}

Sheet Make_Vienna_API_Suite
A1: TestCaseName | B1: EndPoint | C1: Method | D1: Payload | E1: ExpectedStatusCode | F1: Expected Response | G1: Extracted Key
A2: TC1_ Make_Vienna_Create_Raw_Txn | B2: /kpi/api/v1/metrics/metric-raw-txn-details | C2: POST | D2: {"dimensions":{"Opu":"PLASMA","site":"VIENNA","prod_brand_nm":"PROTEIN C","proc_stg":"FDP"},"work_order":5761787,"work_order_request_date":null,"material_description":null,"lot_number":"A1A305AA","packaging_line":null,"product_group":null,"actual_data":{"packaging":{"end_date":"2025-03-07T09:00:00","admin":"vikram-kumar.sinha@takeda.com"},"finishing":{"end_date":"2025-03-09T06:17:00","admin":"vikram-kumar.sinha@takeda.com"},"qa_review":{"end_date":"2025-03-12T08:58:00","admin":"vikram-kumar.sinha@takeda.com"},"mfg_approval":{"end_date":"2025-04-12T15:15:15","admin":"vikram-kumar.sinha@takeda.com"},"qa_approval":{"end_date":"2025-04-14T08:00:00","admin":"vikram-kumar.sinha@takeda.com"}},"first_defect_date_qa_review":"2025-03-12T08:58:00","defects_count_total_doc_errors_per_batch":null,"urgent_flag":"N","comment":null,"deviation_number":null,"reason_for_delay":null} | E2: 200 | F2: {"status":"Success","data":{"message":"Metrics Raw Transactions details created/updated successfully."},"error":null} | G2: ""
A3: TC2_ Make_Vienna_Create_Raw_Txn | B3: /kpi/api/v1/metrics/metric-raw-txn-details | C3: POST | D3: {"dimensions":{"Opu":"PLASMA","site":"VIENNA","prod_brand_nm":"PROTEIN C","proc_stg":"FDP"},"work_order":5761787,"work_order_request_date":null,"material_description":null,"lot_number":"A1B134AAP1","packaging_line":null,"product_group":null,"actual_data":{"packaging":{"end_date":"2024-01-02T15:00:00","admin":"vikram-kumar.sinha@takeda.com"},"finishing":{"end_date":"2024-01-03T16:00:00","admin":"vikram-kumar.sinha@takeda.com"},"qa_review":{"end_date":"2024-01-04T09:00:00","admin":"vikram-kumar.sinha@takeda.com"},"mfg_approval":{"end_date":"2024-01-05T15:00:00","admin":"vikram-kumar.sinha@takeda.com"},"qa_approval":{"end_date":"2024-01-06T22:00:00","admin":"vikram-kumar.sinha@takeda.com"}},"defects_count_total_doc_errors_per_batch":null,"urgent_flag":"N","comment":null,"deviation_number":null,"reason_for_delay":null} | E3: 200 | F3: {"status":"Success","data":{"message":"Metrics Raw Transactions details created/updated successfully."},"error":null} | G3: ""
A4: TC3_ Make_Vienna_Create_Raw_Txn | B4: /kpi/api/v1/metrics/metric-raw-txn-details | C4: POST | D4: {"dimensions":{"Opu":"PLASMA","site":"VIENNA","prod_brand_nm":"PROTEIN C","proc_stg":"FDP"},"work_order_request_date":null,"material_description":null,"lot_number":"A1B488AA","packaging_line":null,"product_group":null,"actual_data":{"packaging":{"end_date":"2024-11-18T08:00:00","admin":"vikram-kumar.sinha@takeda.com"},"finishing":{"end_date":"2024-11-18T20:00:00","admin":"vikram-kumar.sinha@takeda.com"},"qa_review":{"end_date":"2024-11-19T09:00:00","admin":"vikram-kumar.sinha@takeda.com"},"mfg_approval":{"end_date":"2024-11-19T21:00:00","admin":"vikram-kumar.sinha@takeda.com"},"qa_approval":{"end_date":"2024-11-20T07:00:00","admin":"vikram-kumar.sinha@takeda.com"}},"defects_count_total_doc_errors_per_batch":null,"urgent_flag":"N","comment":null,"deviation_number":null,"reason_for_delay":null} | E4: 200 | F4: {"status":"Success","data":{"message":"Metrics Raw Transactions details created/updated successfully."},"error":null} | G4: ""
A5: TC4_ Make_Vienna_Create_Raw_Txn | B5: /kpi/api/v1/metrics/metric-raw-txn-details | C5: POST | D5: {"dimensions":{"Opu":"PLASMA","site":"VIENNA","prod_brand_nm":"PROTEIN C","proc_stg":"FDP"},"work_order_request_date":null,"material_description":null,"lot_number":"A1A066AAP1","packaging_line":null,"product_group":null,"actual_data":{"packaging":{"end_date":"2023-01-23T07:00:00","admin":"vikram-kumar.sinha@takeda.com"},"finishing":{"end_date":"2023-01-23T14:00:00","admin":"vikram-kumar.sinha@takeda.com"},"qa_review":{"end_date":"2023-01-24T08:00:00","admin":"vikram-kumar.sinha@takeda.com"},"mfg_approval":{"end_date":"2023-01-24T16:00:00","admin":"vikram-kumar.sinha@takeda.com"},"qa_approval":{"end_date":"2023-01-25T06:00:00","admin":"vikram-kumar.sinha@takeda.com"}},"defects_count_total_doc_errors_per_batch":null,"urgent_flag":"N","comment":null,"deviation_number":null,"reason_for_delay":null} | E5: 200 | F5: {"status":"Success","data":{"message":"Metrics Raw Transactions details created/updated successfully."},"error":null} | G5: ""
A6: TC5_ Make_Vienna_Create_Raw_Txn | B6: /kpi/api/v1/metrics/metric-raw-txn-details | C6: POST | E6: 201 | F6: {"status":"Success","data":{"message":"Metrics Raw Transactions details created/updated successfully."},"error":null} | G6: ""
A7: TC6_Verify_Swimlane_EndDate_History | B7: /logger/api/v1/logs/batches_event_logging/swimlane_name?param1_name=batch_number&param1_value=B5X016AAP1 | C7: GET | E7: 200 | F7: {"status":"Success","data":{"logs":[]}}
A8: TC7_Verify_Swimlane_EndDate_History_Negative | B8: /logger/api/v1/logs/batches_event_logging/swimlane_name?param1_name=batch_number | C8: GET | E8: 400 | F8: {"status":"Failure"}
A9: TC8_Verify_v2_boards_API_with_query_params | B9: /batches/api/v2/boards/make/FDP/B5X016AAP1/Finishing | C9: GET | E9: 404 | F9: {"detail":"Not Found"}
A10: TC9_Verify_v2_boards_API_without_query_params | B10: /batches/api/v2/boards | C10: GET | E10: 404 | F10: {"detail":"Not Found"}
A11: TC10_ Make_Vienna_Get_Batch_List | B11: /batches/api/v3/batch-list?board_type=Make&opu=PLASMA&site=VIENNA&process=FINISHED%20DRUG%20PRODUCT&page=1&limit=25&status=At%20Risk%7COn%20Track%7COverdue&sort_by=swimlane_start_date&all_combination=false | C11: GET | D11: {} | E11: 200 | F11: {"status":"Success","data":{"batches_data":[{"name":"Finishing Admin","id":1},{"name":"QA Review","id":2},{"name":"MFG Approval","id":3},{"name":"QA Approval","id":4},{"name":"Ready for Disposition","id":55}],"pagination":{"page":1,"limit":20}}} | G11: ""

Sheet Gen_AI_API
A1: TestCaseName | B1: EndPoint | C1: Method | D1: Payload | E1: ExpectedStatusCode | F1: Expected Response | G1: Extracted Key
A2: TC1_GenAI_VerifyCreateConversation | B2: /genai/graphql | C2: POST | D2: mutation MyMutation { create_conversation( inputs: { scope_id: "04b7fc60-63bd-44d7-bcbf-09d1476fa0aa", conversation_name: "Conv created by Automation", conversation_id: "{generated_uuid}", created_timestamp: "{timestamp}", owned_by_user_id: 50395262, shared_by_user_id: 50395262 } ) { data { conversation_id conv_own_emp_id conversation_name created_timestamp last_msg_timestamp scope_id shared_by_user_id } message status } } | E2: 200 | F2: {"data":{"create_conversation":{"data":[{"conversation_id":"{conversation_id}","conv_own_emp_id":50395262,"conversation_name":"Conv created by Automation","scope_id":"04b7fc60-63bd-44d7-bcbf-09d1476fa0aa","shared_by_user_id":50395262}],"message":"Conversation created successfully","status":"Created"}},"errors":[{"message":"'str' object has no attribute 'isoformat'","path":["create_conversation","data",0,"created_timestamp"]}]} | G2: conversation_id
A3: TC2_GenAI_VerifyCreateMessage | B3: /genai/graphql | C3: POST | D3: mutation MyQuery { create_gen_ai_interaction( input: { prompt_details: { user_text: "What is takeda?" } scope_id: "04b7fc60-63bd-44d7-bcbf-09d1476fa0aa" task_id: "cc5f121d-f478-4f83-a88e-f092ae29e921" conversation_id: "{conversation_id}" } ) { data { conversation_id conversation_name created_by_user_id created_timestamp gen_ai_aud message_id owned_by_user_id prompt response response_timestamp src_type user_rating __typename } message status __typename } } | E3: 200 | F3: {"data":{"create_gen_ai_interaction":{"data":{"conversation_id":"{conversation_id}","conversation_name":"New Conversation","created_by_user_id":"50395262","message_id":"{message_id}","owned_by_user_id":"50395262","prompt":{"user_text":"What is takeda?"},"response":{"short_response":"","long_response":{"graph":[],"table":[]},"recommended_questions":[]},"src_type":"GenAI","user_rating":null,"__typename":"GenAIQueryResponse"},"message":"Query is being processed","status":"acknowledgement","__typename":"GenAIInteraction"}}} | G3: message_id
A4: TC3_GenAI_VerifyFetchConversation | B4: /genai/graphql | C4: POST | D4: query MyQuery { fetch_conversations( scope_id: "04b7fc60-63bd-44d7-bcbf-09d1476fa0aa" conversation_ids: "{conversation_id}" ) { conversations { conv_own_emp_id conversation_id conversation_name created_timestamp last_msg_timestamp scope_id shared_by_user_id } } } | E4: 200 | F4: {"data":{"fetch_conversations":{"conversations":[{"conv_own_emp_id":50395262,"conversation_id":"{conversation_id}","conversation_name":"Conv created by Automation","scope_id":"04b7fc60-63bd-44d7-bcbf-09d1476fa0aa","shared_by_user_id":50395262}]}}}
A5: TC4_GenAI_VerifyFetchMessage | B5: /genai/graphql | C5: POST | D5: query MyQuery { fetch_messages( conversation_ids: "{conversation_id}" task_id: "cc5f121d-f478-4f83-a88e-f092ae29e921" ) { messages { conversation_id gen_ai_audit message_id prompt prompt_created_ts prompted_by_emp_id response response_created_ts task_id src_type } } } | E5: 200 | F5: { "data": { "fetch_messages": { "messages": [ { "conversation_id": "{conversation_id}", "gen_ai_audit": {}, "message_id": "{message_id}", "prompt": { "task": "", "scope": "", "context": "", "user_text": "What is takeda?", "custom_instruction": "" }, "prompted_by_emp_id": 50395262, "response": { "long_response": { "graph": [], "table": [] }, "short_response": "", "reasoning_response": "**Processing query**: The system is now generating a response and will update as more information becomes available.", "recommended_questions": [] }, "task_id": "cc5f121d-f478-4f83-a88e-f092ae29e921", "src_type": "GEN_AI" } ] } } }
A6: TC5_GenAI_VerifyUpdateConversation | B6: /genai/graphql | C6: POST | D6: mutation MyMutation { update_conversation( inputs: { conversation_id: "{conversation_id}" scope_id: "04b7fc60-63bd-44d7-bcbf-09d1476fa0aa" conversation_name: "Updated Conversation by automation" } ) { message status data { conv_own_emp_id conversation_id conversation_name created_timestamp last_msg_timestamp scope_id shared_by_user_id } } } | E6: 200 | F6: {"data":{"update_conversation":{"message":"Conversation updated successfully","status":"Updated","data":[{"conv_own_emp_id":50395262,"conversation_id":"{conversation_id}","conversation_name":"Updated Conversation by automation","scope_id":"04b7fc60-63bd-44d7-bcbf-09d1476fa0aa","shared_by_user_id":50395262}]}},"errors":[{"message":"'str' object has no attribute 'isoformat'","locations":[{"line":15,"column":13}],"path":["update_conversation","data",0,"created_timestamp"]}]}
A7: TC6_GenAI_VerifyDeleteConversation | B7: /genai/graphql | C7: POST | D7: mutation MyMutation { delete_conversation( inputs: { scope_id: "04b7fc60-63bd-44d7-bcbf-09d1476fa0aa" conversation_ids: "{conversation_id}" } ) { message status } } | E7: 200 | F7: { "data": { "delete_conversation": { "message": "Conversation deleted successfully", "status": "Deleted" } } }

Sheet Risk
A1: TestCaseName | B1: EndPoint | C1: Method | D1: Payload | E1: ExpectedStatusCode | F1: Expected Response | G1: Extracted Key
A2: https://api-insights-test2.takeda.io/ | B2: risks/api/v1/comprehensive-risks | C2: POST | D2: {"products":null,"risk_id":null,"risk_type_id":null,"key_risk":null,"impacted_site_ids":null,"risk_category_ids":null,"impact_range_ids":null,"mitigation":true,"opu_ids":null,"page":1,"limit":10,"search_keyword":"","financial_impact_range_ids":null,"risk_state_id":null,"risk_owner_id":null,"overall_likelihood_type_id":null,"risk_mitigation_type":null,"overall_ptrb_type_id":null,"risk_phase_ids":null,"risk_universe_ids":[]} | E2: 200 | F2: { "status": 200, "message": "success", "data": { "risks": [ { "id": 2821, "type": { "id": 1, "value": "Single-Product" }, "category": { "id": "72a65ee7-564d-49a8-a096-5ab993f763e2", "value": "Compliance and data integrity breaches (lack of life-cycle, inadequate access management, unethical use of new technologies)" }, "description": "string", "creation_date": "2025-08-20", "closure_date": null, "last_updated_timestamp": "2025-08-23T18:57:49.779787", "is_key_risk": false, "is_confidential_risk": false, "phase": { "id": 1, "value": "Identification" }, "state": { "id": 1, "value": "Active" }, "owner": { "display_name": "Sagar Shivaji Kadam ", "email_id": "sagar-shivaji.kadam@takeda.com" }, "organisation_unit": { "id": null, "value": null }, "risk_score_value": null, "impacted_products": [ "ADVATE" ], "impacted_sites": [], "risk_universe": "Data, Digital & Technology / Information Protection", "mitigation_type": { "id": null, "value": null }, "impact_range": { "id": null, "value": null }, "process_steps": [], "active_mitigation_plan_count": null, "note": null, "current_risk_impact": { "impact_patient": { "id": null, "value": null }, "impact_trust": { "id": null, "value": null }, "impact_reputation": { "id": null, "value": null }, "impact_business": { "id": null, "value": null }, "financial_impact_amount": null, "overall_ptrb": { "id": null, "value": null }, "overall_likelihood": { "id": null, "value": null }, "risk_score_value": null, "impact_assessment_comment": null }, "future_risk_impact": { "impact_patient": { "id": null, "value": null }, "impact_trust": { "id": null, "value": null }, "impact_reputation": { "id": null, "value": null }, "impact_business": { "id": null, "value": null }, "financial_impact_amount": null, "overall_ptrb": { "id": null, "value": null }, "overall_likelihood": { "id": null, "value": null }, "risk_score_value": null, "impact_assessment_comment": null }, "mitigations": [], "associated_risks": [] } ], "pagination": { "total_count": 1, "total_pages": 1, "current_page": 1, "limit": 10 } } } | G2: ""
A3: https://api-insights-test2.takeda.io/ | B3: risks/api/v1/mitigation-plan?risk_ids=2821&page=1&sort_order=asc | C3: GET | D3: {"products":null,"risk_id":null,"risk_type_id":null,"key_risk":null,"impacted_site_ids":null,"risk_category_ids":null,"impact_range_ids":null,"mitigation":true,"opu_ids":null,"page":1,"limit":10,"search_keyword":"","financial_impact_range_ids":null,"risk_state_id":null,"risk_owner_id":null,"overall_likelihood_type_id":null,"risk_mitigation_type":null,"overall_ptrb_type_id":null,"risk_phase_ids":null,"risk_universe_ids":[]} | E3: 200 | F3: { "status": 200, "message": "success", "data": { "mitigation_plans": [], "pagination": { "total_count": 0, "total_pages": 1, "current_page": 1, "limit": 0 }, "sorting": { "sort_by": null, "sort_order": "asc" } } } | G3: ""
A4: https://api-insights-test2.takeda.io/ | B4: risks/api/v1/mitigation-plan?risk_ids=2808&risk_type_ids=1&page=1&sort_order=asc | C4: GET | D4: {"products":null,"risk_id":null,"risk_type_id":null,"key_risk":null,"impacted_site_ids":null,"risk_category_ids":null,"impact_range_ids":null,"mitigation":true,"opu_ids":null,"page":1,"limit":10,"search_keyword":"","financial_impact_range_ids":null,"risk_state_id":null,"risk_owner_id":null,"overall_likelihood_type_id":null,"risk_mitigation_type":null,"overall_ptrb_type_id":null,"risk_phase_ids":null,"risk_universe_ids":[]} | E4: 200 | F4: { "status": 200, "message": "success", "data": { "mitigation_plans": [ { "plan_id": 4767, "plan_description": "dfsfds", "state_description": "", "owner": { "display_name": "Raj M, Arun Prakash (ext)", "email_id": "arun-prakash.raj-m@takeda.com" }, "due_date": null, "closed_date": null, "progress": null, "risk_id": 2808, "risk_type": { "id": 1, "value": "Single-Product" }, "risk_description": "atestatew fsadfsafd", "impacted_products": [ "ADVATE" ], "impacted_sites": [] } ], "pagination": { "total_count": 1, "total_pages": 1, "current_page": 1, "limit": 1 }, "sorting": { "sort_by": null, "sort_order": "asc" } } }
A5: https://api-insights-test2.takeda.io/ | B5: risks/api/v1/mitigation-plan?due_date=2025-07-22&risk_type_ids=1&page=1&sort_order=asc | C5: GET | D5: {"products":null,"risk_id":null,"risk_type_id":null,"key_risk":null,"impacted_site_ids":null,"risk_category_ids":null,"impact_range_ids":null,"mitigation":true,"opu_ids":null,"page":1,"limit":10,"search_keyword":"","financial_impact_range_ids":null,"risk_state_id":null,"risk_owner_id":null,"overall_likelihood_type_id":null,"risk_mitigation_type":null,"overall_ptrb_type_id":null,"risk_phase_ids":null,"risk_universe_ids":[]} | E5: 200 | F5: { "status": 200, "message": "success", "data": { "mitigation_plans": [ { "plan_id": 4770, "plan_description": "sdf", "state_description": "", "owner": { "display_name": "Sagar Shivaji Kadam ", "email_id": "sagar-shivaji.kadam@takeda.com" }, "due_date": "2025-07-22", "closed_date": null, "progress": { "id": 3, "value": "Overdue" }, "risk_id": 2813, "risk_type": { "id": 1, "value": "Single-Product" }, "risk_description": "555", "impacted_products": [ "ADYNOVATE" ], "impacted_sites": [] }, { "plan_id": 4771, "plan_description": "Test", "state_description": "", "owner": { "display_name": "Sagar Shivaji Kadam ", "email_id": "sagar-shivaji.kadam@takeda.com" }, "due_date": "2025-07-22", "closed_date": null, "progress": { "id": 3, "value": "Overdue" }, "risk_id": 2814, "risk_type": { "id": 1, "value": "Single-Product" }, "risk_description": "2814", "impacted_products": [ "FEIBA" ], "impacted_sites": [] } ], "pagination": { "total_count": 2, "total_pages": 1, "current_page": 1, "limit": 2 }, "sorting": { "sort_by": null, "sort_order": "asc" } } }
A6: https://api-insights-test2.takeda.io/ | B6: risks/api/v1/product-details | C6: POST | D6: { "products": [ "string" ] } | E6: 200 | F6: { "status": 200, "message": "success", "data": [] } | G6: ""
A7: https://api-insights-test2.takeda.io/ | B7: risks/api/v1/params/data?assessment_cycle_state=active&ptrb_type=patient | C7: GET | D7: { "products": [ "string" ] } | E7: 200 | F7: { "status": 200, "message": "success", "data": [ { "assessment_cycle_id": 10, "budget_cycle": "MYC", "fiscal_years": "FY2028-30", "cycle_state_id": 2, "cycle_state": "in progress", "risk_params_data": { "impact": { "very_high": { "products": [ "ADVATE", "CEPROTIN", "FAZIRISAN (TAK-999)", "GATTEX/REVESTIVE" ] }, "high": { "products": [] }, "medium": { "products": [ "ADYNOVATE", "ELAPRASE", "ENTYVIO", "GAMMAGARD SD / LOW IGA", "LEUPRORELIN", "MEPACT", "REPLAGAL", "TAK-141 PABINAFUSP ALFA", "VPRIV", "VYVANSE", "ZASOCITINIB (TAK-279)", "ZEJULA" ] }, "low": { "products": [ "ADCETRIS", "ADZYNMA (TAK-755)", "ALBUMIN", "ALOFISEL", "ALUNBRIG", "CABOZANTINIB", "CINRYZE", "CUVITRU", "DEXILANT", "EOHILIA", "EXKIVITY", "FEIBA", "FIRAZYR", "FLEXBUMIN", "FRUZAQLA", "GAMMAGARD LIQUID/KIOVIG", "HYQVIA", "ICLUSIG", "KALBITOR", "LANSOPRAZOLE", "LIVTENCITY", "NATPARA", "NINLARO", "OBIZUR", "PANTOPRAZOLE", "RECOMBINATE", "RIXUBIS", "TAK-935 SOTICLESTAT", "TAKECAB", "TAKHZYRO", "TRINTELLIX", "VECTIBIX", "VELCADE", "VONVENDI" ] } }, "likelihood": { "rare": { "products": [ "ALUNBRIG", "CABOZANTINIB", "CINRYZE", "DEXILANT", "EXKIVITY", "ICLUSIG", "LANSOPRAZOLE", "NATPARA", "PANTOPRAZOLE", "TRINTELLIX", "VECTIBIX", "VELCADE", "ZEJULA" ] }, "unlikely": { "products": [ "ADCETRIS", "ENTYVIO", "EOHILIA", "FEIBA", "FIRAZYR", "FRUZAQLA", "LEUPRORELIN", "MEPACT", "NINLARO", "REPLAGAL", "RIXUBIS", "TAK-141 PABINAFUSP ALFA", "TAK-935 SOTICLESTAT", "TAKECAB", "VONVENDI", "VYVANSE", "ZASOCITINIB (TAK-279)" ] }, "possible": { "products": [ "ADZYNMA (TAK-755)", "ALBUMIN", "CEPROTIN", "CUVITRU", "ELAPRASE", "FLEXBUMIN", "GAMMAGARD LIQUID/KIOVIG", "GAMMAGARD SD / LOW IGA", "HYQVIA", "KALBITOR", "LIVTENCITY", "RECOMBINATE", "VPRIV" ] }, "likely": { "products": [ "ADVATE", "ADYNOVATE", "ALOFISEL", "FAZIRISAN (TAK-999)", "GATTEX/REVESTIVE", "OBIZUR", "TAKHZYRO" ] } } }, "risk_params_combination_data": { "very_high|rare": { "products": [] }, "very_high|unlikely": { "products": [] }, "very_high|possible": { "products": [ "CEPROTIN" ] }, "very_high|likely": { "products": [ "ADVATE", "FAZIRISAN (TAK-999)", "GATTEX/REVESTIVE" ] }, "high|rare": { "products": [] }, "high|unlikely": { "products": [] }, "high|possible": { "products": [] }, "high|likely": { "products": [] }, "medium|rare": { "products": [ "ZEJULA" ] }, "medium|unlikely": { "products": [ "ENTYVIO", "LEUPRORELIN", "MEPACT", "REPLAGAL", "TAK-141 PABINAFUSP ALFA", "VYVANSE", "ZASOCITINIB (TAK-279)" ] }, "medium|possible": { "products": [ "ELAPRASE", "GAMMAGARD SD / LOW IGA", "VPRIV" ] }, "medium|likely": { "products": [ "ADYNOVATE" ] }, "low|rare": { "products": [ "ALUNBRIG", "CABOZANTINIB", "CINRYZE", "DEXILANT", "EXKIVITY", "ICLUSIG", "LANSOPRAZOLE", "NATPARA", "PANTOPRAZOLE", "TRINTELLIX", "VECTIBIX", "VELCADE" ] }, "low|unlikely": { "products": [ "ADCETRIS", "EOHILIA", "FEIBA", "FIRAZYR", "FRUZAQLA", "NINLARO", "RIXUBIS", "TAK-935 SOTICLESTAT", "TAKECAB", "VONVENDI" ] }, "low|possible": { "products": [ "ADZYNMA (TAK-755)", "ALBUMIN", "CUVITRU", "FLEXBUMIN", "GAMMAGARD LIQUID/KIOVIG", "HYQVIA", "KALBITOR", "LIVTENCITY", "RECOMBINATE" ] }, "low|likely": { "products": [ "ALOFISEL", "OBIZUR", "TAKHZYRO" ] } } } ] } | G7: ""
A8: https://api-insights-test2.takeda.io/ | B8: risks/api/v1/params/data?assessment_cycle_state=active&ptrb_type=trust | C8: GET | D8: { "products": [ "string" ] } | E8: 200 | F8: "data": [ { "assessment_cycle_id": 10, "budget_cycle": "MYC", "fiscal_years": "FY2028-30", "cycle_state_id": 2, "cycle_state": "in progress", "risk_params_data": { "impact": { "very_high": { "products": [ "ADVATE", "FAZIRISAN (TAK-999)" ] }, "high": { "products": [] }, "medium": { "products": [ "ADYNOVATE", "ENTYVIO", "GATTEX/REVESTIVE", "LEUPRORELIN", "MEPACT", "REPLAGAL", "TAK-141 PABINAFUSP ALFA", "ZEJULA" ] }, "low": { "products": [ "ADCETRIS", "ADZYNMA (TAK-755)", "ALOFISEL", "CABOZANTINIB", "CINRYZE", "DEXILANT", "FIRAZYR", "GAMMAGARD SD / LOW IGA", "LANSOPRAZOLE", "LIVTENCITY", "OBIZUR", "PANTOPRAZOLE", "TAKECAB", "VECTIBIX", "VELCADE", "VONVENDI", "VPRIV" ] } }, "likelihood": { "rare": { "products": [ "CABOZANTINIB", "CINRYZE", "DEXILANT", "LANSOPRAZOLE", "PANTOPRAZOLE", "VECTIBIX", "VELCADE", "ZEJULA" ] }, "unlikely": { "products": [ "ADCETRIS", "ENTYVIO", "FIRAZYR", "LEUPRORELIN", "MEPACT", "REPLAGAL", "TAK-141 PABINAFUSP ALFA", "TAKECAB", "VONVENDI" ] }, "possible": { "products": [ "ADZYNMA (TAK-755)", "GAMMAGARD SD / LOW IGA", "LIVTENCITY", "VPRIV" ] }, "likely": { "products": [ "ADVATE", "ADYNOVATE", "ALOFISEL", "FAZIRISAN (TAK-999)", "GATTEX/REVESTIVE", "OBIZUR" ] } } }, "risk_params_combination_data": { "very_high|rare": { "products": [] }, "very_high|unlikely": { "products": [] }, "very_high|possible": { "products": [] }, "very_high|likely": { "products": [ "ADVATE", "FAZIRISAN (TAK-999)" ] }, "high|rare": { "products": [] }, "high|unlikely": { "products": [] }, "high|possible": { "products": [] }, "high|likely": { "products": [] }, "medium|rare": { "products": [ "ZEJULA" ] }, "medium|unlikely": { "products": [ "ENTYVIO", "LEUPRORELIN", "MEPACT", "REPLAGAL", "TAK-141 PABINAFUSP ALFA" ] }, "medium|possible": { "products": [] }, "medium|likely": { "products": [ "ADYNOVATE", "GATTEX/REVESTIVE" ] }, "low|rare": { "products": [ "CABOZANTINIB", "CINRYZE", "DEXILANT", "LANSOPRAZOLE", "PANTOPRAZOLE", "VECTIBIX", "VELCADE" ] }, "low|unlikely": { "products": [ "ADCETRIS", "FIRAZYR", "TAKECAB", "VONVENDI" ] }, "low|possible": { "products": [ "ADZYNMA (TAK-755)", "GAMMAGARD SD / LOW IGA", "LIVTENCITY", "VPRIV" ] }, "low|likely": { "products": [ "ALOFISEL", "OBIZUR" ] } } } ] }
A9: https://api-insights-test2.takeda.io | B9: risks/api/v1/params/data?assessment_cycle_state=recently_completed&ptrb_type=reputation | C9: GET | D9: { "products": [ "string" ] } | E9: 200 | F9: { "status": 200, "message": "success", "data": [ { "assessment_cycle_id": 9, "budget_cycle": "MRP", "fiscal_years": "FY2028-30", "cycle_state_id": 4, "cycle_state": "completed", "risk_params_data": { "impact": { "very_high": { "products": [ "ADVATE" ] }, "high": { "products": [ "ALBUMIN", "FLEXBUMIN", "REPLAGAL" ] }, "medium": { "products": [ "ADCETRIS", "ADYNOVATE", "CEPROTIN", "ELAPRASE", "ENTYVIO", "GAMMAGARD SD / LOW IGA", "GATTEX/REVESTIVE", "LEUPRORELIN", "LIVTENCITY", "MEPACT", "TAK-141 PABINAFUSP ALFA", "VYVANSE", "ZEJULA" ] }, "low": { "products": [ "ADZYNMA (TAK-755)", "ALOFISEL", "ALUNBRIG", "CABOZANTINIB", "CUVITRU", "DEXILANT", "EOHILIA", "EXKIVITY", "FEIBA", "FIRAZYR", "FRUZAQLA", "GAMMAGARD LIQUID/KIOVIG", "HYQVIA", "ICLUSIG", "KALBITOR", "LANSOPRAZOLE", "NATPARA", "NINLARO", "OBIZUR", "PANTOPRAZOLE", "RECOMBINATE", "RIXUBIS", "TAK-935 SOTICLESTAT", "TAKECAB", "TAKHZYRO", "TRINTELLIX", "VECTIBIX", "VELCADE", "VONVENDI", "VPRIV", "ZASOCITINIB (TAK-279)" ] } }, "likelihood": { "rare": { "products": [ "ALUNBRIG", "CABOZANTINIB", "DEXILANT", "EXKIVITY", "ICLUSIG", "LANSOPRAZOLE", "NATPARA", "PANTOPRAZOLE", "TRINTELLIX", "VECTIBIX", "VELCADE", "ZEJULA" ] }, "unlikely": { "products": [ "ADCETRIS", "ENTYVIO", "EOHILIA", "FEIBA", "FIRAZYR", "FRUZAQLA", "LEUPRORELIN", "MEPACT", "NINLARO", "REPLAGAL", "RIXUBIS", "TAK-141 PABINAFUSP ALFA", "TAK-935 SOTICLESTAT", "TAKECAB", "VONVENDI", "VYVANSE", "ZASOCITINIB (TAK-279)" ] }, "possible": { "products": [ "ADZYNMA (TAK-755)", "ALBUMIN", "CEPROTIN", "CUVITRU", "ELAPRASE", "FLEXBUMIN", "GAMMAGARD LIQUID/KIOVIG", "GAMMAGARD SD / LOW IGA", "HYQVIA", "KALBITOR", "LIVTENCITY", "RECOMBINATE", "VPRIV" ] }, "likely": { "products": [ "ADVATE", "ADYNOVATE", "ALOFISEL", "GATTEX/REVESTIVE", "OBIZUR", "TAKHZYRO" ] } } }, "risk_params_combination_data": { "very_high|rare": { "products": [] }, "very_high|unlikely": { "products": [] }, "very_high|possible": { "products": [] }, "very_high|likely": { "products": [ "ADVATE" ] }, "high|rare": { "products": [] }, "high|unlikely": { "products": [ "REPLAGAL" ] }, "high|possible": { "products": [ "ALBUMIN", "FLEXBUMIN" ] }, "high|likely": { "products": [] }, "medium|rare": { "products": [ "ZEJULA" ] }, "medium|unlikely": { "products": [ "ADCETRIS", "ENTYVIO", "LEUPRORELIN", "MEPACT", "TAK-141 PABINAFUSP ALFA", "VYVANSE" ] }, "medium|possible": { "products": [ "CEPROTIN", "ELAPRASE", "GAMMAGARD SD / LOW IGA", "LIVTENCITY" ] }, "medium|likely": { "products": [ "ADYNOVATE", "GATTEX/REVESTIVE" ] }, "low|rare": { "products": [ "ALUNBRIG", "CABOZANTINIB", "DEXILANT", "EXKIVITY", "ICLUSIG", "LANSOPRAZOLE", "NATPARA", "PANTOPRAZOLE", "TRINTELLIX", "VECTIBIX", "VELCADE" ] }, "low|unlikely": { "products": [ "EOHILIA", "FEIBA", "FIRAZYR", "FRUZAQLA", "NINLARO", "RIXUBIS", "TAK-935 SOTICLESTAT", "TAKECAB", "VONVENDI", "ZASOCITINIB (TAK-279)" ] }, "low|possible": { "products": [ "ADZYNMA (TAK-755)", "CUVITRU", "GAMMAGARD LIQUID/KIOVIG", "HYQVIA", "KALBITOR", "RECOMBINATE", "VPRIV" ] }, "low|likely": { "products": [ "ALOFISEL", "OBIZUR", "TAKHZYRO" ] } } } ] }
A10: https://api-insights-test2.takeda.io/ | B10: risks/api/v1/params/data?assessment_cycle_state=recently_completed&ptrb_type=business | C10: GET | D10: { "products": [ "string" ] } | E10: 200 | F10: { "status": 200, "message": "success", "data": [ { "assessment_cycle_id": 9, "budget_cycle": "MRP", "fiscal_years": "FY2028-30", "cycle_state_id": 4, "cycle_state": "completed", "risk_params_data": { "impact": { "very_high": { "products": [ "ADYNOVATE" ] }, "high": { "products": [ "ALBUMIN", "FLEXBUMIN", "ZASOCITINIB (TAK-279)" ] }, "medium": { "products": [ "CUVITRU", "GAMMAGARD SD / LOW IGA" ] }, "low": { "products": [ "ADVATE", "EOHILIA", "EXKIVITY", "GAMMAGARD LIQUID/KIOVIG", "GATTEX/REVESTIVE", "VONVENDI" ] } }, "likelihood": { "rare": { "products": [ "EXKIVITY" ] }, "unlikely": { "products": [ "EOHILIA", "VONVENDI", "ZASOCITINIB (TAK-279)" ] }, "possible": { "products": [ "ALBUMIN", "CUVITRU", "FLEXBUMIN", "GAMMAGARD LIQUID/KIOVIG", "GAMMAGARD SD / LOW IGA" ] }, "likely": { "products": [ "ADVATE", "ADYNOVATE", "GATTEX/REVESTIVE" ] } } }, "risk_params_combination_data": { "very_high|rare": { "products": [] }, "very_high|unlikely": { "products": [] }, "very_high|possible": { "products": [] }, "very_high|likely": { "products": [ "ADYNOVATE" ] }, "high|rare": { "products": [] }, "high|unlikely": { "products": [ "ZASOCITINIB (TAK-279)" ] }, "high|possible": { "products": [ "ALBUMIN", "FLEXBUMIN" ] }, "high|likely": { "products": [] }, "medium|rare": { "products": [] }, "medium|unlikely": { "products": [] }, "medium|possible": { "products": [ "CUVITRU", "GAMMAGARD SD / LOW IGA" ] }, "medium|likely": { "products": [] }, "low|rare": { "products": [ "EXKIVITY" ] }, "low|unlikely": { "products": [ "EOHILIA", "VONVENDI" ] }, "low|possible": { "products": [ "GAMMAGARD LIQUID/KIOVIG" ] }, "low|likely": { "products": [ "ADVATE", "GATTEX/REVESTIVE" ] } } } ] }
A11: https://api-insights-test2.takeda.io/ | B11: risks/api/v1/params/data?assessment_cycle_state=active&products=ADVATE&opus=biologics&ptrb_type=patient | C11: GET | D11: { "products": [ "string" ] } | E11: 200 | F11: { "status": 200, "message": "success", "data": [ { "assessment_cycle_id": 10, "budget_cycle": "MYC", "fiscal_years": "FY2028-30", "cycle_state_id": 2, "cycle_state": "in progress", "risk_params_data": { "impact": { "very_high": { "products": [ "ADVATE" ] }, "high": { "products": [] }, "medium": { "products": [] }, "low": { "products": [] } }, "likelihood": { "rare": { "products": [] }, "unlikely": { "products": [] }, "possible": { "products": [] }, "likely": { "products": [ "ADVATE" ] } } }, "risk_params_combination_data": { "very_high|rare": { "products": [] }, "very_high|unlikely": { "products": [] }, "very_high|possible": { "products": [] }, "very_high|likely": { "products": [ "ADVATE" ] }, "high|rare": { "products": [] }, "high|unlikely": { "products": [] }, "high|possible": { "products": [] }, "high|likely": { "products": [] }, "medium|rare": { "products": [] }, "medium|unlikely": { "products": [] }, "medium|possible": { "products": [] }, "medium|likely": { "products": [] }, "low|rare": { "products": [] }, "low|unlikely": { "products": [] }, "low|possible": { "products": [] }, "low|likely": { "products": [] } } } ] }
A12: https://api-insights-test2.takeda.io/ | B12: risks/api/v1/site-details?site_type_ids=2 | C12: GET | D12: {"products":null,"risk_id":null,"risk_type_id":null,"key_risk":null,"impacted_site_ids":null,"risk_category_ids":null,"impact_range_ids":null,"mitigation":true,"opu_ids":null,"page":1,"limit":10,"search_keyword":"","financial_impact_range_ids":null,"risk_state_id":null,"risk_owner_id":null,"overall_likelihood_type_id":null,"risk_mitigation_type":null,"overall_ptrb_type_id":null,"risk_phase_ids":null,"risk_universe_ids":[]} | E12: 200 | F12: { "status": 200, "message": "success", "data": { "site_details": [ { "id": 40, "name": "DC PUERTO RICO (CESAR CASTILLO)", "type": "Distribution", "country": "UNITED STATES OF AMERICA", "opu": null, "region": "", "function": "Supply Chain", "legal_entity": "CESAR CASTILLO LLC", "address": "Rd #1 Km 21.1, PR-1, 00971, Puerto Rico", "is_internal": false, "risk_owner": null, "risk_coordinator": null, "risk_manager": null, "products": [], "site_image_url": "/brand/Risk/dcpuertoricocesar.png" }, { "id": 38, "name": "DC USA – ESPORT (ICS)", "type": "Distribution", "country": "UNITED STATES OF AMERICA", "opu": null, "region": "", "function": "Supply Chain", "legal_entity": "Integrated Commercialization Solutions, LLC", "address": "6450 La Salle Dr, Lockbourne, OH 43137", "is_internal": false, "risk_owner": null, "risk_coordinator": null, "risk_manager": null, "products": [], "site_image_url": "/brand/Risk/dcusaesportics.png" }, { "id": 39, "name": "DC USA – EXPORT (MCKESSON)", "type": "Distribution", "country": "UNITED STATES OF AMERICA", "opu": null, "region": "", "function": "Supply Chain", "legal_entity": "RxCrossroads 3PL LLC", "address": "170 Clermont Rd, STE A, 40165 Shepherdsville, KY", "is_internal": false, "risk_owner": null, "risk_coordinator": null, "risk_manager": null, "products": [], "site_image_url": "/brand/Risk/dcusaexportmckess.png" }, { "id": 28, "name": "EU EXPORT HUB GERMANY (ARVATO)", "type": "Distribution", "country": "Germany", "opu": null, "region": "", "function": "Supply Chain", "legal_entity": "Arvato SE", "address": "Gottlieb-Daimler-Straße 1, 33428 Harsewinkel", "is_internal": false, "risk_owner": { "display_name": "Pascal René Halm", "email_id": "Pascal.Halm@takeda.com" }, "risk_coordinator": { "display_name": "Eduardo Teixeira", "email_id": "eduardo.teixeira@takeda.com" }, "risk_manager": { "display_name": "Italo Rusconi", "email_id": "Italo.Rusconi@takeda.com" }, "products": [], "site_image_url": "/brand/Risk/arvatogermany.png" }, { "id": 30, "name": "GDC CONTROLLED DRUGS GERMANY (UNITAX)", "type": "Distribution", "country": "Germany", "opu": null, "region": "", "function": "Supply Chain", "legal_entity": "UNITAX Pharmalogistik GmbH", "address": "An d. Anhalter Bahn, 14979 Großbeeren, Germany", "is_internal": false, "risk_owner": { "display_name": "Pascal René Halm", "email_id": "Pascal.Halm@takeda.com" }, "risk_coordinator": { "display_name": "Eduardo Teixeira", "email_id": "eduardo.teixeira@takeda.com" }, "risk_manager": { "display_name": "Italo Rusconi", "email_id": "Italo.Rusconi@takeda.com" }, "products": [], "site_image_url": "/brand/Risk/gdccontrolleddrugs.png" }, { "id": 31, "name": "GDC VACCINES BELGIUM (K+N)", "type": "Distribution", "country": "Belgium", "opu": null, "region": "", "function": "Supply Chain", "legal_entity": "Kuehne+Nagel Logistics NV", "address": "Kuehne + Nagel Logistics NV ,Klaus-Michael Kuehnelaan 8,2440, Geel, Belgium", "is_internal": false, "risk_owner": { "display_name": "Pascal René Halm", "email_id": "Pascal.Halm@takeda.com" }, "risk_coordinator": { "display_name": "Eduardo Teixeira", "email_id": "eduardo.teixeira@takeda.com" }, "risk_manager": { "display_name": "Italo Rusconi", "email_id": "Italo.Rusconi@takeda.com" }, "products": [], "site_image_url": "/brand/Risk/gdcvaccines.png" }, { "id": 32, "name": "GERLACH", "type": "Distribution", "country": "Netherlands", "opu": null, "region": "", "function": "Supply Chain", "legal_entity": "Gerlach & Co BV", "address": "van Heemskerckweg 6, NL-5928 LL Venlo, The Netherlands", "is_internal": false, "risk_owner": { "display_name": "Sasank Mohanty", "email_id": "sasank.mohanty@takeda.com" }, "risk_coordinator": null, "risk_manager": { "display_name": "Italo Rusconi", "email_id": "Italo.Rusconi@takeda.com" }, "products": [], "site_image_url": "/brand/Risk/gerlach.png" }, { "id": 33, "name": "IRELAND EXPORT HUB", "type": "Distribution", "country": "Ireland", "opu": null, "region": "", "function": "Supply Chain", "legal_entity": "Takeda Pharmaceutical Company Limited", "address": "Unit 4 Horizon Logistics Park, New Naul Road, Harristown, Co. Dublin, Ireland", "is_internal": false, "risk_owner": { "display_name": "Hiromitsu Ito ", "email_id": "hiromitsu.ito@takeda.com" }, "risk_coordinator": { "display_name": "Hiromi Takami ", "email_id": "hiromi.takami@takeda.com" }, "risk_manager": { "display_name": "Italo Rusconi", "email_id": "Italo.Rusconi@takeda.com" }, "products": [], "site_image_url": "/brand/Risk/irelandexporthub.png" }, { "id": 37, "name": "JP EXPORT HUB (KWE)", "type": "Distribution", "country": "Japan", "opu": null, "region": "", "function": "Supply Chain", "legal_entity": "Takeda Pharmaceutical Company Limited", "address": "2-21, Rinku Orai-Kita, Izumisano-City, Osaka, Japan", "is_internal": false, "risk_owner": { "display_name": "Hiromitsu Ito ", "email_id": "hiromitsu.ito@takeda.com" }, "risk_coordinator": { "display_name": "Hiromi Takami ", "email_id": "hiromi.takami@takeda.com" }, "risk_manager": { "display_name": "Italo Rusconi", "email_id": "Italo.Rusconi@takeda.com" }, "products": [], "site_image_url": "/brand/Risk/rinku.png" }, { "id": 34, "name": "RDC FRANCE (CSP)", "type": "Distribution", "country": "France", "opu": null, "region": "", "function": "Supply Chain", "legal_entity": "CENTRE SPÉCIALITÉS PHARMACEUTIQUES", "address": "CSP, 76-78 Av. du Midi, 63800 Cournon-d'Auvergne, France", "is_internal": false, "risk_owner": { "display_name": "Pascal René Halm", "email_id": "Pascal.Halm@takeda.com" }, "risk_coordinator": { "display_name": "Eduardo Teixeira", "email_id": "eduardo.teixeira@takeda.com" }, "risk_manager": { "display_name": "Italo Rusconi", "email_id": "Italo.Rusconi@takeda.com" }, "products": [], "site_image_url": "/brand/Risk/rdcfrance.png" }, { "id": 35, "name": "RDC GERMANY (TOF)", "type": "Distribution", "country": "Germany", "opu": null, "region": "", "function": "Supply Chain", "legal_entity": "Trans-o-flex Logistik Service GmbH", "address": "A10, 63755 Alzenau, Industriegebiet S E, 63755 Alzenau, Germany", "is_internal": false, "risk_owner": { "display_name": "Pascal René Halm", "email_id": "Pascal.Halm@takeda.com" }, "risk_coordinator": { "display_name": "Eduardo Teixeira", "email_id": "eduardo.teixeira@takeda.com" }, "risk_manager": { "display_name": "Italo Rusconi", "email_id": "Italo.Rusconi@takeda.com" }, "products": [], "site_image_url": "/brand/Risk/rdcgermany.png" }, { "id": 29, "name": "RDC POLAND (ARVATO)", "type": "Distribution", "country": "Poland", "opu": null, "region": "", "function": "Supply Chain", "legal_entity": "Arvato Polska sp. z o.o", "address": "05-870 Kopytów; 44 h, 05-870, Poland", "is_internal": false, "risk_owner": { "display_name": "Pascal René Halm", "email_id": "Pascal.Halm@takeda.com" }, "risk_coordinator": { "display_name": "Eduardo Teixeira", "email_id": "eduardo.teixeira@takeda.com" }, "risk_manager": { "display_name": "Italo Rusconi", "email_id": "Italo.Rusconi@takeda.com" }, "products": [], "site_image_url": "/brand/Risk/arvatopoland.png" }, { "id": 36, "name": "RDC POLAND (KWIZDA)", "type": "Distribution", "country": "Austria", "opu": null, "region": "", "function": "Supply Chain", "legal_entity": "Kwizda Pharmadistribution GmbH", "address": "Achauerstraße 2, 2333 Leopoldsdorf bei Wien, Austria", "is_internal": false, "risk_owner": { "display_name": "Pascal René Halm", "email_id": "Pascal.Halm@takeda.com" }, "risk_coordinator": { "display_name": "Eduardo Teixeira", "email_id": "eduardo.teixeira@takeda.com" }, "risk_manager": { "display_name": "Italo Rusconi", "email_id": "Italo.Rusconi@takeda.com" }, "products": [], "site_image_url": "/brand/Risk/rdckwizda.png" }, { "id": 41, "name": "RDC SINGAPORE (KN+)", "type": "Distribution", "country": "Singapore", "opu": null, "region": "", "function": "Supply Chain", "legal_entity": "TAKEDA PHARMACEUTICALS INTERNATIONAL AG SINGAPORE BRANCH", "address": "10 PIONEER CRESCENT #01-00 SINGAPORE 628566", "is_internal": false, "risk_owner": null, "risk_coordinator": null, "risk_manager": null, "products": [], "site_image_url": "/brand/Risk/rdcsingaporekn.png" } ] } } | G12: ""
A13: https://api-insights-test2.takeda.io/ | B13: risks/api/v1/site-details?site_type_ids=1 | C13: GET | D13: {"products":null,"risk_id":null,"risk_type_id":null,"key_risk":null,"impacted_site_ids":null,"risk_category_ids":null,"impact_range_ids":null,"mitigation":true,"opu_ids":null,"page":1,"limit":10,"search_keyword":"","financial_impact_range_ids":null,"risk_state_id":null,"risk_owner_id":null,"overall_likelihood_type_id":null,"risk_mitigation_type":null,"overall_ptrb_type_id":null,"risk_phase_ids":null,"risk_universe_ids":[]} | E13: 200 | F13: { "status": 200, "message": "success", "data": { "site_details": [ { "id": 4, "name": "BEKASI", "type": "Manufacturing", "country": "Indonesia", "opu": "SMALL MOLECULES AND ONCOLOGY", "region": "", "function": "", "legal_entity": "Takeda Indonesia", "address": "Jl. Pangeran Diponegoro KM.38,Tambun, Bekasi,17510", "is_internal": true, "risk_owner": null, "risk_coordinator": { "display_name": "Prasanth Palani ", "email_id": "prasanth.palani@takeda.com" }, "risk_manager": null, "products": [], "site_image_url": "/brand/Risk/bekasi.png" }, { "id": 1, "name": "BRAY", "type": "Manufacturing", "country": "Ireland", "opu": "SMALL MOLECULES AND ONCOLOGY", "region": "", "function": "", "legal_entity": "Takeda Ireland - Bray", "address": "Bray Business Park, Kilruddery, Co. Wicklow,Bray,A98 CD36", "is_internal": true, "risk_owner": null, "risk_coordinator": null, "risk_manager": null, "products": [ "ALUNBRIG", "ICLUSIG", "LIVTENCITY", "TAK-935 SOTICLESTAT", "TAKECAB" ], "site_image_url": "/brand/Risk/bray.png" }, { "id": 5, "name": "BROOKLYN PARK", "type": "Manufacturing", "country": "UNITED STATES OF AMERICA", "opu": "BIOLOGICS", "region": "MN", "function": "", "legal_entity": "Takeda Manufacturing USA, Inc.", "address": "9450 Winnetka Avenue North,Brooklyn Park,55445", "is_internal": true, "risk_owner": { "display_name": "Tom Lego", "email_id": "Thomas.Lego@takeda.com" }, "risk_coordinator": { "display_name": "Prasanth Palani ", "email_id": "prasanth.palani@takeda.com" }, "risk_manager": { "display_name": "Leela Akkala ", "email_id": "leela.akkala@takeda.com" }, "products": [ "ENTYVIO", "ADCETRIS" ], "site_image_url": "/brand/Risk/brooklynpark.png" }, { "id": 6, "name": "COVINGTON", "type": "Manufacturing", "country": " United States", "opu": "PLASMA", "region": "GA", "function": "", "legal_entity": "Covington Manufacturing Facility", "address": "505 Shire Parkway,Social Circle,30025", "is_internal": true, "risk_owner": { "display_name": "Cyril Buckley", "email_id": "cyril.buckley@takeda.com" }, "risk_coordinator": { "display_name": "Charlotte Erland", "email_id": "charlotte.erland@takeda.com" }, "risk_manager": { "display_name": "Kori Schultz", "email_id": "kori.schultz@takeda.com" }, "products": [ "FLEXBUMIN", "GAMMAGARD LIQUID/KIOVIG" ], "site_image_url": "/brand/Risk/covington.png" }, { "id": 7, "name": "GRANGE CASTLE", "type": "Manufacturing", "country": "Ireland", "opu": "SMALL MOLECULES AND ONCOLOGY", "region": "", "function": "", "legal_entity": "Takeda Ireland Ltd ", "address": "Grange Castle Business Park,Dublin,22", "is_internal": true, "risk_owner": { "display_name": "Paul Keogh", "email_id": "Paul.Keogh@Takeda.com" }, "risk_coordinator": { "display_name": "Michelle Farrell", "email_id": "michelle.farrell@takeda.com" }, "risk_manager": null, "products": [ "TAKECAB", "NINLARO" ], "site_image_url": "/brand/Risk/grangecastle.png" }, { "id": 8, "name": "HIKARI", "type": "Manufacturing", "country": "Japan", "opu": "JAPAN REGION", "region": "", "function": "", "legal_entity": "Takeda Pharmaceutical Company Limited", "address": "4720 Takeda, Mitsui, Hikari City,Yamaguchi 743-8502", "is_internal": true, "risk_owner": { "display_name": "Hideki Fujiwara ", "email_id": "hideki.fujiwara@takeda.com" }, "risk_coordinator": { "display_name": "Tsuyoshi Kawabe ", "email_id": "tsuyoshi.kawabe@takeda.com" }, "risk_manager": { "display_name": "Satoshi Ito ", "email_id": "satoshi.ito@takeda.com" }, "products": [ "ENTYVIO", "TAKHZYRO", "LEUPRORELIN", "TAKECAB", "VECTIBIX", "ADCETRIS", "ALUNBRIG", "TRINTELLIX" ], "site_image_url": "/brand/Risk/hikari.png" }, { "id": 9, "name": "JAGUARIUNA", "type": "Manufacturing", "country": "Brazil", "opu": "SMALL MOLECULES AND ONCOLOGY", "region": "", "function": "", "legal_entity": "Takeda Pharma Ltda", "address": "RODOVIA SP 340 KM 133 + 500 M,JAGUARIUNA,CEP 13.916-072", "is_internal": true, "risk_owner": { "display_name": "Luiz Roque Neto", "email_id": "luiz.neto@takeda.com" }, "risk_coordinator": { "display_name": "Thaila Ponte", "email_id": "Thaila.Ponte@takeda.com" }, "risk_manager": null, "products": [ "DEXILANT" ], "site_image_url": "/brand/Risk/jaguariuna.png" }, { "id": 10, "name": "LESSINES", "type": "Manufacturing", "country": "Belgium", "opu": "PLASMA", "region": "", "function": "", "legal_entity": "Baxalta Belgium Manufacturing S.A.", "address": "80 Boulevard René Branquart,Lessines,7860", "is_internal": true, "risk_owner": { "display_name": "Geoffrey Pot", "email_id": "geoffrey.pot@takeda.com" }, "risk_coordinator": { "display_name": "Valery Lepers", "email_id": "valery.lepers@takeda.com" }, "risk_manager": null, "products": [ "ADVATE", "CUVITRU", "GAMMAGARD LIQUID/KIOVIG" ], "site_image_url": "/brand/Risk/lessines.png" }, { "id": 11, "name": "LEXINGTON", "type": "Manufacturing", "country": "UNITED STATES OF AMERICA", "opu": "BIOLOGICS", "region": "", "function": "", "legal_entity": "Shire Human Genetic Therapies, Inc.", "address": "300 & 400 Shire Way,Lexington", "is_internal": true, "risk_owner": { "display_name": "Natalie Friel", "email_id": "natalie.friel@takeda.com" }, "risk_coordinator": { "display_name": "Eduart Golloshi", "email_id": "eduart.golloshi@takeda.com" }, "risk_manager": null, "products": [ "ELAPRASE", "REPLAGAL", "TAKHZYRO", "VPRIV" ], "site_image_url": "/brand/Risk/lexington.png" }, { "id": 12, "name": "LINZ", "type": "Manufacturing", "country": "Austria", "opu": "SMALL MOLECULES AND ONCOLOGY", "region": "", "function": "", "legal_entity": "Takeda Austria GmbH", "address": "St. Peter-Straße 25,Linz,4020", "is_internal": true, "risk_owner": { "display_name": "Roland Fabris", "email_id": "Roland.Fabris@takeda.com" }, "risk_coordinator": { "display_name": "Alfred Josef Hopfner-Heindl", "email_id": "Alfred.Hopfner-Heindl@takeda.com" }, "risk_manager": null, "products": [ "ENTYVIO", "TAKHZYRO", "ADCETRIS", "MEPACT" ], "site_image_url": "/brand/Risk/linz.png" }, { "id": 13, "name": "LOS ANGELES", "type": "Manufacturing", "country": "UNITED STATES OF AMERICA", "opu": "PLASMA", "region": "CA", "function": "", "legal_entity": "Baxalta US Inc.", "address": "4501 Colorado Boulevard,Los Angeles,90039", "is_internal": true, "risk_owner": { "display_name": "Babak Haghiri", "email_id": "babak.haghiri@takeda.com" }, "risk_coordinator": { "display_name": "Angelica Nava-Gutierrez", "email_id": "angelica.nava-gutierrez@takeda.com" }, "risk_manager": { "display_name": "T.K. Kim", "email_id": "tk.kim@takeda.com" }, "products": [ "CUVITRU", "FLEXBUMIN", "GAMMAGARD LIQUID/KIOVIG", "HYQVIA" ], "site_image_url": "/brand/Risk/losangeles.png" }, { "id": 14, "name": "MADRID", "type": "Manufacturing", "country": "Spain", "opu": "BIOLOGICS", "region": "", "function": "", "legal_entity": "Madrid Mftg Site", "address": "c/Marconi, 1, Parque Tecnológico de Madrid,Madrid,28760", "is_internal": true, "risk_owner": { "display_name": "Maria del Pilar Redondo Pastor", "email_id": "Pilar.Redondo@takeda.com" }, "risk_coordinator": { "display_name": "Israel Jimenez Manjarrez", "email_id": "Israel.Jimenez@takeda.com" }, "risk_manager": null, "products": [ "ALOFISEL" ], "site_image_url": "/brand/Risk/madrid.png" }, { "id": 15, "name": "NARITA", "type": "Manufacturing", "country": "Japan", "opu": "JAPAN REGION", "region": "", "function": "", "legal_entity": "Narita Mftg site", "address": "3-1, Shin-izumi,Narita,Chiba,286-0825", "is_internal": true, "risk_owner": { "display_name": "Takeharu Michioka ", "email_id": "takeharu.michioka@takeda.com" }, "risk_coordinator": { "display_name": "Tetsuya Kotai ", "email_id": "tetsuya.kotai@takeda.com" }, "risk_manager": { "display_name": "Akiko Yamada ", "email_id": "akiko.yamada@takeda.com" }, "products": [ "CUVITRU", "ALBUMIN" ], "site_image_url": "/brand/Risk/narita.png" }, { "id": 16, "name": "NAUCALPAN", "type": "Manufacturing", "country": "Mexico", "opu": "SMALL MOLECULES AND ONCOLOGY", "region": "", "function": "", "legal_entity": "Takeda México, S.A. DEC.V.", "address": "Av. Primero de Mayo 130, Col. IndustrialAtoto,Naucalpan de Juárez, Estado de Mexico.", "is_internal": true, "risk_owner": { "display_name": "Claudia Bizello", "email_id": "claudia.bizello@takeda.com" }, "risk_coordinator": { "display_name": "Juan Ponce Sandoval", "email_id": "Juan-Manuel.Ponce@takeda.com" }, "risk_manager": { "display_name": "Vianney Chavez Rodal", "email_id": "Vianney.Chavez@takeda.com" }, "products": [ "DEXILANT" ], "site_image_url": "/brand/Risk/naucalpan.png" }, { "id": 17, "name": "NEUCHATEL", "type": "Manufacturing", "country": "Switzerland", "opu": "BIOLOGICS", "region": "", "function": "", "legal_entity": "Baxalta Manufacturing S.A.R.L.", "address": "Route de Pierre-à-Bot 111,Neuchâtel,2000", "is_internal": true, "risk_owner": { "display_name": "Sebastien Bourgeois", "email_id": "sebastien.bourgeois@takeda.com" }, "risk_coordinator": { "display_name": "Jérôme Veyret", "email_id": "jerome.veyret@takeda.com" }, "risk_manager": null, "products": [ "ADVATE", "ADYNOVATE", "VONVENDI" ], "site_image_url": "/brand/Risk/neuchatel.png" }, { "id": 18, "name": "ORANIENBURG", "type": "Manufacturing", "country": "Germany", "opu": "SMALL MOLECULES AND ONCOLOGY", "region": "", "function": "", "legal_entity": "Takeda GmbH - Plant Oriannenburg", "address": "Lehnitzstraße 70 – 98,Oranienburg,16515", "is_internal": true, "risk_owner": { "display_name": "Chris Buttkus", "email_id": "chris.buttkus@takeda.com" }, "risk_coordinator": { "display_name": "Falk Missfelder", "email_id": "falk.missfelder@takeda.com" }, "risk_manager": null, "products": [ "DEXILANT", "PANTOPRAZOLE", "TRINTELLIX", "VYVANSE" ], "site_image_url": "/brand/Risk/oranienburg.png" }, { "id": 19, "name": "OSAKA", "type": "Manufacturing", "country": "Japan", "opu": "JAPAN REGION", "region": "", "function": "", "legal_entity": "Osaka Mftg site ", "address": "17-85 Jusohonmachi 2-chome, Yodogawa-ku,Osaka,532-8686", "is_internal": true, "risk_owner": { "display_name": "Akihiro Yamada ", "email_id": "akihiro.yamada@takeda.com" }, "risk_coordinator": { "display_name": "Norihiko Kurebayashi ", "email_id": "norihiko.kurebayashi@takeda.com" }, "risk_manager": null, "products": [ "ALOFISEL", "LEUPRORELIN" ], "site_image_url": "/brand/Risk/osaka.png" }, { "id": 20, "name": "PISA", "type": "Manufacturing", "country": "Italy", "opu": "PLASMA", "region": "", "function": "", "legal_entity": "Takeda Manufacturing Italia S.p.A.", "address": "Via Giovan Battista Oliva, 2 Ospedaletto,Pisa,56121", "is_internal": true, "risk_owner": { "display_name": "Francesca Micheli", "email_id": "francesca.micheli@takeda.com" }, "risk_coordinator": { "display_name": "Sandro Starace", "email_id": "sandro.starace@takeda.com" }, "risk_manager": { "display_name": "Alessandra Guadagnoli", "email_id": "alessandra.guadagnoli@takeda.com" }, "products": [ "ALBUMIN" ], "site_image_url": "/brand/Risk/pisa.png" }, { "id": 21, "name": "RIETI", "type": "Manufacturing", "country": "Italy", "opu": "PLASMA", "region": "", "function": "", "legal_entity": "Takeda Manufacturing Italia S.p.A.", "address": "Via della Chimica 5, S. Rufina – Cittaducale,Rieti,2015", "is_internal": true, "risk_owner": { "display_name": "Francesca Micheli", "email_id": "francesca.micheli@takeda.com" }, "risk_coordinator": { "display_name": "Sandro Starace", "email_id": "sandro.starace@takeda.com" }, "risk_manager": { "display_name": "Viviana Massimiliani", "email_id": "viviana.massimiliani@takeda.com" }, "products": [ "CUVITRU", "FEIBA", "FLEXBUMIN", "GAMMAGARD LIQUID/KIOVIG", "GAMMAGARD SD / LOW IGA", "ALBUMIN", "HYQVIA" ], "site_image_url": "/brand/Risk/rieti.png" }, { "id": 22, "name": "ROUND LAKE", "type": "Manufacturing", "country": "UNITED STATES OF AMERICA", "opu": "PLASMA", "region": "IL", "function": "", "legal_entity": "TPUSA Round Lake Site", "address": "25212 West Illinois Route 120,Round Lake,60073", "is_internal": true, "risk_owner": { "display_name": "Cary Wauters", "email_id": "cary.wauters@takeda.com" }, "risk_coordinator": { "display_name": "Dow Carter", "email_id": "dow.carter@takeda.com" }, "risk_manager": null, "products": [ "FLEXBUMIN" ], "site_image_url": "/brand/Risk/roundlake.png" }, { "id": 23, "name": "SINGAPORE", "type": "Manufacturing", "country": "Singapore", "opu": "BIOLOGICS", "region": "", "function": "", "legal_entity": "Takeda MFG SG PteLtd", "address": "2A Woodlands Industrial Park D Street 2,Singapore,737779", "is_internal": true, "risk_owner": { "display_name": "George Lam", "email_id": "george.lam@takeda.com" }, "risk_coordinator": { "display_name": "Edward Liu", "email_id": "edward.liu@takeda.com" }, "risk_manager": null, "products": [ "ADYNOVATE", "RIXUBIS", "ADZYNMA (TAK-755)", "ADVATE" ], "site_image_url": "/brand/Risk/singapore.png" }, { "id": 24, "name": "THOUSAND OAKS", "type": "Manufacturing", "country": "UNITED STATES OF AMERICA", "opu": "BIOLOGICS", "region": "", "function": "", "legal_entity": "Takeda Pharma U.S.A.", "address": "1700 Rancho Conejo Blvd,Thousand Oaks,91320", "is_internal": true, "risk_owner": { "display_name": "Stephen Hatke", "email_id": "stephen.hatke@takeda.com" }, "risk_coordinator": { "display_name": "Lisa Garcia", "email_id": "lisa.garcia@takeda.com" }, "risk_manager": null, "products": [ "ADVATE", "ADYNOVATE", "RECOMBINATE", "RIXUBIS", "VONVENDI" ], "site_image_url": "/brand/Risk/thousandoaks.png" }, { "id": 25, "name": "TIANJIN", "type": "Manufacturing", "country": "China", "opu": "SMALL MOLECULES AND ONCOLOGY", "region": "", "function": "", "legal_entity": "Tianjin Takeda Pharmaceuticals Co., Ltd.", "address": "No.11 Xinghua Road, Xiqing area,Tianjin,300385", "is_internal": true, "risk_owner": { "display_name": "Tao Hong ", "email_id": "Tao.Hong@takeda.com" }, "risk_coordinator": { "display_name": "Diogo Portapila", "email_id": "Diogo.Portapila@takeda.com" }, "risk_manager": { "display_name": "Yongfu Gao ", "email_id": "Yongfu.Gao@takeda.com" }, "products": [], "site_image_url": "/brand/Risk/tianjin.png" }, { "id": 26, "name": "VASHI", "type": "Manufacturing", "country": "India", "opu": "SMALL MOLECULES AND ONCOLOGY", "region": "", "function": "", "legal_entity": "ZYDUS TAKEDA HEALTHCARE P LTD", "address": "C-4, MIDC, Village Pawne, Thane Belapur Road, Vashi,Navi Mumbai,400703", "is_internal": true, "risk_owner": { "display_name": "Upendra Bahuguna", "email_id": "Upendra.Bahuguna@zydustakeda.com" }, "risk_coordinator": { "display_name": "Kiran Patil", "email_id": "Kiran1.patil@zydustakeda.com" }, "risk_manager": { "display_name": "Atul Kumar", "email_id": "atul.kumar1@takeda.com" }, "products": [ "PANTOPRAZOLE" ], "site_image_url": "/brand/Risk/vashi.png" }, { "id": 2, "name": "VIENNA", "type": "Manufacturing", "country": "Austria", "opu": "PLASMA", "region": "", "function": "", "legal_entity": "Takeda Manufacturing Austria AG", "address": "Industriestraße 67,Vienna,1221", "is_internal": true, "risk_owner": { "display_name": "Maria Löflund", "email_id": "maria.loeflund@takeda.com" }, "risk_coordinator": { "display_name": "Miriam Kaundert", "email_id": "miriam.kaundert@takeda.com" }, "risk_manager": { "display_name": "Stefanie Weidenauer", "email_id": "stefanie.weidenauer@takeda.com" }, "products": [ "GAMMAGARD SD / LOW IGA", "TAK-880 LOW IG-A", "TAK-881 20% FSCIG", "PROTHROMPLEX (PKT)", "ADVATE", "ALOFISEL", "OBIZUR", "TAKHZYRO", "VONVENDI", "ALBUMIN", "CEPROTIN", "CUVITRU", "FEIBA", "FLEXBUMIN", "GAMMAGARD LIQUID/KIOVIG", "HYQVIA" ], "site_image_url": "/brand/Risk/vienna.png" }, { "id": 27, "name": "YAROSLAVL", "type": "Manufacturing", "country": "Russia", "opu": "SMALL MOLECULES AND ONCOLOGY", "region": "", "function": "", "legal_entity": "Takeda Yaroslavl LLC", "address": "9, Tekhnoparkovaya street,Yaroslavl,150030", "is_internal": true, "risk_owner": { "display_name": "Anastasia Taranova ", "email_id": "anastasia.simonova@takeda.com" }, "risk_coordinator": { "display_name": "Margarita Rassokhina ", "email_id": "margarita.rassokhina@takeda.com" }, "risk_manager": null, "products": [ "NINLARO" ], "site_image_url": "/brand/Risk/yaroslavl.png" } ] } } | G13: ""
A15: TC4_Risk_VerifyProcessQualityQuery | B15: /process-quality/graphql | C15: POST | D15: query MyQuery { fetch_process_quality_details( param_value: {manufacturing_stage: "Drug Substance", clinical_code: "TAK-279", site_name: "Cambrex Charles City"} ) { clinical_code data_source load_time_stamp manufacturing_stage opu process_id process_name site ... on TechTransfer { process_id process_name clinical_code data_source load_time_stamp manufacturing_stage opu project_id receiving_unit sending_unit site user_name sub_process { input_output_yield_percentage operation_unit stage batch_volume { maximum_volume minimum_volume process_volume_range stage_name } equipments { equipment_code equipment_id equipment_name equipment_type material_of_construction } solubility { material_name solubility_description solubility_value solvent_name } stability { details { peak_id stability_attributes { comment_description parameter_name parameter_value uom_description } } solution_name } } workspace_id workspace_name } } } | E15: 200 | F15: { "data": { "fetch_process_quality_details": { "clinical_code": "TAK-279", "data_source": "Sphera Stature", "load_time_stamp": "2026-03-23T20:03:41.762+00:00", "manufacturing_stage": "Drug Substance", "opu": [ "SMALL MOLECULES & ONCOLOGY" ], "process_id": "1000093014", "process_name": "TAK-279 QbD RM_DRAFT_10-10-2025_1", "site": [ "Cambrex Charles City" ], "project_id": null, "receiving_unit": null, "sending_unit": null, "user_name": null, "sub_process": [ { "input_output_yield_percentage": null, "operation_unit": null, "stage": "Step 3", "batch_volume": [ { "maximum_volume": "1353 gallons / 5122 L", "minimum_volume": "198 gallons/ 750 L", "process_volume_range": null, "stage_name": "Step 3" } ], "equipments": [ { "equipment_code": "T-4562", "equipment_id": 1027902455, "equipment_name": "7000 Gallon Tank", "equipment_type": "Tank", "material_of_construction": null }, { "equipment_code": "F-4560", "equipment_id": 1027902572, "equipment_name": "6 m2 Agitated Filter Dryer", "equipment_type": "Filtration System", "material_of_construction": null }, { "equipment_code": "T-5501", "equipment_id": 1027901927, "equipment_name": "500 Gallon Tank", "equipment_type": "Tank", "material_of_construction": null }, { "equipment_code": "R-4554", "equipment_id": 1027900358, "equipment_name": "4000 Gallon Reactor", "equipment_type": "Reactor", "material_of_construction": null }, { "equipment_code": "R-4432", "equipment_id": 1027905575, "equipment_name": "4000 Gallon Reactor", "equipment_type": "Reactor", "material_of_construction": null }, { "equipment_code": "R-4554", "equipment_id": 1027902129, "equipment_name": "4000 Gallon Reactor", "equipment_type": "Reactor", "material_of_construction": null }, { "equipment_code": "R-4554", "equipment_id": 1027902451, "equipment_name": "4000 Gallon Reactor", "equipment_type": "Reactor", "material_of_construction": null }, { "equipment_code": "R-4554", "equipment_id": 1027904271, "equipment_name": "4000 Gallon Reactor", "equipment_type": "Reactor", "material_of_construction": null }, { "equipment_code": "H-4555", "equipment_id": 1027901755, "equipment_name": "Heat Exchanger", "equipment_type": null, "material_of_construction": null }, { "equipment_code": "R-4554", "equipment_id": 1027903643, "equipment_name": "4000 Gallon Reactor", "equipment_type": "Reactor", "material_of_construction": null }, { "equipment_code": "R-4432", "equipment_id": 1027905936, "equipment_name": "4000 Gallon Reactor", "equipment_type": "Reactor", "material_of_construction": null }, { "equipment_code": "R-4554", "equipment_id": 1027902570, "equipment_name": "4000 Gallon Reactor", "equipment_type": "Reactor", "material_of_construction": null }, { "equipment_code": "T-3301", "equipment_id": 1027905938, "equipment_name": "500 Gallon Tank", "equipment_type": "Tank", "material_of_construction": null }, { "equipment_code": "R-4432", "equipment_id": 1027906960, "equipment_name": "4000 Gallon Reactor", "equipment_type": "Reactor", "material_of_construction": null }, { "equipment_code": "R-4554", "equipment_id": 1027902308, "equipment_name": "4000 Gallon Reactor", "equipment_type": "Reactor", "material_of_construction": null }, { "equipment_code": "T-4562", "equipment_id": 1027907375, "equipment_name": "7000 Gallon Tank", "equipment_type": "Tank", "material_of_construction": null }, { "equipment_code": "R-4554", "equipment_id": 1027902063, "equipment_name": "4000 Gallon Reactor", "equipment_type": "Reactor", "material_of_construction": null }, { "equipment_code": "R-4554", "equipment_id": 1027905228, "equipment_name": "4000 Gallon Reactor", "equipment_type": "Reactor", "material_of_construction": null }, { "equipment_code": "R-4554", "equipment_id": 1027900933, "equipment_name": "4000 Gallon Reactor", "equipment_type": "Reactor", "material_of_construction": null }, { "equipment_code": "T-3301", "equipment_id": 1027905728, "equipment_name": "500 Gallon Tank", "equipment_type": "Tank", "material_of_construction": null }, { "equipment_code": "R-4554", "equipment_id": 1027902108, "equipment_name": "4000 Gallon Reactor", "equipment_type": "Reactor", "material_of_construction": null }, { "equipment_code": "R-4554", "equipment_id": 1027903751, "equipment_name": "4000 Gallon Reactor", "equipment_type": "Reactor", "material_of_construction": null }, { "equipment_code": "R-4554", "equipment_id": 1027904133, "equipment_name": "4000 Gallon Reactor", "equipment_type": "Reactor", "material_of_construction": null }, { "equipment_code": "R-4554", "equipment_id": 1027905570, "equipment_name": "4000 Gallon Reactor", "equipment_type": "Reactor", "material_of_construction": null }, { "equipment_code": "R-4432", "equipment_id": 1027906069, "equipment_name": "4000 Gallon Reactor", "equipment_type": "Reactor", "material_of_construction": null }, { "equipment_code": "R-4554", "equipment_id": 1027901387, "equipment_name": "4000 Gallon Reactor", "equipment_type": "Reactor", "material_of_construction": null }, { "equipment_code": "R-4432", "equipment_id": 1027906909, "equipment_name": "4000 Gallon Reactor", "equipment_type": "Reactor", "material_of_construction": null }, { "equipment_code": "R-4558", "equipment_id": 1027905372, "equipment_name": "2000 Gallon Reactor", "equipment_type": "Reactor", "material_of_construction": null }, { "equipment_code": "R-4554", "equipment_id": 1027901669, "equipment_name": "4000 Gallon Reactor", "equipment_type": "Reactor", "material_of_construction": null }, { "equipment_code": "R-4432", "equipment_id": 1027906373, "equipment_name": "4000 Gallon Reactor", "equipment_type": "Reactor", "material_of_construction": null }, { "equipment_code": "R-4432", "equipment_id": 1027906503, "equipment_name": "4000 Gallon Reactor", "equipment_type": "Reactor", "material_of_construction": null }, { "equipment_code": "R-4558", "equipment_id": 1027904446, "equipment_name": "2000 Gallon Reactor", "equipment_type": "Reactor", "material_of_construction": null }, { "equipment_code": "R-4554", "equipment_id": 1027901488, "equipment_name": "4000 Gallon Reactor", "equipment_type": "Reactor", "material_of_construction": null }, { "equipment_code": "R-4554", "equipment_id": 1027900696, "equipment_name": "4000 Gallon Reactor", "equipment_type": "Reactor", "material_of_construction": null }, { "equipment_code": "R-4554", "equipment_id": 1027905171, "equipment_name": "4000 Gallon Reactor", "equipment_type": "Reactor", "material_of_construction": null }, { "equipment_code": "R-4432", "equipment_id": 1027905465, "equipment_name": "4000 Gallon Reactor", "equipment_type": "Reactor", "material_of_construction": null }, { "equipment_code": "R-4554", "equipment_id": 1027904974, "equipment_name": "4000 Gallon Reactor", "equipment_type": "Reactor", "material_of_construction": null }, { "equipment_code": "R-4432", "equipment_id": 1027906393, "equipment_name": "4000 Gallon Reactor", "equipment_type": "Reactor", "material_of_construction": null }, { "equipment_code": "R-4554", "equipment_id": 1027901929, "equipment_name": "4000 Gallon Reactor", "equipment_type": "Reactor", "material_of_construction": null }, { "equipment_code": "R-4432", "equipment_id": 1027906713, "equipment_name": "4000 Gallon Reactor", "equipment_type": "Reactor", "material_of_construction": null }, { "equipment_code": "R-4554", "equipment_id": 1027904483, "equipment_name": "4000 Gallon Reactor", "equipment_type": "Reactor", "material_of_construction": null }, { "equipment_code": "R-4558", "equipment_id": 1027903818, "equipment_name": "2000 Gallon Reactor", "equipment_type": "Reactor", "material_of_construction": null }, { "equipment_code": "R-4554", "equipment_id": 1027901097, "equipment_name": "4000 Gallon Reactor", "equipment_type": "Reactor", "material_of_construction": null }, { "equipment_code": "F-4560", "equipment_id": 1027907111, "equipment_name": "6 m2 Agitated Filter Dryer", "equipment_type": "Filtration System", "material_of_construction": null }, { "equipment_code": "R-4432", "equipment_id": 1027906809, "equipment_name": "4000 Gallon Reactor", "equipment_type": "Reactor", "material_of_construction": null }, { "equipment_code": "R-4432", "equipment_id": 1027907011, "equipment_name": "4000 Gallon Reactor", "equipment_type": "Reactor", "material_of_construction": null }, { "equipment_code": "R-4554", "equipment_id": 1027902662, "equipment_name": "4000 Gallon Reactor", "equipment_type": "Reactor", "material_of_construction": null }, { "equipment_code": "R-4432", "equipment_id": 1027907109, "equipment_name": "4000 Gallon Reactor", "equipment_type": "Reactor", "material_of_construction": null }, { "equipment_code": "R-4554", "equipment_id": 1027901759, "equipment_name": "4000 Gallon Reactor", "equipment_type": "Reactor", "material_of_construction": null }, { "equipment_code": "R-4554", "equipment_id": 1027901555, "equipment_name": "4000 Gallon Reactor", "equipment_type": "Reactor", "material_of_construction": null } ], "solubility": [ { "material_name": "TR06854013", "solubility_description": "Soluble at RT", "solubility_value": "N/A", "solvent_name": "DMF" }, { "material_name": "TR06854013", "solubility_description": "Not soluable at RT", "solubility_value": "N/A", "solvent_name": "5% acetic acid" }, { "material_name": "TR06854013", "solubility_description": "Not soluable at RT", "solubility_value": "N/A", "solvent_name": "5% sodium hydroxide" }, { "material_name": "TR06854013", "solubility_description": "Not soluable at RT", "solubility_value": "N/A", "solvent_name": "Isopropyl acetate" }, { "material_name": "TR06854013", "solubility_description": "Partially soluble at RT", "solubility_value": "N/A", "solvent_name": "Acetone" }, { "material_name": "TR06854013", "solubility_description": "Not soluble at RT; soluble on heating", "solubility_value": "N/A", "solvent_name": "Acetonitrile" }, { "material_name": "TR06854013", "solubility_description": "Soluble at RT", "solubility_value": "N/A", "solvent_name": "50% acetic acid" }, { "material_name": "TR06854013", "solubility_description": "Not soluable at RT; partially soluble on heating", "solubility_value": "N/A", "solvent_name": "Ethyl acetate" }, { "material_name": "TR06854013", "solubility_description": "Partially soluble at RT", "solubility_value": "N/A", "solvent_name": "25% acetic acid" }, { "material_name": "TR06854013", "solubility_description": "Not soluble at RT or on heating", "solubility_value": "N/A", "solvent_name": "CIP 100" }, { "material_name": "TR06854013", "solubility_description": "Not soluble at RT or on heating", "solubility_value": "N/A", "solvent_name": "CIP 200" }, { "material_name": "TR06854013", "solubility_description": "Slightly soluble at RT; Soluble on heating, but precipitated on cooling", "solubility_value": "N/A", "solvent_name": "Methanol" }, { "material_name": "TR06854013", "solubility_description": "Soluble at RT", "solubility_value": "N/A", "solvent_name": "NMP" }, { "material_name": "TR06854013", "solubility_description": "Not soluble at RT or on heating", "solubility_value": "N/A", "solvent_name": "Isopropanol" }, { "material_name": "TR06854013", "solubility_description": "Not soluble at RT or on heating", "solubility_value": "N/A", "solvent_name": "Water" } ], "stability": [ { "details": [ { "peak_id": "HMPL-013-I", "stability_attributes": [ { "comment_description": null, "parameter_name": "4 h reflux", "parameter_value": "ND", "uom_description": "%Area" } ] }, { "peak_id": "RRT ~ 0.926", "stability_attributes": [ { "comment_description": null, "parameter_name": "RRT", "parameter_value": "0", "uom_description": null } ] }, { "peak_id": "RRT ~ 1.556", "stability_attributes": [ { "comment_description": null, "parameter_name": "RRT", "parameter_value": "1", "uom_description": null }, { "comment_description": null, "parameter_name": "4 h reflux", "parameter_value": "0", "uom_description": null } ] }, { "peak_id": "RRT ~ 0.834", "stability_attributes": [ { "comment_description": null, "parameter_name": "RT", "parameter_value": "4", "uom_description": null } ] }, { "peak_id": "RRT ~ 1.502", "stability_attributes": [ { "comment_description": null, "parameter_name": "RRT", "parameter_value": "1", "uom_description": null } ] }, { "peak_id": "RRT ~ 1.346", "stability_attributes": [ { "comment_description": null, "parameter_name": "4 h reflux", "parameter_value": "0", "uom_description": null }, { "comment_description": null, "parameter_name": "RRT", "parameter_value": "1", "uom_description": null } ] }, { "peak_id": "RRT ~ 0.885", "stability_attributes": [ { "comment_description": null, "parameter_name": "4 h reflux", "parameter_value": "0", "uom_description": null }, { "comment_description": null, "parameter_name": "Room temperature", "parameter_value": "ND", "uom_description": "%Area" }, { "comment_description": null, "parameter_name": "RT", "parameter_value": "5", "uom_description": null } ] }, { "peak_id": "HMPL-013-SM2", "stability_attributes": [ { "comment_description": null, "parameter_name": "4 h reflux", "parameter_value": "99", "uom_description": null } ] }, { "peak_id": "RRT ~ 1.908", "stability_attributes": [ { "comment_description": null, "parameter_name": "RRT", "parameter_value": "1", "uom_description": null }, { "comment_description": null, "parameter_name": "RT", "parameter_value": "11", "uom_description": null } ] }, { "peak_id": "RRT ~ 1.140", "stability_attributes": [ { "comment_description": null, "parameter_name": "RT", "parameter_value": "6", "uom_description": null } ] } ], "solution_name": "THF" } ] }, { "input_output_yield_percentage": null, "operation_unit": null, "stage": "Step 1", "batch_volume": [ { "maximum_volume": "997 gallons / 3774 L", "minimum_volume": "254 gallons / 962 L", "process_volume_range": null, "stage_name": "Step 1" } ], "equipments": [ { "equipment_code": "R-3146", "equipment_id": 1027891582, "equipment_name": "2000 Gallon Reactor", "equipment_type": "Reactor", "material_of_construction": null }, { "equipment_code": "R-3146", "equipment_id": 1027888813, "equipment_name": "2000 Gallon Reactor", "equipment_type": "Reactor", "material_of_construction": null }, { "equipment_code": "R-3146", "equipment_id": 1027888730, "equipment_name": "2000 Gallon Reactor", "equipment_type": "Reactor", "material_of_construction": null }, { "equipment_code": "R-3156", "equipment_id": 1027891312, "equipment_name": "1200 Gallon Reactor", "equipment_type": "Reactor", "material_of_construction": null }, { "equipment_code": "T-3147", "equipment_id": 1027889139, "equipment_name": "500 Gallon Tank", "equipment_type": "Tank", "material_of_construction": null }, { "equipment_code": "F-3388", "equipment_id": 1027891233, "equipment_name": "30\" Filter housing (3-Cartridge)", "equipment_type": "Filtration System", "material_of_construction": null }, { "equipment_code": "F-3123 or F-2157", "equipment_id": 1027891232, "equipment_name": "36\" Sparkler filter", "equipment_type": "Filtration System", "material_of_construction": null }, { "equipment_code": "R-3146", "equipment_id": 1027889544, "equipment_name": "2000 Gallon Reactor", "equipment_type": "Reactor", "material_of_construction": null }, { "equipment_code": "R-3146", "equipment_id": 1027888981, "equipment_name": "2000 Gallon Reactor", "equipment_type": "Reactor", "material_of_construction": null }, { "equipment_code": "R-3146", "equipment_id": 1027889723, "equipment_name": "2000 Gallon Reactor", "equipment_type": "Reactor", "material_of_construction": null }, { "equipment_code": "R-3146", "equipment_id": 1027888506, "equipment_name": "2000 Gallon Reactor", "equipment_type": "Reactor", "material_of_construction": null }, { "equipment_code": "R-3146", "equipment_id": 1027889456, "equipment_name": "2000 Gallon Reactor", "equipment_type": "Reactor", "material_of_construction": null }, { "equipment_code": "R-3156", "equipment_id": 1027890869, "equipment_name": "1200 Gallon Reactor", "equipment_type": "Reactor", "material_of_construction": null }, { "equipment_code": "R-3379 or similar", "equipment_id": 1027890421, "equipment_name": "Portable Reactor", "equipment_type": "Reactor", "material_of_construction": null }, { "equipment_code": "T-3147", "equipment_id": 1027892340, "equipment_name": "500 Gallon Tank", "equipment_type": "Tank", "material_of_construction": null }, { "equipment_code": "R-3146", "equipment_id": 1027889081, "equipment_name": "2000 Gallon Reactor", "equipment_type": "Reactor", "material_of_construction": null }, { "equipment_code": "R-3156", "equipment_id": 1027890746, "equipment_name": "1200 Gallon Reactor", "equipment_type": "Reactor", "material_of_construction": null }, { "equipment_code": "R-3156", "equipment_id": 1027890671, "equipment_name": "1200 Gallon Reactor", "equipment_type": "Reactor", "material_of_construction": null }, { "equipment_code": "R-3146", "equipment_id": 1027890144, "equipment_name": "2000 Gallon Reactor", "equipment_type": "Reactor", "material_of_construction": null }, { "equipment_code": "R-3146", "equipment_id": 1027892758, "equipment_name": "2000 Gallon Reactor", "equipment_type": "Reactor", "material_of_construction": null }, { "equipment_code": "R-3146", "equipment_id": 1027891810, "equipment_name": "2000 Gallon Reactor", "equipment_type": "Reactor", "material_of_construction": null }, { "equipment_code": "R-3146", "equipment_id": 1027892168, "equipment_name": "2000 Gallon Reactor", "equipment_type": "Reactor", "material_of_construction": null }, { "equipment_code": "R-3146", "equipment_id": 1027888139, "equipment_name": "2000 Gallon Reactor", "equipment_type": "Reactor", "material_of_construction": null }, { "equipment_code": "F-2107 or similar", "equipment_id": 1027892342, "equipment_name": "48\" Clamshell filter", "equipment_type": "Filtration System", "material_of_construction": null }, { "equipment_code": "T-3147", "equipment_id": 1027891812, "equipment_name": "500 Gallon Tank", "equipment_type": "Tank", "material_of_construction": null }, { "equipment_code": "R-3146", "equipment_id": 1027889508, "equipment_name": "2000 Gallon Reactor", "equipment_type": "Reactor", "material_of_construction": null }, { "equipment_code": "T-3147", "equipment_id": 1027892716, "equipment_name": "500 Gallon Tank", "equipment_type": "Tank", "material_of_construction": null }, { "equipment_code": "R-3178", "equipment_id": 1027891228, "equipment_name": "1000 Gallon Reactor", "equipment_type": "Reactor", "material_of_construction": null }, { "equipment_code": "R-3379 or similar", "equipment_id": 1027890313, "equipment_name": "Portable Reactor", "equipment_type": "Reactor", "material_of_construction": null }, { "equipment_code": "T-3147", "equipment_id": 1027889510, "equipment_name": "500 Gallon Tank", "equipment_type": "Tank", "material_of_construction": null }, { "equipment_code": "R-3146", "equipment_id": 1027890059, "equipment_name": "2000 Gallon Reactor", "equipment_type": "Reactor", "material_of_construction": null }, { "equipment_code": "R-3146", "equipment_id": 1027892462, "equipment_name": "2000 Gallon Reactor", "equipment_type": "Reactor", "material_of_construction": null }, { "equipment_code": "R-3146", "equipment_id": 1027892549, "equipment_name": "2000 Gallon Reactor", "equipment_type": "Reactor", "material_of_construction": null }, { "equipment_code": "R-3146", "equipment_id": 1027889137, "equipment_name": "2000 Gallon Reactor", "equipment_type": "Reactor", "material_of_construction": null }, { "equipment_code": "R-3146", "equipment_id": 1027891230, "equipment_name": "2000 Gallon Reactor", "equipment_type": "Reactor", "material_of_construction": null }, { "equipment_code": "R-3146", "equipment_id": 1027892653, "equipment_name": "2000 Gallon Reactor", "equipment_type": "Reactor", "material_of_construction": null }, { "equipment_code": "R-3146", "equipment_id": 1027889828, "equipment_name": "2000 Gallon Reactor", "equipment_type": "Reactor", "material_of_construction": null }, { "equipment_code": "R-3146", "equipment_id": 1027891715, "equipment_name": "2000 Gallon Reactor", "equipment_type": "Reactor",

Sheet Make_Vienna_TestData
A1: TestCaseName | B1: Wo | C1: Actual end date (Packaging) Start date of finishin admin | D1: Actual End Date (Finishing admin) | E1: Date when first defect was captured in QA Review (Event: Defect: Date&time) | F1: Actual End date (QA Review) | G1: Actual end date (Mfg Approval) | H1: Actual end date (QA Approval) | I1: End (permanent batch): Line -> Admin [h] F&H WO-Specialist | J1: End (continuous batch): Admin -> QA BRR return [h] H&J QA Review | K1: End (duration batch): correction loop Target≤18[h] J&K Korrekturschleife MW | L1: End (duration batch): QA BRR-> Approver [h] K&M Genehmiger | M1: End (duration batch): Approver-> CoC completion [h] M&O CoC Abschluss | N1: Total time in days Line -> CoC completion Target≤2[day] F&O Gesamtzeit
A2: TC1_Make_Vienna_NormalBatch_WithoutDefect_NoWeekendNoHoliday | B2: A1A066AAP1 | C2: 44949.292 | D2: 44949.583 | F2: 44950.333 | G2: 44950.667 | H2: 44951.25 | I2: 7 | J2: Data error | K2: #VALUE! | L2: 8 | M2: 14 | N2: 1.96
A3: TC2_Make_Vienna_NormalBatch_WithoutDefect_1WeekendNoHoliday | B3: A1A067AB | C3: 45667.625 | D3: 45668.292 | F3: 45668.833 | G3: 45670.625 | H3: 45671.458 | I3: 16 | J3: Data error | K3: #VALUE! | L3: 9 | M3: 20 | N3: 1.81
A4: TC3_Make_Vienna_NormalBatch_WithoutDefect_NoWeekend1Holiday | B4: A1A068ABP1 | C4: 45651.292 | D4: 45651.583 | F4: 45653.25 | G4: 45653.271 | H4: 45638.285 | I4: 7 | J4: Data error | K4: #VALUE! | L4: 0.5 | M4: #VALUE! | N4: #VALUE!
A5: TC4_Make_Vienna_NormalBatch_WithoutDefect_2orMoreWeekendNoHoliday | B5: A1A066AAP1 | C5: 44949.292 | D5: 44949.583 | F5: 44950.333 | G5: 44950.667 | H5: 44951.25 | I5: 7 | J5: Data error | K5: #VALUE! | L5: 8 | M5: 14 | N5: 1.96
A6: TC5_Make_Vienna_NormalBatch_WithoutDefect_NoWeekendMultipleHoliday | B6: A1A067AB | C6: 45667.625 | D6: 45668.292 | F6: 45668.833 | G6: 45670.625 | H6: 45671.458 | I6: 16 | J6: Data error | K6: #VALUE! | L6: 9 | M6: 20 | N6: 1.81
A7: TC6_Make_Vienna_NormalBatch_WithoutDefect_HolidayFallingOnWeekend | B7: A1A068ABP1 | C7: 45651.292 | D7: 45651.583 | F7: 45653.25 | G7: 45653.271 | H7: 45638.285 | I7: 7 | J7: Data error | K7: #VALUE! | L7: 0.5 | M7: #VALUE! | N7: #VALUE!
A8: TC7_Make_Vienna_UrgentBatch_WithoutDefect_NoWeekendNoHoliday | B8: A1B680AA | C8: 45724.375 | D8: 45727.501 | E8: 45728.778 | F8: 45728.778 | G8: 45728.92 | H8: 45729.333 | I8: 30 | J8: 30.7 | K8: 0 | L8: 3.4 | M8: 9.91 | N8: 3
A9: TC8_Make_Vienna_UrgentBatch_WithoutDefect_1WeekendNoHoliday | B9: A1B618AA | C9: 45720.375 | D9: 45722.327 | E9: 45723.409 | F9: 45723.409 | G9: 45723.639 | H9: 45723.833 | I9: 46.9 | J9: 26 | K9: 0 | L9: 5.5 | M9: 4.66 | N9: 3
A10: TC9_Make_Vienna_UrgentBatch_WithoutDefect_NoWeekend1Holiday | B10: A1B679AA | C10: 45727.375 | D10: 45728.885 | E10: 45728.953 | F10: 45728.953 | G10: 45729.04 | H10: 45729.333 | I10: 36.3 | J10: 1.6 | K10: 0 | L10: 2.1 | M10: 7.02 | N10: 2
A11: TC10_Make_Vienna_UrgentBatch_WithoutDefect_2orMoreWeekendNoHoliday | B11: A1B659AA | C11: 45727.375 | D11: 45727.463 | E11: 45728.425 | F11: 45728.425 | G11: 45728.921 | H11: 45729.333 | I11: 2.1 | J11: 23.1 | K11: 0 | L11: 11.9 | M11: 9.9 | N11: 2
A12: TC11_Make_Vienna_UrgentBatch_WithoutDefect_NoWeekendMultipleHoliday | B12: A4B371AA | C12: 45733.375 | D12: 45733.393 | E12: 45735.587 | F12: 45735.712 | G12: 45736.345 | H12: 45736.833 | I12: 0.4 | J12: 52.6 | K12: 3 | L12: 15.2 | M12: 11.71 | N12: 3
A13: TC12_Make_Vienna_UrgentBatch_WithoutDefect_HolidayFallingOnWeekend | B13: A1B233AA | C13: 45733.375 | D13: 45734.328 | E13: 45734.833 | F13: 45734.833 | G13: 45735.749 | H13: 45736.333 | I13: 22.9 | J13: 12.1 | K13: 0 | L13: 22 | M13: 14.01 | N13: 3
A14: TC13_Make_Vienna_NormalAndUrgentBatch_WithoutDefect_NoWeekendNoHoliday | B14: A1B681AA | C14: 45733.375 | D14: 45734.328 | E14: 45734.833 | F14: 45734.833 | G14: 45735.749 | H14: 45736.333 | I14: 22.9 | J14: 12.1 | K14: 0 | L14: 22 | M14: 14.01 | N14: 3
A15: TC14_Make_Vienna_NormalAndUrgentBatch_WithoutDefect_1WeekendNoHoliday | B15: A1B283AA | C15: 45725.349 | D15: 45725.417 | E15: 45726.917 | F15: 45726.917 | G15: 45726.951 | H15: 45727.347 | I15: #VALUE! | J15: #VALUE! | K15: 0 | L15: 0.8 | M15: 9.5 | N15: 0
A16: TC15_Make_Vienna_NormalAndUrgentBatch_WithoutDefect_NoWeekend1Holiday | B16: C3B110AB | C16: 45743.375 | D16: 45743.614 | E16: 45747.026 | F16: 45747.026 | G16: 45747.275 | H16: 45747.333 | I16: 5.7 | J16: 33.4 | K16: 0 | L16: 6 | M16: 1.4 | N16: 2
A17: TC16_Make_Vienna_NormalAndUrgentBatch_WithoutDefect_2orMoreWeekendNoHoliday | B17: A1B466AA | C17: 45744.375 | D17: 45747.071 | E17: 45747.279 | F17: 45747.279 | G17: 45747.281 | H17: 45747.333 | I17: 16.2 | J17: 5 | K17: 0 | L17: 0 | M17: 1.26 | N17: 1
A18: TC17_Make_Vienna_NormalAndUrgentBatch_WithoutDefect_NoWeekendMultipleHoliday | B18: A4B257U1 | C18: 45742.375 | D18: 45743.81 | E18: 45747.224 | F18: 45747.224 | G18: 45747.229 | H18: 45747.333 | I18: 34.4 | J18: 33.4 | K18: 0 | L18: 0.1 | M18: 2.49 | N18: 3
A19: TC18_Make_Vienna_NormalAndUrgentBatch_WithoutDefect_HolidayFallingOnWeekend | B19: A1B464AA | C19: 45742.375 | D19: 45747.084 | E19: 45747.206 | F19: 45747.206 | G19: 45747.221 | H19: 45747.333 | I19: 64.5 | J19: 2.9 | K19: 0 | L19: 0.4 | M19: 2.69 | N19: 3
A20: TC19_Make_Vienna_NormalBatch_WithDefect_NoWeekendNoHoliday | B20: C3B116AA | C20: 45739.375 | D20: 45743.715 | E20: 45747.318 | F20: 45747.318 | G20: 45747.323 | H20: 45747.333 | I20: 83.2 | J20: 38 | K20: 0 | L20: 0.1 | M20: 0.25 | N20: 4
A21: TC20_Make_Vienna_NormalBatch_WithDefect_1WeekendNoHoliday | B21: VBRXG05AA | C21: 45744.375 | D21: 45745.483 | E21: 45746.878 | F21: 45746.878 | G21: 45747.319 | H21: 45747.333 | I21: 26.6 | J21: #VALUE! | K21: #VALUE! | L21: 1.7 | M21: 0.33 | N21: 1
A22: TC21_Make_Vienna_NormalBatch_WithDefect_NoWeekend1Holiday | B22: A1B467AA | C22: 45744.375 | D22: 45744.657 | E22: 45745.751 | F22: 45745.751 | G22: 45747.165 | H22: 45747.333 | I22: 6.8 | J22: 26.2 | K22: #VALUE! | L22: -2 | M22: 4.05 | N22: 1
A23: TC22_Make_Vienna_NormalBatch_WithDefect_2orMoreWeekendNoHoliday | B23: C3B117AB | C23: 45744.375 | D23: 45744.988 | E23: 45746.855 | F23: 45746.855 | G23: 45747.231 | H23: 45747.333 | I23: 14.7 | J23: #VALUE! | K23: #VALUE! | L23: -0.4 | M23: 2.44 | N23: 1
A24: TC23_Make_Vienna_NormalBatch_WithDefect_NoWeekendMultipleHoliday | B24: A1B416AA | C24: 45742.375 | D24: 45743.133 | E24: 45744.307 | F24: 45744.307 | G24: 45747.227 | H24: 45747.333 | I24: 18.2 | J24: 28.2 | K24: 0 | L24: 21.6 | M24: 2.55 | N24: 3
A25: TC24_Make_Vienna_NormalBatch_WithDefect_HolidayFallingOnWeekend | B25: B6B006AF | C25: 45740.375 | D25: 45742.762 | E25: 45747.249 | F25: 45747.249 | G25: 45747.301 | H25: 45747.333 | I25: 57.3 | J25: 59.2 | K25: 0 | L25: 1.2 | M25: 0.77 | N25: 5
A26: TC25_Make_Vienna_UrgentBatch_WithDefect_NoWeekendNoHoliday | B26: A1B671AA | C26: 45723.375 | D26: 45723.75 | F26: 45725.458 | G26: 45726.958 | H26: 45727.333 | I26: 9 | J26: Data error | K26: #VALUE! | L26: 17 | M26: 9 | N26: 2
A27: TC26_Make_Vienna_UrgentBatch_WithDefect_1WeekendNoHoliday | B27: A4B338AA | C27: 45723.344 | D27: 45723.781 | F27: 45725.493 | G27: 45726.974 | H27: 45727.347 | I27: 10.5 | J27: Data error | K27: #VALUE! | L27: 17.4 | M27: 8.95 | N27: 2
A28: TC27_Make_Vienna_UrgentlBatch_WithDefect_NoWeekend1Holiday | B28: A4B361AA | C28: 45720.385 | D28: 45720.781 | F28: 45721.451 | G28: 45723.974 | H28: 45724.347 | I28: 9.5 | J28: Data error | K28: #VALUE! | L28: 60.6 | M28: 8.95 | N28: 4
A29: TC28_Make_Vienna_UrgentlBatch_WithDefect_2orMoreWeekendNoHoliday | B29: A1B653AA | C29: 45723.375 | D29: 45723.75 | F29: 45725.458 | G29: 45726.958 | H29: 45728.333 | I29: 9 | J29: Data error | K29: #VALUE! | L29: 17 | M29: 33 | N29: 3
A30: TC29_Make_Vienna_UrgentBatch_WithDefect_NoWeekendMultipleHoliday | B30: A1B230AA | C30: 45758.375 | D30: 45758.917 | E30: 45762.019 | F30: 45762.019 | G30: 45762.302 | H30: 45762.333 | I30: 13 | J30: 26 | K30: 0 | L30: 6.8 | M30: 0.75 | N30: 2
A31: TC30_Make_Vienna_UrgentBatch_WithDefect_HolidayFallingOnWeekend | B31: A1B539AA | C31: 45761.375 | D31: 45761.706 | E31: 45761.892 | F31: 45761.892 | G31: 45762.107 | H31: 45762.333 | I31: 7.9 | J31: 4.5 | K31: 0 | L31: 5.2 | M31: 5.43 | N31: 1
A32: TC31_Make_Vienna_NormalAndUrgentBatch_WithDefect_NoWeekendNoHoliday | B32: A4B461AA | C32: 45756.375 | D32: 45756.426 | E32: 45756.516 | F32: 45762.319 | G32: 45762.481 | H32: 45762.833 | I32: 1.2 | J32: 2.2 | K32: 90.8 | L32: 3.9 | M32: 8.45 | N32: 4
A33: TC32_Make_Vienna_NormalAndUrgentBatch_WithDefect_1WeekendNoHoliday | B33: C3B100AA | C33: 45755.375 | D33: 45755.798 | E33: 45756.152 | F33: 45756.152 | G33: 45761.484 | H33: 45762.708 | I33: 10.2 | J33: 8.5 | K33: 0 | L33: 79.5 | M33: 29.37 | N33: 5
A34: TC33_Make_Vienna_NormalAndUrgentBatch_WithDefect_NoWeekend1Holiday | B34: C3B090AB | C34: 45758.375 | D34: 45760.224 | E34: 45761.637 | F34: 45761.637 | G34: 45761.833 | H34: 45762.333 | I34: -4.1 | J34: #VALUE! | K34: 0 | L34: 4.7 | M34: 11.99 | N34: 2
A35: TC34_Make_Vienna_NormalAndUrgentBatch_WithDefect_2orMoreWeekendNoHoliday | B35: B6B003AX | C35: 45755.375 | D35: 45756.003 | E35: 45762.376 | F35: 45762.376 | G35: 45762.742 | H35: 45762.75 | I35: 15.1 | J35: 104.5 | K35: 0 | L35: 8.8 | M35: 0.17 | N35: 5
A36: TC35_Make_Vienna_NormalAndUrgentBatch_WithDefect_NoWeekendMultipleHoliday | B36: C3C001AA | C36: 45754.375 | D36: 45755.162 | E36: 45755.711 | F36: 45755.711 | G36: 45756.173 | H36: 45756.333 | I36: 18.9 | J36: 13.2 | K36: 0 | L36: 11.1 | M36: 3.84 | N36: 2
A37: TC36_Make_Vienna_NormalAndUrgentBatch_WithDefect_HolidayFallingOnWeekend | B37: A1B417AA | C37: 45754.375 | D37: 45754.892 | E37: 45755.415 | F37: 45755.415 | G37: 45755.803 | H37: 45756.333 | I37: 12.4 | J37: 12.5 | K37: 0 | L37: 9.3 | M37: 12.72 | N37: 2

Sheet Platform_API_Test
A1: TestCaseName | B1: EndPoint | C1: Method | D1: Payload | E1: ExpectedStatusCode | F1: Expected Response | G1: Extracted Key
A2: TC1_ Captain_Marvel_Add_Memberships | B2: /core/user-management/graphql | C2: POST | D2: { "query": "mutation MyMutation { addMemberships(membershipRequests: {userGroupId: \"3c311c3d-b394-465e-a1db-09f9caa85ade\", userEmpId: 50065693, accessRoleId: \"6965505e-965f-4495-892f-9240ec4bc32f\"}) { accessStatus accessRoleId status membershipDetails { valueDescription dimId value } requestedByEmpId reasonDescription reasonCatgDescription actionDatetime actionByEmpId userEmpId userGroupId } }" } | E2: 200 | F2: { "data": { "addMemberships": [ { "accessStatus": "Access", "accessRoleId": "{accessRoleId}", "status": "valid", "membershipDetails": [], "reasonDescription": null, "reasonCatgDescription": null, "actionDatetime": null, "userEmpId": {userEmpId}, "userGroupId": "{userGroupId}" } ] } } | G2: accessRoleId,userEmpId,userGroupId
A3: TC2_ Captain_Marvel_Add_Memberships | B3: /core/user-management/graphql | C3: POST | D3: { "query": "mutation MyMutation { addMemberships(membershipRequests: {userGroupId: \"3c311c3d-b394-465e-a1db-09f9caa85ade\", userEmpId: 50065693, accessRoleId: \"6965505e-965f-4495-892f-9240ec4bc32f\"}) { accessStatus accessRoleId status membershipDetails { valueDescription dimId value } requestedByEmpId reasonDescription reasonCatgDescription actionDatetime actionByEmpId userEmpId userGroupId } }" } | E3: 200 | F3: { "data": { "addMemberships": [ { "accessStatus": "Access", "accessRoleId": "{accessRoleId}", "status": "invalid", "membershipDetails": [], "reasonDescription": null, "reasonCatgDescription": null, "actionDatetime": null, "userEmpId": {userEmpId}, "userGroupId": "{userGroupId}" } ] } } | G3: accessRoleId,userEmpId,userGroupId

Sheet Ship
A1: TestCaseName | B1: EndPoint | C1: Method | D1: Payload | E1: ExpectedStatusCode | F1: Expected Response | G1: Extracted Key
A2: TC_Ship_Get_Batch_details | B2: /batches/api/v1/batch-details/A4A095 | C2: GET | D2: {} | E2: 200 | F2: { "status": "Success", "data": { "batch_details": [ { "batch_number": "{batch_number}", "creation_date": null, "modified_date": null, "brand_name": "Albumin NG", "manufacture_stage": "FDP", "batch_progress": "Completed", "status": "Completed", "potency": "20.00% 50ml", "assign_to": [], "swimlane_target_date": "2023-02-28T00:00:00Z", "reason_for_delay": [], "atp_date": "2024-04-30T00:00:00Z", "swimlane": "Finishing Admin", "swimlane_start_date": null, "swimlane_end_date": null, "projected_swimlane_end_date": null, "opu": "PLASMA", "site": "VIENNA", "error_correction_date": null } ], "sku_details": [ { "sku_description": "ALB,20%,50ML,CN,HEP,ETOH25%", "sku_number": "7572571", "sku_country": "FILLED/UNLABELED", "stocking_type": "M", "brand_code": "032", "manufacture_stage_code": "FUV", "brand_description": "NHA", "order_prep_days": null, "bom_effective_date": null, "potency_desc": "20.00% 50ml", "planner_number": "210002" } ], "wo_details": [ { "work_order_number": "5480493", "work_order_status": "98", "work_order_reference_description": "{batch_number} // AFA094 PPQ Opt6", "work_order_lot_information": "PPQ EtOH Opt6", "work_order_date": "2023-01-21", "work_order_request_date": "2023-02-24", "ordered_quantity": 13690, "shipped_quantity": 13654, "work_order_type": "WO", "related_type": "", "expiry_date": "2026-01-31", "shelf_life": "1080", "suitable_for_country": null, "jde_batch_status": "", "uom_name": "EA" } ], "so_details": [ { "ship_to_location_id": "145342", "ship_to_location_name": null, "plant_name": "VN1", "sales_order_number": "50251", "line_number": 937, "quantity_shipped": 150, "ship_out_date_initially_planned": "2025-12-31", "ship_out_date": "2025-12-31T00:00:00", "line_type": "S", "storage_location": "HRL01", "ship_to_country": "conf. lot China auth. test WB" } ] } } | G2: batch_number
A3: TC_Ship_Put_invalid_error_correction_date_format | B3: /batches/api/v1/batch-details | C3: PUT | D3: { "assign_to": [ "vijayakumara.k@takeda.com" ], "swimlane_end_date": null, "swimlane": "Finishing Admin", "batch_number": "A4A095", "swimlane_start_date": null, "projected_swimlane_end_date": "null", "reason_for_delay": [], "swimlane_target_date": "string", "site": "VIENNA", "po_number": "null", "cmo_number": "null", "board_type": "ship", "date_of_manufacturing": "24-03-2023", "error_correction_date": "24-03-2023 14:00" } | E3: 400 | F3: { "detail": "Error: Invalid input parameter. Please provide correct input" }
A4: TC_Ship_Put_with_missing_batch_number | B4: /batches/api/v1/batch-details | C4: PUT | D4: { "assign_to": [ "vijayakumara.k@takeda.com" ], "swimlane_end_date": null, "swimlane": "Finishing Admin", "batch_number": "null", "swimlane_start_date": null, "projected_swimlane_end_date": "null", "reason_for_delay": [], "swimlane_target_date": "string", "site": "VIENNA", "po_number": "null", "cmo_number": "null", "board_type": "ship", "date_of_manufacturing": "24-03-2023", "error_correction_date": "24-03-2023 14:00" } | E4: 400 | F4: { "detail": "Invalid input parameter. Please provide correct input" }
A5: TC_Ship_Get_non_existent_batch_id | B5: /batches/api/v1/batch-details/INVALID123 | C5: GET | D5: {} | E5: 404 | F5: { "detail": "No records were found" }
A6: TC_Ship_Unauthorized access | B6: /batches/api/v1/batch-details/A4A095 | C6: GET | D6: {} | E6: 401 | F6: { "message": "Unauthorized" }
A7: TC_Ship_Put_Update_Assign_to_Batch_details | B7: /batches/api/v1/batch-details | C7: PUT | D7: { "assign_to": [ "vijayakumara.k@takeda.com" ], "swimlane": "Finishing Admin", "batch_number": "F2C006AH" } | E7: 200 | F7: { "status": "Data updated successfully" }
A8: TC_Ship_Validate_Assign_to_in_Batch_details | B8: /batches/api/v1/batch-details/F2C006AH | C8: GET | D8: {} | E8: 200 | F8: { "status": "Success", "data": { "batch_details": [ { "batch_number": "F2C006AH", "creation_date": null, "modified_date": null, "brand_name": "Feiba", "manufacture_stage": "FDP", "batch_progress": "Completed", "status": "Completed", "potency": "1,000.00IU", "assign_to": ["vijayakumara.k@takeda.com"], "swimlane_target_date": "2025-07-22T00:00:00Z", "reason_for_delay": [], "atp_date": "2025-12-05T00:00:00Z", "swimlane": "Finishing Admin", "swimlane_start_date": null, "swimlane_end_date": null, "projected_swimlane_end_date": null, "opu": "PLASMA", "site": "VIENNA", "error_correction_date": null } ], "sku_details": [ { "sku_description": "FEIBA,1000U,10ML", "sku_number": "6511450", "sku_country": "IRELAND", "stocking_type": "M", "brand_code": "025", "manufacture_stage_code": "FIN", "brand_description": "FNF", "order_prep_days": null, "bom_effective_date": null, "potency_desc": "1,000.00IU", "planner_number": "210000" } ], "wo_details": [ { "work_order_number": "6063666", "work_order_status": "98", "work_order_reference_description": "INVP/STKG/Reg.Muster/PH", "work_order_lot_information": "F2C006 STKG Reg. sam", "work_order_date": "2025-06-13", "work_order_request_date": "2025-07-18", "ordered_quantity": 2, "shipped_quantity": 2, "work_order_type": "WO", "related_type": "SB", "expiry_date": "2026-12-31", "shelf_life": "720", "suitable_for_country": null, "jde_batch_status": "", "uom_name": "EA" } ], "so_details": [ { "ship_to_location_id": "127644", "ship_to_location_name": "Philippines", "plant_name": "VN1", "sales_order_number": "50097", "line_number": 224, "quantity_shipped": 2, "ship_out_date_initially_planned": "2026-01-30", "ship_out_date": "2026-01-30T00:00:00", "line_type": "S", "storage_location": "HRL01", "ship_to_country": "SR Reg, samples" } ], "event_details": [] } }
A9: TC_Ship_Put_Remove_Assign_to_Batch_details | B9: /batches/api/v1/batch-details | C9: PUT | D9: { "assign_to": [], "swimlane": "Finishing Admin", "batch_number": "F2C006AH" } | E9: 200 | F9: { "status": "Data updated successfully" }
A10: TC_Ship_Verify_Smart_search_filters | B10: /core/graphql/graphql | C10: POST | D10: query MyQuery { fetchPaginatedDimensions( paginationFilters: { limit: 1000, page: 1 } dimensionIds: [1, 2, 3, 7] ) { limit page totalRecords dimensions { dimensionId name description values( limitPerDimension: 1000 version: 1 valueIds: [ "03347122-f8e2-445f-96c4-40577cbd43a4", "66faa6e5-40f1-441d-94b4-50a10e22de91", "19f11724-c488-466f-8673-5cd9428ec062" ] ) { valueId name aliases { aliasName __typename } __typename } __typename } __typename } } | E10: 200 | F10: { "data": { "fetchPaginatedDimensions": { "limit": 1000, "page": 1, "totalRecords": 4, "dimensions": [ { "dimensionId": 1, "name": "OpU", "description": "opu", "values": [ { "valueId": "03347122-f8e2-445f-96c4-40577cbd43a4", "name": "PLASMA", "aliases": [ { "aliasName": "PLASMA", "__typename": "ValueAlias" }, { "aliasName": "PLASMA OPU", "__typename": "ValueAlias" } ], "__typename": "DimensionValue" } ], "__typename": "Dimension" }, { "dimensionId": 2, "name": "Brand", "description": "brand", "values": [], "__typename": "Dimension" }, { "dimensionId": 3, "name": "Site", "description": "site", "values": [ { "valueId": "66faa6e5-40f1-441d-94b4-50a10e22de91", "name": "VIENNA", "aliases": [ { "aliasName": "VIENNA", "__typename": "ValueAlias" } ], "__typename": "DimensionValue" } ], "__typename": "Dimension" }, { "dimensionId": 7, "name": "Stage", "description": "stage", "values": [ { "valueId": "19f11724-c488-466f-8673-5cd9428ec062", "name": "Finished Drug Product", "aliases": [ { "aliasName": "FDP", "__typename": "ValueAlias" }, { "aliasName": "Finished Drug Product", "__typename": "ValueAlias" } ], "__typename": "DimensionValue" } ], "__typename": "Dimension" } ], "__typename": "PaginatedDimensions" } } }
A11: TC_Ship_Verify_Legend_details | B11: /batches/api/v2/legends?opu=PLASMA&site=VIENNA&board_type=Make&type_description= | C11: GET | D11: {} | E11: 200 | F11: { "status": "Success", "data": { "events": [ { "name": "At Risk", "mouse_hover_info": null }, { "name": "Exception Process", "mouse_hover_info": null }, { "name": "Open Deviation", "mouse_hover_info": null }, { "name": "Open Lab Investigation", "mouse_hover_info": null }, { "name": "Repacking", "mouse_hover_info": null }, { "name": "First of Code", "mouse_hover_info": "Indicates if a SKU is processed the very first time after its creation" }, { "name": "Risk Assessment", "mouse_hover_info": "Enables shipment to avoid market risk even though there is an ongoing deviation" }, { "name": "Life Saver", "mouse_hover_info": "To be processed in minimum Lead Time" }, { "name": "High Priority", "mouse_hover_info": null }, { "name": "Escalated", "mouse_hover_info": null }, { "name": "Expedited", "mouse_hover_info": null }, { "name": "GDP", "mouse_hover_info": "GDP correction loop ongoing" }, { "name": "Non Deviation Hold", "mouse_hover_info": "Hold of batch, but not due to status H nor due to deviation" }, { "name": "Tender", "mouse_hover_info": "Indicates that in case the ship-out date is missed by the site, it has to pay penalty fees due to tender contract" }, { "name": "Quarantine", "mouse_hover_info": null }, { "name": "NSSR", "mouse_hover_info": null }, { "name": "Late", "mouse_hover_info": null }, { "name": "Defect", "mouse_hover_info": null }, { "name": "SDN", "mouse_hover_info": "Supply disruption notification indicates that a country is out of stock with the respective FDP" }, { "name": "Pre-Alert", "mouse_hover_info": "Indicates that a country is below safety stock level with the respective FDP" }, { "name": "Adhoc", "mouse_hover_info": "Time between WO creation and ATP Date < tbd." }, { "name": "Exclude from Metric", "mouse_hover_info": "Exclude from Metric Computation" } ], "status": [ { "type": "atrisk", "name": "At Risk" }, { "type": "ontrack", "name": "On Track" }, { "type": "overdue", "name": "Overdue" } ] } }
A12: TC_Ship_Verify_search_results_of_Batch | B12: /batches/api/v3/batch-list?board_type=ship&opu=PLASMA&site=VIENNA&process=FINISHED%20DRUG%20PRODUCT&search=15/216AT&all_combination=false | C12: GET | D12: {} | E12: 200 | F12: { "status": "Success", "data": { "batches_data": [ { "name": "Finishing Admin", "id": 1, "info": "Owner: Admin Specialists of Finishing Operations VIE; Scope: all FDP batches that are physically packed and wait for finalization by Admin Specialists before they can be handed over to QA Finishing for review", "cardList": [ { "batch_number": "15/216AT", "batch_progress": "Completed", "creation_date": null, "modified_date": null, "brand_name": "Obizur", "manufacture_stage": "FDP", "status": "Completed", "events": [ null ], "sku_number": "1505746", "potency": "500.00IU", "jde_batch_status": "", "work_order_reference_description": "INVP/SAFETY STOCK WORLD", "sku_description": "OBIZUR,500U,SINGLE,SUBST", "assign_to": null, "atp_date": "2025-11-06T00:00:00+00:00", "swimlane_target_date": "2024-06-11T00:00:00+00:00", "ship_out_date": "2025-10-31T00:00:00", "open_tw_events": 0, "impacted_tw_events": 0, "wo_number": "5786543", "sales_order_number": "50475", "sales_order_line_number": 94, "pr_number": null, "po_number": null, "cmo_number": null, "comments_count": null, "attachments_count": null, "ship_to_location_name": null, "assignee_full_name": null } ] }, { "name": "QA Review", "id": 2, "info": "Owner: QA Finishing VIE; Scope: all FDP batches that are finalized by Admins Specialists and wait for Batch Record Review before they can be handed over to the Head of Department for approval", "cardList": [] }, { "name": "MFG Approval", "id": 3, "info": "Owner: Head of Department of Finishing Operations VIE; Scope: all FDP batches that have been reviewed by QA Finishing and wait for approval before they can be handed over to QA Finishing for final approval", "cardList": [] }, { "name": "QA Approval", "id": 4, "info": "Owner: QA Finishing VIE; Scope: all FDP batches that have been approved by Head of Department and wait for final approval before they can be handed over to FIN-Disposition", "cardList": [] }, { "name": "Ready for Disposition", "id": 55, "info": "Scope: all FDP batches that are ready for disposition", "cardList": [] } ], "pagination": { "page": 1, "limit": 100, "total_records": 1 } } }
A13: TC_Ship_Get_Brand_details | B13: /core/api/v1/filter/brands?name=ALBUMIN%20NG&limit=1 | C13: GET | D13: {} | E13: 200 | F13: { "status": "Success", "data": { "page": 1, "limit": 1, "total_records": 206, "brands": [ { "id": 87, "name": "ALBUMIN NG", "type": null, "group": null, "family": null, "trade": null, "potency": null, "ta": null, "status": null, "prog_phase": null, "strategic_growth_flg": null, "brand_img_url_desc": "/brand/Human Albumin/Human Albumin.svg" } ] }, "error": null }
A14: TC_Ship_Put_Delete_Event_Attached_Pre | B14: /batches/api/v1/events/user-attached | C14: PUT | D14: { "event_id": 45, "batch_number": "A4B174AA", "swimlane": "Finishing Admin", "user_rationale": "QA_Test", "opu": "Plasma", "site": "Vienna", "flag_type": "1" } | E14: 200 | F14: { "status": "Success", "data": { "message": "Event Risk Assessment was successfully removed." } }
... A16: TC_Ship_Get_Attached_Event | B16: /batches/api/v1/events/user-attached/A4B174AA | C16: GET | D16: {} | E16: 200 | F16: { "status": 200, "message": "success", "data": { "event_type": "USER_ATTACHED", "event_details": [ { "event_id": 45, "event_name": "Risk Assessment", "user_rationale": "acgac", "flag_type": "0" } ] } }
A17: TC_Ship_Get_Events_with_derived_type | B17: /batches/api/v2/A4B174AA/events/?event_type=derived | C17: GET | E17: 200 | F17: { "status": "Success", "data": [ { "event_type": "Derived Event", "event_details": [] } ] }

Sheet AOS
A1: TestCaseName | B1: EndPoint | C1: Method | D1: Payload | E1: ExpectedStatusCode | F1: Expected Response | G1: Extracted Key
A2: TC1_Get_Status | B2: /aos/api/v1/status/ | C2: GET | E2: 200 | F2: { "message": "OK" }
A3: TC2_Create_Board | B3: /aos/api/v2/boards/ | C3: POST | D3: { "board_owner_name": "Test", "template_name": "Tier 4 Performance", "tier_name": "TIER 1", "operating_unit_description": "BIOLOGICS", "site_description": "BROOKLYN PARK", "board_name": "Test", "board_type": "AOS", "template_ids": [ 1 ], "parent_tier2_board_id": 232, "operating_unit_id": 1, "site_id": 7, "tier_id": 1, "site_val_id": "54cc6d4c-5000-41a3-917e-30e523c53289", "opu_val_id": "acfb91c7-d08f-48dd-a0ed-98b56113b986", "func_val_id": null, "func_team_val_id": null, "tier_val_id": "e7d87d04-f7ef-46a2-a596-992f02a38c95" } | E3: 201 | F3: {"status":"Success","error":null,"data":{"board_id":"{board_id}","template_id":[1]}} | G3: board_id
A4: TC3_Create_AOS_Tier_Board_Log_Details | B4: /aos/api/v1/boards/logs/process_flow_action/ | C4: POST | D4: { "board_id":"{board_id}", "data": [ { "status": "", "topic_desc": "1234", "addtl_notes_desc": "active", "owner_name": "Prasad Ravindra Antarkar [C]", "due_date": "2026-02-26", "closed_date": null, "escalated_from": null, "escalated_to": null, "date_initiated": "2026-02-25", "initial_due_date": "2026-02-26", "log_owner_email_id": "prasad-ravindra.antarkar@takeda.com" } ] } | E4: 201 | F4: { "status": "Success", "error": null, "data": [ { "topic_desc": "1234", "log_id":"{log_id}" , "response_message": "success" } ] } | G4: log_id
A5: TC4_Get_AOS_Tier_Board_Log_Details | B5: /aos/api/v1/boards/{board_id}/logs/process_flow_action/ | C5: GET | D5: {} | E5: 200 | F5: { "status": "Success", "error": null, "data": [ { "status": "", "topic_desc": "1234", "addtl_notes_desc": "active", "escalated_from": null, "escalated_to": null, "owner_name": "Prasad Ravindra Antarkar [C]", "date_initiated": "2026-02-25", "due_date": "2026-02-26", "log_id":"{log_id}" , "closed_date": null, "audit_user_id":"LogScreen", "log_owner_email_id": "prasad-ravindra.antarkar@takeda.com", "initial_due_date": "2026-02-26" } ] }
A6: TC5_Update_AOS_Tier_Board_Action_Log | B6: /aos/api/v1/boards/logs/process_flow_action/ | C6: PUT | D6: { "board_id": "{board_id}", "data": [ { "status": "Open", "topic_desc": "1234", "addtl_notes_desc": "active", "owner_name": "Prasad Ravindra Antarkar [C]", "due_date": "2026-02-25", "closed_date": null, "is_deleted": false, "log_id": "{log_id}", "escalated_from": null, "escalated_to": null, "initial_due_date": "2026-02-26", "log_owner_email_id": "prasad-ravindra.antarkar@takeda.com" } ] } | E6: 200 | F6: { "status": "Success", "error": null, "data": [ { "topic_desc": "1234", "log_id":"{log_id}", "response_message": "updated" } ] }
A7: TC6_Get_Create_Board | B7: /aos/api/v2/boards/{board_id}/ | C7: GET | D7: {} | E7: 200 | F7: { "status": "Success", "error": null, "data": [ { "board_id": "{board_id}", "template_id": [1], "board_name": "Test", "board_owner_name": "Test", "tier_name": "TIER 1", "operating_unit_description": "BIOLOGICS" } ] }
A8: TC7_Update_Create_Board | B8: /aos/api/v2/boards/ | C8: PUT | D8: { "board_id": "{board_id}", "board_name": "Biologics- Singapore", "board_owner_name": "Vaccine Test", "opu_id": 1, "opu_description": "BIOLOGICS", "site_id": 35, "site_description": "SINGAPORE", "tier_id": 2, "tier_description": "TIER 2", "template_ids": [1,2], "parent_tier2_board_id": 327, "board_own_by_group_name": ["Lexington - 200 Shire Way", "USA - MA, Massachusetts Biologics Operations"], "meeting_frequency_description": "WEEKLY", "meeting_time": "2024-07-12 06:45:10.403", "is_deleted": false } | E8: 200 | F8: { "status": "Success", "error": null, "data": { "board_id": "{board_id}", "message": "Board updated successfully" } }
A9: TC8_Fetch_Create_Board | B9: /aos/api/v2/boards/ | C9: GET | D9: {} | E9: 200 | F9: { "status": "Success", "data": [ { "board_id": "{board_id}", "template_id": [1, 5], "board_owner_name": "test", "board_type": "AOS", "is_active": true } ] }
A10: TC9_Fetch_Board_Rules | B10: /aos/boards/{board_id}/boardRules/ | C10: GET | D10: {} | E10: 200 | F10: { "data": [ { "board_seq_num": 1, "board_rules_desc": "All board members must be present and on time unless an excused absence. When absent, a delegate is present who is responsible for providing updates" }, { "board_seq_num": 2, "board_rules_desc": "Total engagement of all team members is expected. No side conversations, texting, looking at phones, etc. For Virtual meetings, cameras on (min. facilitator of the meeting and individual presenters)" }, { "board_seq_num": 3, "board_rules_desc": "All data on board is updated prior to the meeting start." }, { "board_seq_num": 4, "board_rules_desc": "All metrics have actuals and targets. " }, { "board_seq_num": 5, "board_rules_desc": "All red metrics are connected to the Pareto and action is taken once a clear leading cause is indicated." }, { "board_seq_num": 6, "board_rules_desc": "All KPI results are trended and discussed at a minimum of monthly / weekly depending on KPI. Actions are taken for special cause variation." }, { "board_seq_num": 7, "board_rules_desc": "Each action item has an individual owner and a due date listed. If the original due date is not met, status \"Red\" is indicated." }, { "board_seq_num": 8, "board_rules_desc": "Action items can only be assigned to meeting attendees." }, { "board_seq_num": 9, "board_rules_desc": "Meetings will have a facilitator and a scribe identified ahead of meeting." } ] }
A11: TC10_Update_Board_Rules | B11: /aos/boards/boardRules/ | C11: PUT | D11: [ { "board_id": "{board_id}", "board_rules": [ { "board_seq_num": 1, "board_rules_desc": "All board members must be present and on time unless an excused absence. When absent, a delegate is present who is responsible for providing updates", "old_board_seq_num": 1, "is_deleted": false }, { "board_seq_num": 2, "board_rules_desc": "test", "old_board_seq_num": 2, "is_deleted": false }, { "board_seq_num": 3, "board_rules_desc": "test", "old_board_seq_num": 0, "is_deleted": false }, { "board_seq_num": 4, "board_rules_desc": "Total engagement of all team members is expected. No side conversations, texting, looking at phones, etc. For Virtual meetings, cameras on (min. facilitator of the meeting and individual presenters)", "old_board_seq_num": 3, "is_deleted": false }, { "board_seq_num": 5, "board_rules_desc": "All data on board is updated prior to the meeting start.", "old_board_seq_num": 4, "is_deleted": false }, { "board_seq_num": 6, "board_rules_desc": "All metrics have actuals and targets.", "old_board_seq_num": 5, "is_deleted": false }, { "board_seq_num": 7, "board_rules_desc": "All red metrics are connected to the Pareto and action is taken once a clear leading cause is indicated.", "old_board_seq_num": 6, "is_deleted": false }, { "board_seq_num": 8, "board_rules_desc": "All KPI results are trended and discussed at a minimum of monthly / weekly depending on KPI. Actions are taken for special cause variation.", "old_board_seq_num": 7, "is_deleted": false }, { "board_seq_num": 9, "board_rules_desc": "Each action item has an individual owner and a due date listed. If the original due date is not met, status \"Red\" is indicated.", "old_board_seq_num": 8, "is_deleted": false }, { "board_seq_num": 10, "board_rules_desc": "Action items can only be assigned to meeting attendees.", "old_board_seq_num": 9, "is_deleted": false }, { "board_seq_num": 11, "board_rules_desc": "Meetings will have a facilitator and a scribe identified ahead of meeting.", "old_board_seq_num": 10, "is_deleted": false } ] } ] | E11: 200 | F11: { "status": 200, "message": "OK", "data": [ { "board_id": "{board_id}", "message": "Update Successful" } ] }
A12: TC11_Get_Meeting_Agenda_Details | B12: /aos/boards/{board_id}/meetingAgenda/ | C12: GET | D12: {} | E12: 200 | F12: { "status": 200, "message": "OK", "data": [ { "board_id": "{board_id}", "agenda": [ { "agenda_seq_num": 1, "agenda_topic_desc": "Attendance - Roll Call", "alloc_time_num": 0, "lead_name": "Sample Text", "addtl_notes_desc": "Sample Text" }, { "agenda_seq_num": 2, "agenda_topic_desc": "Escalations", "alloc_time_num": 0, "lead_name": "Sample Text", "addtl_notes_desc": "Sample Text" }, { "agenda_seq_num": 3, "agenda_topic_desc": "Performance Review (Focus on Reds)", "alloc_time_num": 0, "lead_name": "Sample Text", "addtl_notes_desc": "Sample Text" }, { "agenda_seq_num": 4, "agenda_topic_desc": "Reognition", "alloc_time_num": 0, "lead_name": "Sample Text", "addtl_notes_desc": "Sample Text" }, { "agenda_seq_num": 5, "agenda_topic_desc": "CI Loop", "alloc_time_num": 0, "lead_name": "Sample Text", "addtl_notes_desc": "Sample Text" }, { "agenda_seq_num": 6, "agenda_topic_desc": "Meeting Process Confirmation", "alloc_time_num": 0, "lead_name": "Sample Text", "addtl_notes_desc": "Sample Text" }, { "agenda_seq_num": 7, "agenda_topic_desc": "Leader Process Confirmation", "alloc_time_num": 0, "lead_name": "Sample Text", "addtl_notes_desc": "Sample Text" } ] } ] }
A13: TC12_Update_Meeting_Agenda_Details | B13: /aos/boards/meetingAgenda/ | C13: PUT | D13: [ { "board_id": {board_id}, "agenda": [ { "agenda_seq_num": 1, "old_agenda_seq_num": 1, "agenda_topic_desc": "Attendance - Roll Call", "alloc_time_num": 0, "lead_name": "Sample Text", "addtl_notes_desc": "Sample Text", "is_deleted": false }, { "agenda_seq_num": 2, "old_agenda_seq_num": 2, "agenda_topic_desc": "Escalations", "alloc_time_num": 0, "lead_name": "Sample Text", "addtl_notes_desc": "Sample Text", "is_deleted": false }, { "agenda_seq_num": 3, "old_agenda_seq_num": 3, "agenda_topic_desc": "Performance Review (Focus on Reds)", "alloc_time_num": 0, "lead_name": "Sample Text", "addtl_notes_desc": "Sample Text", "is_deleted": false }, { "agenda_seq_num": 4, "old_agenda_seq_num": 4, "agenda_topic_desc": "Reognition", "alloc_time_num": 0, "lead_name": "Sample Text", "addtl_notes_desc": "Sample Text", "is_deleted": false }, { "agenda_seq_num": 5, "old_agenda_seq_num": 5, "agenda_topic_desc": "CI Loop", "alloc_time_num": 0, "lead_name": "Sample Text", "addtl_notes_desc": "Sample Text", "is_deleted": false }, { "agenda_seq_num": 6, "old_agenda_seq_num": 6, "agenda_topic_desc": "Meeting Process Confirmation", "alloc_time_num": 0, "lead_name": "Sample Text", "addtl_notes_desc": "Sample Text", "is_deleted": false }, { "agenda_seq_num": 7, "old_agenda_seq_num": 7, "agenda_topic_desc": "Leader Process Confirmation", "alloc_time_num": 0, "lead_name": "Sample Text", "addtl_notes_desc": "Sample Text", "is_deleted": false } ] } ] | E13: 200 | F13: { "status": 200, "message": "OK", "data": [ { "board_id": "{board_id}", "message": "Update Successful" } ] }
A14: TC13_Get_Attendance_Log | B14: /aos/boards/{board_id}/attendanceLog/ | C14: GET | D14: {} | E14: 200 | F14: { "status": 200, "message": "OK", "data": [ { "attendee_name": "Prasad Ravindra Antarkar [C]", "job_func_desc": "Sample", "attendee_link_id": 1, "attend_by_email_id": "prasad-ravindra.antarkar@takeda.com", "meeting_dates": [ { "meet_date": "03-17-2026", "avail_stat_cd": "", "attendance_id": 1388 } ] } ] }

Sheet DQH
A1: TestCaseName | B1: EndPoint | C1: Method | D1: Payload | E1: ExpectedStatusCode | F1: Expected Response | G1: Extracted Key
A2: TC_DQH_Get_DPM_details | B2: dqh/graphql | C2: POST | D2: query MyQuery { fetchDataPipeline(dataPipelineJobsInput: {paginationInfo: {limit: 2, page: 2}}) { page limit totalCount data { url } } } | E2: 200 | F2: { "data": { "fetchDataPipeline": { "page": 2, "limit": 2, "totalCount": 49, "data": [ { "url": "https://onetakeda-usdev-gmsgq.cloud.databricks.com/pipelines/9fa12738-c72a-490e-b2a1-c691f13372a7/updates/abffb8e1-9df9-40f1-a6f6-46313c91cc94?o=55286904982311" }, { "url": "https://onetakeda-usdev-gmsgq.cloud.databricks.com/pipelines/26ce6053-9e4e-4f67-b26b-98844918663a/updates/fb0b8f0b-fc85-4c37-a26b-4f227aabd864?o=55286904982779" } ] } } }
A3: TC_DQH_Get_DTM_details | B3: dqh/graphql | C3: POST | D3: query MyQuery { fetchDataTableMonitor( dataTableMonitorsInput: {paginationInfo: {limit: 2, page: 2}} ) { page limit totalCount } } | E3: 200 | F3: { "data": { "fetchDataTableMonitor": { "page": 2, "limit": 2, "totalCount": 7133 } } }

Sheet Test
A1: TestCaseName | B1: EndPoint | C1: Method | D1: Payload | E1: ExpectedStatusCode | F1: Expected Response | G1: Extracted Key
A2: TC_fetchMaterialProductRegions_single_MaterialID | B2: /coa/graphql/graphql | C2: POST | D2: query MyQuery { fetchMaterialProductRegions(materialIds: ["6510186"]) { materialId productSpecificationCode productSpecificationRegions } } | E2: 200 | F2: { "data": { "fetchMaterialProductRegions": [ { "materialId": "6510186", "productSpecificationCode": "MB_ELAPRASE_DP_V", "productSpecificationRegions": [ "GLOBAL", "REGION3", "REGION4", "REGION1", "REGION5", "REGION2" ] } ] } }
A3: TC_fetchMaterialProductRegions_multiple_MaterialIDs | B3: /coa/graphql/graphql | C3: POST | D3: query MyQuery { fetchMaterialProductRegions(materialIds: ["6000576", "7000022-007", "7001727"]) { materialId productSpecificationCode productSpecificationRegions } } | E3: 200 | F3: { "data": { "fetchMaterialProductRegions": [ { "materialId": "6000576", "productSpecificationCode": "MB_LANA_SHP643_DP_150_S", "productSpecificationRegions": [ "GLOBAL_CL" ] }, { "materialId": "7000022-007", "productSpecificationCode": "MB_REPLAGAL_AF_DP", "productSpecificationRegions": [ "REGION4", "REGION2", "REGION3", "REGION1", "GLOBAL", "MB_SWFI_GATTEX_DP_V" ] }, { "materialId": "7001727", "productSpecificationCode": "MB_LANA_TAK743_DP_300_S", "productSpecificationRegions": [ "GLOBAL", "REGION8", "REGION10", "REGION7", "REGION4", "REGION9", "REGION5", "REGION6", "REGION1", "REGION2" ] } ] } }
A4: TC_fetchMaterialProductRegions_null_MaterialID | B4: /coa/graphql/graphql | C4: POST | D4: query MyQuery { fetchMaterialProductRegions(materialIds: []) { materialId productSpecificationCode productSpecificationRegions } } | E4: 200 | F4: { "data": { "fetchMaterialProductRegions": [] } }
A5: TC_fetchMaterialProductRegions_invalid_MaterialID | B5: /coa/graphql/graphql | C5: POST | D5: query MyQuery { fetchMaterialProductRegions(materialIds: ["123"]) { materialId productSpecificationRegions productSpecificationCode } } | E5: 200 | F5: { "data": { "fetchMaterialProductRegions": [ { "materialId": "123", "productSpecificationRegions": null, "productSpecificationCode": null } ] } }
A6: TC_fetchMaterialProductRegions_mismatch_MaterialID | B6: /coa/graphql/graphql | C6: POST | D6: query MyQuery { fetchMaterialProductRegions(materialIds: [""]) { materialId productSpecificationRegions productSpecificationCode } } | E6: 200 | F6: { "data": { "fetchMaterialProductRegions": [ { "materialId": "", "productSpecificationRegions": null, "productSpecificationCode": null } ] } }
A7: TC_assign_single_Assignee | B7: /batches/api/v1/external-batch-details | C7: PUT | D7: { "po_number": "4501742936", "assign_to": ["vijayakumara.k@takeda.com"], "batch_number": "", "cmo_number": "", "date_of_manufacturing": "" } | E7: 200 | F7: { "status": "Data updated successfully" }
A8: TC_validate_single_assignee_details | B8: /batches/api/v1/external-batch-details/?batch_id=null&po_id=4501742936&cmo_id=null | C8: GET | D8: {} | E8: 200 | F8: { "status": "Success", "data": { "batch_details": [ { "batch_id": null, "cmo_number": null, "po_number": "4501742936", "batch_stat_id": "12", "batch_progress_id": "8", "board_type_desc": "TEST", "prod_brand_desc": "VEDOLIZUMAB", "site_desc": "EXTERNAL BIO", "opu_desc": "BIOLOGICS", "mfg_stg_cd": "DS", "swimlane_id": "41", "swimlane_strt_dts": null, "swimlane_end_dts": null, "swimlane_tgt_dts": null, "po_mfg_dts": null, "batch_expire_dt": null, "swimlane_delay_rsn_desc": null, "assign_to_user_id": [ "vijayakumara.k@takeda.com" ], "external_batch_id": null, "usage_decision_date": null } ], "po_details": [ { "batch_id": null, "po_number": "4501742936", "po_item_num": "000010", "po_doc_crt_dt": "2023-09-22", "mat_id": "6502654", "mfg_site_desc": "AbbVie Bioresearch Center Inc.", "potency_desc": "1" } ], "process_schedule_summary": { "test_locations": "AbbVie Bioresearch,Catalent Kansas City,Linz", "start_date_planned": null, "start_date_actual": null, "start_date_predicted": null, "end_date_planned": null, "end_date_actual": null, "end_date_predicted": null } } }
A9: TC_assign_multiple_Assignees | B9: /batches/api/v1/external-batch-details | C9: PUT | D9: { "po_number": "4501742936", "assign_to": [ "vijayakumara.k@takeda.com", "pallavi-ashok.yadav@takeda.com", "jyothsna.j-h@takeda.com" ], "batch_number": "", "cmo_number": "", "date_of_manufacturing": "" } | E9: 200 | F9: { "status": "Data updated successfully" }
A10: TC_validate_multiple_assignee_details | B10: /batches/api/v1/external-batch-details/?batch_id=null&po_id=4501742936&cmo_id=null | C10: GET | D10: {} | E10: 200 | F10: { "status": "Success", "data": { "batch_details": [ { "batch_id": null, "cmo_number": null, "po_number": "4501742936", "batch_stat_id": "12", "batch_progress_id": "8", "board_type_desc": "TEST", "prod_brand_desc": "VEDOLIZUMAB", "site_desc": "EXTERNAL BIO", "opu_desc": "BIOLOGICS", "mfg_stg_cd": "DS", "swimlane_id": "41", "swimlane_strt_dts": null, "swimlane_end_dts": null, "swimlane_tgt_dts": null, "po_mfg_dts": null, "batch_expire_dt": null, "swimlane_delay_rsn_desc": null, "assign_to_user_id": [ "jyothsna.j-h@takeda.com", "pallavi-ashok.yadav@takeda.com", "vijayakumara.k@takeda.com" ], "external_batch_id": null, "usage_decision_date": null } ], "po_details": [ { "batch_id": null, "po_number": "4501742936", "po_item_num": "000010", "po_doc_crt_dt": "2023-09-22", "mat_id": "6502654", "mfg_site_desc": "AbbVie Bioresearch Center Inc.", "potency_desc": "1" } ], "process_schedule_summary": { "test_locations": "AbbVie Bioresearch,Catalent Kansas City,Linz", "start_date_planned": null, "start_date_actual": null, "start_date_predicted": null, "end_date_planned": null, "end_date_actual": null, "end_date_predicted": null } } }
A11: TC_Unassign_assignee | B11: /batches/api/v1/external-batch-details | C11: PUT | D11: { "po_number": "4501742936", "assign_to": [], "batch_number": "", "cmo_number": "", "date_of_manufacturing": "" } | E11: 200 | F11: { "status": "Data updated successfully" }
A12: TC_FetchCOAStatus | B12: /coa/graphql/graphql | C12: POST | D12: query MyQuery { fetchCoaStatus { id status } } | E12: 200 | F12: { "data": { "fetchCoaStatus": [ { "id": 1, "status": "Uploaded" }, { "id": 2, "status": "Pending_general_Info" }, { "id": 3, "status": "Pending_test_info" }, { "id": 4, "status": "Pending_e-verification" }, { "id": 5, "status": "Pending_email_verification" }, { "id": 6, "status": "Verified" } ] } }
A13: TC_fetchProductSpecification_with_multple_params | B13: /coa/graphql/graphql | C13: POST | D13: query MyQuery { fetchProductSpecification( prodSpecInput: {productSpecificationCode: "MB_LANA_SHP643_DS", analysisCode: "MB_RENTSCHLER_HCP2"} ) { analysisCode componentName maxValue minValue productSpecificationCode regionDescription ruleDescription textValue } } | E13: 200 | F13: { "data": { "fetchProductSpecification": [ { "analysisCode": "MB_RENTSCHLER_HCP2", "componentName": "Host Cell Protein", "maxValue": 10.0, "minValue": 0.0, "productSpecificationCode": "MB_LANA_SHP643_DS", "regionDescription": "GLOBAL", "ruleDescription": "Result <= MAX", "textValue": null }, { "analysisCode": "MB_RENTSCHLER_HCP2", "componentName": "Host Cell Protein", "maxValue": 10.0, "minValue": 0.0, "productSpecificationCode": "MB_LANA_SHP643_DS", "regionDescription": "REGION3", "ruleDescription": "Result <= MAX", "textValue": null }, { "analysisCode": "MB_RENTSCHLER_HCP2", "componentName": "Host Cell Protein", "maxValue": 10.0, "minValue": 0.0, "productSpecificationCode": "MB_LANA_SHP643_DS", "regionDescription": "REGION4", "ruleDescription": "Result <= MAX", "textValue": null }, { "analysisCode": "MB_RENTSCHLER_HCP2", "componentName": "Host Cell Protein", "maxValue": 10.0, "minValue": 0.0, "productSpecificationCode": "MB_LANA_SHP643_DS", "regionDescription": "REGION7", "ruleDescription": "Result <= MAX", "textValue": null }, { "analysisCode": "MB_RENTSCHLER_HCP2", "componentName": "Host Cell Protein", "maxValue": 10.0, "minValue": 0.0, "productSpecificationCode": "MB_LANA_SHP643_DS", "regionDescription": "REGION8", "ruleDescription": "Result <= MAX", "textValue": null } ] } }
... A32: TC_fetchMaterialProductSpecifications_with_mismatch_MaterialID | B32: /coa/graphql/graphql | C32: POST | D32: query MyQuery { fetchMaterialProductSpecifications(materialIds: ["MB_GATTEX_DS_B"]) { productSpecificationCode materialId } } | E32: 200 | F32: { "data": { "fetchMaterialProductSpecifications": [] } }
A33: TC_Batches_Pagination_limit_100 | B33: /batches/api/v1/external-batch-list?opu=BIOLOGICS&site=EXTERNAL%20BIO&process=Drug%20Product|Drug%20Substance&boardType=Test&page=1&limit=120 | C33: GET | D33: {} | E33: 200 | F33: { "status": "Success", "data": { "pagination": { "page": 1, "limit": 100, "total_records": "{total_records}" } } } | G33: total_records
A34: TC_Batches_Pagination_limit_120 | B34: /batches/api/v1/external-batch-list?opu=BIOLOGICS&site=EXTERNAL%20BIO&process=Drug%20Product|Drug%20Substance&boardType=Test&page=1&limit=120 | C34: GET | D34: {} | E34: 200 | F34: { "status": "Success", "data": { "pagination": { "page": 1, "limit": 100, "total_records": "{total_records}" } } } | G34: total_records
A35: TC_Batches_Pagination_limit_0 | B35: /batches/api/v1/external-batch-list?opu=BIOLOGICS&site=EXTERNAL%20BIO&process=Drug%20Product|Drug%20Substance&boardType=Test&page=1&limit=0 | C35: GET | D35: {} | E35: 404 | F35: { "detail": "Error: Record not found" }
A36: TC_Batches_Pagination_limit_invalid_combination | B36: /batches/api/v1/external-batch-list?site=EXTERNAL%20BIO&process=Drug%20Product|Drug%20Substance&boardType=Test&page=1&limit=10 | C36: GET | D36: {} | E36: 404 | F36: { "detail": "Error: Record not found" }
A37: TC_Batches_Pagination_limit_invalid_request | B37: https://api-insights-dev2.takeda.io/batches/api/v1/external-batch-list?board_type=test&opu=Plasma|Biologics&site=Vienna|Madrid&process=Drug Substance|Finished Drug Product|Master Cell Stock&brand=Albumin NG|Alofisel&page=1&limit=100&events=Tender|CPA&status=Completed|On Track&potency=Blank - Sales Rpt Code 541/S5 | C37: GET | D37: {} | E37: 400 | F37: { "detail": "Invalid input parameter. Please provide correct input" }
A38: TC_Board_type_equal_to_random_value | B38: /batches/api/v1/filters?board_type=avhkad | C38: GET | D38: {} | E38: 400 | F38: { "detail": "Error: Board name is not correct" }
A39: TC_Board_type_equal_to_string_value | B39: /batches/api/v1/filters?board_type="Test" | C39: GET | D39: {} | E39: 400 | F39: { "detail": "Error: Board name is not correct" }
A40: TC_Board_type_equal_to_Test_value | B40: /batches/api/v1/filters?board_type=Test | C40: GET | D40: {} | E40: 200 | F40: { "status": "Success", "data": { "events": [ "At Risk", "Biz Decision Delay", "Escalated", "Expedited", "Lab Assessment", "Low Priority", "Open Change Control", "Open Deviation", "Open Lab Investigation", "Rejected" ], "status": [ "Batch Overdue", "Incoming Due Date", "On Track" ], "brands": [], "potency": [ "1", "25", "75", "6", "108", "1,25", "10", "", "50", "400", "150", "300" ], "ship_to_locations": [], "jde_batch_status": [] } }
A41: TC_fetchTestByLab_single_batchid_without_other_params | B41: /coa/graphql/graphql | C41: POST | D41: query MyQuery { fetchTestByLab( batchinput: [{batchId: "B189-041060", stdSiteName: "Lonza Hayward"}] ) { batchId stdSiteName batch { batchId mfgDate productName } testresult { testName testMethod testDate testedFor testResultDesc testResultState verificationDate verifiedBy lab { labsiteName } } } } | E41: 200 | F41: { "data": { "fetchTestByLab": [ { "batchId": "B189-041060", "stdSiteName": "Lonza Hayward", "batch": [ { "batchId": "B189-041060", "mfgDate": "2021-08-11", "productName": "rFurin" } ], "testresult": [ { "testName": "Appearance", "testMethod": "USHA-427", "testDate": "{testDate}", "testedFor": null, "testResultDesc": "Clear, colorless solution,\nabsence of particles", "testResultState": null, "verificationDate": "{verificationDate}", "verifiedBy": "Katharina Riedler", "lab": { "labsiteName": "Lonza" } } ] } ] } } | G41: testDate,verificationDate
A42: TC_fetchTestByLab_single_batchid_with_other_params | B42: /coa/graphql/graphql | C42: POST | D42: query MyQuery { fetchTestByLab( batchinput: [{batchId: "B189-041060", stdSiteName: "Lonza Hayward"}] ) { batchId stdSiteName batch { batchId mfgDate productName } testresult { testName testMethod testDate testedFor testResultDesc testResultState verificationDate verifiedBy lab { labsiteName } } } } | E42: 200 | F42: { "data": { "fetchTestByLab": [ { "batchId": "B189-041060", "stdSiteName": "Lonza Hayward", "batch": [ { "batchId": "B189-041060", "mfgDate": "2021-08-11", "productName": "rFurin" } ], "testresult": [ { "testName": "Appearance", "testMethod": "USHA-427", "testDate": "{testDate}", "testedFor": null, "testResultDesc": "Clear, colorless solution,\nabsence of particles", "testResultState": null, "verificationDate": "{verificationDate}", "verifiedBy": "Katharina Riedler", "lab": { "labsiteName": "Lonza" } } ] } ] } } | G42: testDate,verificationDate
A43: TC_fetchTestByLab_multiple_batchid_and_stdSiteName | B43: /coa/graphql/graphql | C43: POST | D43: query MyQuery { fetchTestByLab( batchinput: [{batchId: "B189-041060", stdSiteName: "Lonza Hayward"}, { batchId: "A2100006", stdSiteName: "JHS" } { batchId: "520830", stdSiteName: "AbbVie Bioresearch" } ] ) { batchId stdSiteName batch { batchId mfgDate productName } testresult { testName testMethod testDate testedFor testResultDesc testResultState verificationDate verifiedBy lab { labsiteName } } } } | E43: 200 | F43: { "data": { "fetchTestByLab": [ { "batchId": "B189-041060", "stdSiteName": "Lonza Hayward", "batch": [ { "batchId": "B189-041060", "mfgDate": "2021-08-11", "productName": "rFurin" } ], "testresult": [ { "testName": "Appearance", "testMethod": "USHA-427", "testedFor": null, "testResultDesc": "Clear, colorless solution,\nabsence of particles", "testResultState": null, "verificationDate": "{verificationDate}", "verifiedBy": "Katharina Riedler", "lab": { "labsiteName": "Lonza" } } ] }, { "batchId": "A2100006", "stdSiteName": "JHS", "batch": [ { "batchId": "A2100006", "mfgDate": "2021-02-11", "productName": "KALBITOR 10MG∕ML DYX" } ], "testresult": [ { "testName": "Particulate Matter >= 10\nμm", "testMethod": "SOP 402.60", "testedFor": null, "testResultDesc": "39 Particles", "testResultState": null, "verificationDate": "{verificationDate}", "verifiedBy": "Katharina Riedler", "lab": { "labsiteName": "Jubilant HollisterStier LLC" } } ] }, { "batchId": "520830", "stdSiteName": "AbbVie Bioresearch", "batch": [ { "batchId": "520830", "mfgDate": "2021-12-29", "productName": "Vedolizumab Bulk Drug Substance" } ], "testresult": [ { "testName": "A280", "testMethod": "QCA-416", "testedFor": "Takeda Pharmaceuticals International. Inc.", "testResultDesc": "96.4 mg/mL", "testResultState": null, "verificationDate": "{verificationDate}", "verifiedBy": "Katharina Riedler", "lab": { "labsiteName": "AbbVie Bioresearch Center" } } ] } ] } } | G43: testDate,verificationDate
A44: TC_fetchTestByLab_invalid_batchid_and_stdSiteName | B44: /coa/graphql/graphql | C44: POST | D44: query MyQuery { fetchTestByLab( batchinput: [{batchId: "cjasvcha", stdSiteName: "cjCKVS"} ] ) { batchId stdSiteName batch { batchId mfgDate productName } testresult { testName testMethod testDate testedFor testResultDesc testResultState verificationDate verifiedBy lab { labsiteName } } } } | E44: 200 | F44: { "data": { "fetchTestByLab": [ { "batchId": "cjasvcha", "stdSiteName": "cjCKVS", "batch": null, "testresult": [] } ] } }
A45: TC_fetchTestByLab_missing_batchid_or_stdSiteName | B45: /coa/graphql/graphql | C45: POST | D45: query MyQuery { fetchTestByLab( batchinput: [{batchId: " ", stdSiteName: "Lonza Hayward"} ] ) { batchId stdSiteName batch { batchId mfgDate productName } testresult { testName testMethod testDate testedFor testResultDesc testResultState verificationDate verifiedBy lab { labsiteName } } } } | E45: 200 | F45: { "data": null, "errors": [ { "message": "Error: Field not found in the request", "locations": [ { "line": 2, "column": 3 } ], "path": [ "fetchTestByLab" ] } ] }

Sheet Disposition
A1: TestCaseName | B1: EndPoint | C1: Method | D1: Payload | E1: ExpectedStatusCode | F1: Expected Response | G1: Extracted Key
A2: TC1_Disposition_Verify_batch_details_retrieval | B2: /batches/api/v1/disposition-batch-details/A1A068AC/VN1/FIN | C2: GET | D2: {} | E2: 200 | F2: { "status": "Success" } | G2: ""
A3: TC2_Disposition_Verify_user_assigned_to_batch | B3: /batches/api/v1/disposition-batch-details | C3: PUT | D3: { "site_id": "VN1", "batch_id": "ALA0003", "disposition_group": "BLK", "assigned_users": [ "archana.r@takeda.com" ] } | E3: 200 | F3: { "status": "Success", "data": { "message": "Disposition batch details updated successfully" } } | G3: ""
A4: TC3_Disposition_Verify_user_removed_from_batch | B4: /batches/api/v1/disposition-batch-assigned-users/ALA0003 | C4: DELETE | D4: { "site_id": "VN1", "disposition_group": "BLK", "assigned_users": [ "archana.r@takeda.com" ] } | E4: 200 | F4: { "status": "Success", "data": { "message": "Users from Disposition batch details removed successfully" } } | G4: ""
A5: TC4_Disposition_Verify_disposition_filters | B5: /batches/api/v1/process/disposition/filters | C5: POST | D5: {"page":1,"limit":10,"filters":["batch_id","material_id","batch_short_code"]} | E5: 200 | F5: { "status": "Success" } | G5: ""
A6: TC5_Disposition_Verify_disposition_batch_automated_checks | B6: /batches/api/v1/checklist-item-state/A1A068AC?item_type=automated | C6: GET | D6: {} | E6: 200 | F6: { "status": "Success" } | G6: ""

Sheet tech_transfer
A1: TestCaseName | B1: EndPoint | C1: Method | D1: Payload | E1: ExpectedStatusCode | F1: Expected Response | G1: Extracted Key
A2: TC1_techTransfer_verify_fetch_process_quality_details | B2: /process-quality/graphql | C2: POST | D2: query MyQuery { fetch_process_quality_details( param_value: {manufacturing_stage: "Drug Substance", clinical_code: "TAK-279", site_name: "Cambrex Charles City"} ) { clinical_code data_source load_time_stamp manufacturing_stage opu process_id process_name site ... on TechTransfer { process_id process_name clinical_code data_source load_time_stamp manufacturing_stage opu project_id receiving_unit sending_unit site user_name sub_process { input_output_yield_percentage operation_unit stage batch_volume { maximum_volume minimum_volume process_volume_range stage_name } equipments { equipment_code equipment_id equipment_name equipment_type material_of_construction } solubility { material_name solubility_description solubility_value solvent_name } stability { details { peak_id stability_attributes { comment_description parameter_name parameter_value uom_description } } solution_name } } workspace_id workspace_name } } } | E2: 200 | F2: {"data":{"fetch_process_quality_details":{"clinical_code":"TAK-279","data_source":"Sphera Stature","load_time_stamp":"2026-03-23T20:03:41.762+00:00","manufacturing_stage":"Drug Substance","opu":["SMALL MOLECULES & ONCOLOGY"],"process_id":"1000093014","process_name":"TAK-279 QbD RM_DRAFT_10-10-2025_1","site":["Cambrex Charles City"],"project_id":null,"receiving_unit":null,"sending_unit":null,"user_name":null,"sub_process":[{"stage":"Step 3","batch_volume":[{"maximum_volume":"1353 gallons / 5122 L","minimum_volume":"198 gallons/ 750 L","stage_name":"Step 3"}],"equipments":[{"equipment_code":"T-4562","equipment_id":1027902455,"equipment_name":"7000 Gallon Tank","equipment_type":"Tank"}],"solubility":[{"material_name":"TR06854013","solubility_description":"Soluble at RT","solvent_name":"DMF"}],"stability":[{"solution_name":"THF","details":[{"peak_id":"HMPL-013-I","stability_attributes":[{"parameter_name":"4 h reflux","parameter_value":"ND","uom_description":"%Area"}]}]}]}]}}}
A3: TC2_techTransfer_verify_fetch_sub_process_details | B3: /process-quality/graphql | C3: POST | D3: query MyQuery { fetch_sub_process_details( param_values: {stage: "Stage 1", clinical_code: "TAK-279", site_name: "Cambrex Charles City", manufacturing_stage: "Drug Substance"} ) { input_output_yield_percentage operation_unit stage solubility { material_name } stability { solution_name details { peak_id stability_attributes { parameter_name } } } batch_volume { maximum_volume stage_name } equipments { equipment_code material_of_construction } } } | E3: 200 | F3: {"data":{"fetch_sub_process_details":[{"stage":"Step 3","solubility":[{"material_name":"TR06854013"}],"stability":[{"solution_name":"THF","details":[{"peak_id":"HMPL-013-I","stability_attributes":[{"parameter_name":"4 h reflux"}]}]}],"batch_volume":[{"maximum_volume":"1353 gallons / 5122 L","stage_name":"Step 3"}],"equipments":[{"equipment_code":"T-4562","material_of_construction":null}]},{"stage":"Step 1","solubility":[{"material_name":"TR06803253"}],"stability":[{"solution_name":"Acetone","details":[{"peak_id":"RRT ~ 1.24","stability_attributes":[{"parameter_name":"RT"}]}]}],"batch_volume":[{"maximum_volume":"997 gallons / 3774 L","stage_name":"Step 1"}],"equipments":[{"equipment_code":"R-3146","material_of_construction":null}]}]}}
A4: TC3_techTransfer_verify_fetch_tech_transfer_details | B4: /process-quality/graphql | C4: POST | D4: query MyQuery { fetch_tech_transfer_details { clinical_code data_source load_time_stamp manufacturing_stage opu process_id process_name project_id receiving_unit sending_unit site user_name sub_process { input_output_yield_percentage operation_unit stage solubility { material_name solubility_description solubility_value solvent_name } batch_volume { maximum_volume minimum_volume process_volume_range stage_name } equipments { equipment_code equipment_id equipment_name equipment_type material_of_construction } stability { details { peak_id stability_attributes { comment_description parameter_name parameter_value uom_description } } solution_name } } workspace_id workspace_name } } | E4: 200 | F4: {"data":{"fetch_tech_transfer_details":[{"clinical_code":"TAK-279","manufacturing_stage":"Drug Substance","opu":["SMALL MOLECULES AND ONCOLOGY"],"project_id":1056750,"receiving_unit":"Grange Castle","sending_unit":"Cambrex Charles City","sub_process":[{"stage":"Step 3","batch_volume":[{"maximum_volume":"1353 gallons / 5122 L","minimum_volume":"198 gallons/ 750 L","stage_name":"Step 3"}],"equipments":[{"equipment_code":"T-4562","equipment_id":1027902455,"equipment_name":"7000 Gallon Tank","equipment_type":"Tank","material_of_construction":null},{"equipment_code":"R-4554","equipment_id":1027900358,"equipment_name":"4000 Gallon Reactor","equipment_type":"Reactor","material_of_construction":null}]},{"stage":"Step 1","batch_volume":[{"maximum_volume":"997 gallons / 3774 L","stage_name":"Step 1"}],"equipments":[{"equipment_code":"R-3146","equipment_name":"2000 Gallon Reactor","equipment_type":"Reactor","material_of_construction":null}]}]}]}}
